{
  "date": "2026-07-17",
  "overview": "今日热点聚焦于世界杯决赛对阵（阿根廷对阵西班牙）及极端高温天气。A股市场波动加剧，巴菲特警告市场已成“赌场”，韩国股市遭遇黑色星期四。社会新闻方面，多地发生治安事件及自然灾害，引发公众关注。科技领域，realme暂停中国业务，小鹏发布新车型。国际局势方面，俄方不承认南海仲裁案，美日菲关系及地缘政治紧张局势持续发酵。",
  "topics": [
    {
      "title": "世界杯决赛：阿根廷对阵西班牙",
      "summary": "世界杯决赛对阵已确定，阿根廷在半决赛中击败英格兰，西班牙击败法国，双方将争夺大力神杯，冠军奖金创历史新高。",
      "entryIndices": [
        3,
        30,
        31,
        39,
        60,
        63,
        71,
        72,
        89,
        90,
        119,
        133,
        161,
        171,
        193,
        220,
        226,
        227,
        243
      ],
      "sources": [
        "baidu-hot",
        "douyin-hot",
        "kuaishou-hot",
        "toutiao-search",
        "weibo-search"
      ]
    },
    {
      "title": "俄方不承认南海仲裁案合法性",
      "summary": "俄罗斯科学家及中方学者发声，驳斥南海仲裁案裁决，强调中国现在是世界第一，并指出菲律宾相关报告的谬误。",
      "entryIndices": [
        1,
        16,
        21,
        169,
        170
      ],
      "sources": [
        "toutiao-search",
        "baidu-hot",
        "kuaishou-hot"
      ]
    },
    {
      "title": "中国多地遭遇极端高温",
      "summary": "中国多地气温创历史新高，气象台回应40℃预报，三伏天已至，多地发布高温预警，引发公众对极端天气的关注。",
      "entryIndices": [
        7,
        8,
        17,
        101,
        121,
        137,
        163,
        205,
        231,
        297
      ],
      "sources": [
        "weibo-search",
        "baidu-hot",
        "kuaishou-hot",
        "toutiao-search"
      ]
    },
    {
      "title": "A股市场波动与巴菲特警告",
      "summary": "巴菲特警告市场已成“赌场”，韩国股市遭遇黑色星期四，A股板块出现分化，科技基金近一月亏损。",
      "entryIndices": [
        11,
        28,
        52,
        61,
        82,
        102,
        108,
        185,
        245,
        296
      ],
      "sources": [
        "toutiao-search",
        "zhihu-search",
        "baidu-hot",
        "weibo-search"
      ]
    },
    {
      "title": "电竞与乒乓球赛事",
      "summary": "BLG战胜T1晋级EWC淘汰赛，马龙许昕晋级男双16强，DYG与TTG展开激烈对决。",
      "entryIndices": [
        24,
        35,
        67,
        81,
        225,
        237,
        275,
        280,
        295
      ],
      "sources": [
        "douyin-hot",
        "baidu-hot",
        "weibo-search"
      ]
    },
    {
      "title": "社会治安与公共安全事件",
      "summary": "多地发生女子当街殴打老人、男子杀妻、民警为护群众牺牲等恶性或悲剧事件，引发社会广泛关注。",
      "entryIndices": [
        26,
        42,
        106,
        125,
        180,
        206,
        211,
        233
      ],
      "sources": [
        "kuaishou-hot",
        "toutiao-search",
        "baidu-hot",
        "weibo-search"
      ]
    },
    {
      "title": "科技与汽车行业动态",
      "summary": "realme暂停中国业务，小鹏MONA L03发布，AI产品即将亮相，台积电Q2净利润创新高。",
      "entryIndices": [
        12,
        15,
        40,
        46,
        49,
        124,
        131,
        149,
        194,
        248,
        271,
        286
      ],
      "sources": [
        "weibo-search",
        "kuaishou-hot",
        "baidu-hot",
        "toutiao-search"
      ]
    },
    {
      "title": "娱乐圈动态与名人离世",
      "summary": "西游记演员史崇仁、TVB演员梁爱在离世，张小斐成首位票房破百亿85花，薛之谦发布新单曲，杨紫启动法律维权。",
      "entryIndices": [
        0,
        18,
        37,
        44,
        50,
        65,
        71,
        94,
        100,
        103,
        130,
        136,
        150,
        152,
        202,
        213,
        236,
        246,
        263,
        264,
        268,
        288,
        294
      ],
      "sources": [
        "kuaishou-hot",
        "baidu-hot",
        "toutiao-search",
        "weibo-search",
        "douyin-hot"
      ]
    },
    {
      "title": "国际局势与突发事件",
      "summary": "美国考虑突袭古巴，日本图谋将菲律宾打造成桥头堡，德国主持人辱华引发众怒，小马科斯被指把菲律宾推进火坑。",
      "entryIndices": [
        68,
        120,
        139,
        157,
        235,
        266
      ],
      "sources": [
        "toutiao-search",
        "baidu-hot",
        "weibo-search"
      ]
    },
    {
      "title": "自然灾害与灾后恢复",
      "summary": "中国进入防汛关键期，云南、贵州、广西等地遭遇暴雨、冰雹及毒气事件，四川发生车辆坠崖事故。",
      "entryIndices": [
        10,
        27,
        43,
        83,
        112,
        123,
        134,
        153,
        174,
        178,
        201,
        233,
        234,
        278,
        292
      ],
      "sources": [
        "kuaishou-hot",
        "toutiao-search",
        "baidu-hot",
        "weibo-search"
      ]
    },
    {
      "title": "健康与生活方式趋势",
      "summary": "饮料市场出现反常现象，三伏天养生话题热度高，疥疮爆发，茉莉花价格创新高，假性食欲引发讨论。",
      "entryIndices": [
        4,
        6,
        17,
        59,
        84,
        98,
        99,
        109,
        159,
        217,
        242
      ],
      "sources": [
        "douyin-hot",
        "toutiao-search",
        "baidu-hot",
        "weibo-search"
      ]
    },
    {
      "title": "消费与经济政策",
      "summary": "快递地址只写到小区，28个省份生娃基本不花钱，A股板块逆势吸筹。",
      "entryIndices": [
        2,
        11,
        16,
        28,
        52,
        61,
        82,
        102,
        108,
        185,
        245,
        296
      ],
      "sources": [
        "weibo-search",
        "toutiao-search",
        "zhihu-search",
        "baidu-hot"
      ]
    }
  ]
}