[{"title":"高考英语难不难","url":"https://www.kuaishou.com/short-video/3xtmfeh3i88phau","hotScore":13483000,"normalizedScore":9888,"source":"kuaishou-hot"},{"title":"iOS27 调休闹钟","url":"https://s.weibo.com/weibo?q=iOS27%20%E8%B0%83%E4%BC%91%E9%97%B9%E9%92%9F&t=31&band_rank=10&Refer=top","hotScore":903684,"normalizedScore":9859,"source":"weibo-search"},{"title":"三峡水运新通道开工","url":"https://so.toutiao.com/search?keyword=三峡水运新通道开工","hotScore":35519279,"normalizedScore":9851,"source":"toutiao-search"},{"title":"习近平和彭丽媛观看朝鲜文艺演出","url":"https://www.baidu.com/s?wd=%E4%B9%A0%E8%BF%91%E5%B9%B3%E5%92%8C%E5%BD%AD%E4%B8%BD%E5%AA%9B%E8%A7%82%E7%9C%8B%E6%9C%9D%E9%B2%9C%E6%96%87%E8%89%BA%E6%BC%94%E5%87%BA&sa=fyb_news&rsv_dl=fyb_news","hotScore":7808050,"normalizedScore":9833,"source":"baidu-hot"},{"title":"读懂山西才懂何以中国","url":"https://www.douyin.com/hot/2525840","hotScore":11908854,"normalizedScore":9833,"source":"douyin-hot"},{"title":"华哥花胖查寝良子偷吃","url":"https://www.kuaishou.com/short-video/3xnju9dg24g2htu","hotScore":13026000,"normalizedScore":9775,"source":"kuaishou-hot"},{"title":"高考作文 给阿嬷的情书","url":"https://s.weibo.com/weibo?q=%E9%AB%98%E8%80%83%E4%BD%9C%E6%96%87%20%E7%BB%99%E9%98%BF%E5%AC%B7%E7%9A%84%E6%83%85%E4%B9%A6&t=31&band_rank=1&Refer=top","hotScore":529572,"normalizedScore":9718,"source":"weibo-search"},{"title":"15万买新能源车还没开回家就出问题","url":"https://so.toutiao.com/search?keyword=15万买新能源车还没开回家就出问题","hotScore":32139172,"normalizedScore":9701,"source":"toutiao-search"},{"title":"“李华 我再也不用见到你了”","url":"https://www.baidu.com/s?wd=%E2%80%9C%E6%9D%8E%E5%8D%8E+%E6%88%91%E5%86%8D%E4%B9%9F%E4%B8%8D%E7%94%A8%E8%A7%81%E5%88%B0%E4%BD%A0%E4%BA%86%E2%80%9D&sa=fyb_news&rsv_dl=fyb_news","hotScore":7712742,"normalizedScore":9667,"source":"baidu-hot"},{"title":"中国男足将在主场迎战泰国队","url":"https://www.douyin.com/hot/2526774","hotScore":11896857,"normalizedScore":9667,"source":"douyin-hot"},{"title":"习近平观看朝鲜专场文艺演出","url":"https://www.kuaishou.com/short-video/3x52srjdrufpvug","hotScore":12736000,"normalizedScore":9663,"source":"kuaishou-hot"},{"title":"平壤各界群众和少年儿童身着节日盛装","url":"https://s.weibo.com/weibo?q=%23%E5%B9%B3%E5%A3%A4%E5%90%84%E7%95%8C%E7%BE%A4%E4%BC%97%E5%92%8C%E5%B0%91%E5%B9%B4%E5%84%BF%E7%AB%A5%E8%BA%AB%E7%9D%80%E8%8A%82%E6%97%A5%E7%9B%9B%E8%A3%85%23&t=31&band_rank=3&Refer=top","hotScore":437548,"normalizedScore":9577,"source":"weibo-search"},{"title":"中朝传统友谊崭新篇章如何续写","url":"https://so.toutiao.com/search?keyword=中朝传统友谊崭新篇章如何续写","hotScore":29080726,"normalizedScore":9552,"source":"toutiao-search"},{"title":"世界末日真的具象化了","url":"https://www.kuaishou.com/short-video/3xis3sqdq569r7w","hotScore":12497000,"normalizedScore":9551,"source":"kuaishou-hot"},{"title":"中朝传统友谊崭新篇章如何续写","url":"https://www.baidu.com/s?wd=%E4%B8%AD%E6%9C%9D%E4%BC%A0%E7%BB%9F%E5%8F%8B%E8%B0%8A%E5%B4%AD%E6%96%B0%E7%AF%87%E7%AB%A0%E5%A6%82%E4%BD%95%E7%BB%AD%E5%86%99&sa=fyb_news&rsv_dl=fyb_news","hotScore":7619352,"normalizedScore":9500,"source":"baidu-hot"},{"title":"从这些瞬间感受中朝友谊","url":"https://www.douyin.com/hot/2527792","hotScore":11841559,"normalizedScore":9500,"source":"douyin-hot"},{"title":"从这些瞬间感受中朝友谊","url":"https://www.kuaishou.com/short-video/3xssax9zzusru4k","hotScore":12232000,"normalizedScore":9438,"source":"kuaishou-hot"},{"title":"iOS27","url":"https://s.weibo.com/weibo?q=iOS27&t=31&band_rank=1&Refer=top","hotScore":411086,"normalizedScore":9437,"source":"weibo-search"},{"title":"鸡蛋为什么突然涨价","url":"https://so.toutiao.com/search?keyword=鸡蛋为什么突然涨价","hotScore":26313329,"normalizedScore":9403,"source":"toutiao-search"},{"title":"考生考完英语：别人easy我是abandon","url":"https://www.baidu.com/s?wd=%E8%80%83%E7%94%9F%E8%80%83%E5%AE%8C%E8%8B%B1%E8%AF%AD%EF%BC%9A%E5%88%AB%E4%BA%BAeasy%E6%88%91%E6%98%AFabandon&sa=fyb_news&rsv_dl=fyb_news","hotScore":7523760,"normalizedScore":9333,"source":"baidu-hot"},{"title":"高考语文试题评析","url":"https://www.douyin.com/hot/2525984","hotScore":11783610,"normalizedScore":9333,"source":"douyin-hot"},{"title":"宁波巨型圆球走红","url":"https://www.kuaishou.com/short-video/3xyzc3fdk6v3p6u","hotScore":11967000,"normalizedScore":9326,"source":"kuaishou-hot"},{"title":"双胞胎姐妹遭袭一死一伤案最新进展","url":"https://s.weibo.com/weibo?q=%23%E5%8F%8C%E8%83%9E%E8%83%8E%E5%A7%90%E5%A6%B9%E9%81%AD%E8%A2%AD%E4%B8%80%E6%AD%BB%E4%B8%80%E4%BC%A4%E6%A1%88%E6%9C%80%E6%96%B0%E8%BF%9B%E5%B1%95%23&t=31&band_rank=7&Refer=top","hotScore":335308,"normalizedScore":9296,"source":"weibo-search"},{"title":"金价下跌后郑州金店被挤爆","url":"https://so.toutiao.com/search?keyword=金价下跌后郑州金店被挤爆","hotScore":23809284,"normalizedScore":9254,"source":"toutiao-search"},{"title":"发现外星生命须立即通报联合国","url":"https://www.kuaishou.com/short-video/3xbmnuibtssc5ti","hotScore":11836000,"normalizedScore":9213,"source":"kuaishou-hot"},{"title":"考生连续4次第一个跑出考场","url":"https://www.baidu.com/s?wd=%E8%80%83%E7%94%9F%E8%BF%9E%E7%BB%AD4%E6%AC%A1%E7%AC%AC%E4%B8%80%E4%B8%AA%E8%B7%91%E5%87%BA%E8%80%83%E5%9C%BA&sa=fyb_news&rsv_dl=fyb_news","hotScore":7424976,"normalizedScore":9167,"source":"baidu-hot"},{"title":"高考英语","url":"https://www.douyin.com/hot/2527232","hotScore":11042116,"normalizedScore":9167,"source":"douyin-hot"},{"title":"为什么面试要填家庭成员信息","url":"https://s.weibo.com/weibo?q=%E4%B8%BA%E4%BB%80%E4%B9%88%E9%9D%A2%E8%AF%95%E8%A6%81%E5%A1%AB%E5%AE%B6%E5%BA%AD%E6%88%90%E5%91%98%E4%BF%A1%E6%81%AF&t=31&band_rank=5&Refer=top","hotScore":330356,"normalizedScore":9155,"source":"weibo-search"},{"title":"菲律宾为何会发生强震","url":"https://so.toutiao.com/search?keyword=菲律宾为何会发生强震","hotScore":21543531,"normalizedScore":9104,"source":"toutiao-search"},{"title":"双胞胎报警2次后遇害","url":"https://www.kuaishou.com/short-video/3xcyr3rpya6haru","hotScore":11741000,"normalizedScore":9101,"source":"kuaishou-hot"},{"title":"A股","url":"https://www.zhihu.com/search?q=A股","hotScore":10,"normalizedScore":9091,"source":"zhihu-search"},{"title":"国行iPhone 悬着的心终于死了","url":"https://s.weibo.com/weibo?q=%E5%9B%BD%E8%A1%8CiPhone%20%E6%82%AC%E7%9D%80%E7%9A%84%E5%BF%83%E7%BB%88%E4%BA%8E%E6%AD%BB%E4%BA%86&t=31&band_rank=7&Refer=top","hotScore":277839,"normalizedScore":9014,"source":"weibo-search"},{"title":"司机避开远光灯后发现4人在车道吃饭","url":"https://www.baidu.com/s?wd=%E5%8F%B8%E6%9C%BA%E9%81%BF%E5%BC%80%E8%BF%9C%E5%85%89%E7%81%AF%E5%90%8E%E5%8F%91%E7%8E%B04%E4%BA%BA%E5%9C%A8%E8%BD%A6%E9%81%93%E5%90%83%E9%A5%AD&sa=fyb_news&rsv_dl=fyb_news","hotScore":7331324,"normalizedScore":9000,"source":"baidu-hot"},{"title":"当我的拼豆手环是专属应援","url":"https://www.douyin.com/hot/2526987","hotScore":10964771,"normalizedScore":9000,"source":"douyin-hot"},{"title":"NBA总决赛G3","url":"https://www.kuaishou.com/short-video/3xsaumkkfeywii9","hotScore":11529000,"normalizedScore":8989,"source":"kuaishou-hot"},{"title":"伊朗宣布停止对以色列的军事行动","url":"https://so.toutiao.com/search?keyword=伊朗宣布停止对以色列的军事行动","hotScore":19493393,"normalizedScore":8955,"source":"toutiao-search"},{"title":"陕西致62人死亡失踪桥梁垮塌细节","url":"https://www.kuaishou.com/short-video/3xy4a45dcb9x3dg","hotScore":11095000,"normalizedScore":8876,"source":"kuaishou-hot"},{"title":"人在什么状态下学习效率最高","url":"https://s.weibo.com/weibo?q=%E4%BA%BA%E5%9C%A8%E4%BB%80%E4%B9%88%E7%8A%B6%E6%80%81%E4%B8%8B%E5%AD%A6%E4%B9%A0%E6%95%88%E7%8E%87%E6%9C%80%E9%AB%98&t=31&band_rank=10&Refer=top","hotScore":245015,"normalizedScore":8873,"source":"weibo-search"},{"title":"18年前被捡的弃婴高考后跪谢养母","url":"https://www.baidu.com/s?wd=18%E5%B9%B4%E5%89%8D%E8%A2%AB%E6%8D%A1%E7%9A%84%E5%BC%83%E5%A9%B4%E9%AB%98%E8%80%83%E5%90%8E%E8%B7%AA%E8%B0%A2%E5%85%BB%E6%AF%8D&sa=fyb_news&rsv_dl=fyb_news","hotScore":7238744,"normalizedScore":8833,"source":"baidu-hot"},{"title":"台湾岛东部海域执法行动画面","url":"https://www.douyin.com/hot/2526967","hotScore":9766886,"normalizedScore":8833,"source":"douyin-hot"},{"title":"高考数学题让宁夏青铜峡108塔出名了","url":"https://so.toutiao.com/search?keyword=高考数学题让宁夏青铜峡108塔出名了","hotScore":17638352,"normalizedScore":8806,"source":"toutiao-search"},{"title":"日媒曝高市孙子在中国大陆留学","url":"https://www.kuaishou.com/short-video/3xvedm2tr9acnxm","hotScore":10870000,"normalizedScore":8764,"source":"kuaishou-hot"},{"title":"窦骁打假罗伯特","url":"https://s.weibo.com/weibo?q=%23%E7%AA%A6%E9%AA%81%E6%89%93%E5%81%87%E7%BD%97%E4%BC%AF%E7%89%B9%23&t=31&band_rank=18&Refer=top","hotScore":223681,"normalizedScore":8732,"source":"weibo-search"},{"title":"考完数学沉默了 考完英语又笑了","url":"https://www.baidu.com/s?wd=%E8%80%83%E5%AE%8C%E6%95%B0%E5%AD%A6%E6%B2%89%E9%BB%98%E4%BA%86+%E8%80%83%E5%AE%8C%E8%8B%B1%E8%AF%AD%E5%8F%88%E7%AC%91%E4%BA%86&sa=fyb_news&rsv_dl=fyb_news","hotScore":7138562,"normalizedScore":8667,"source":"baidu-hot"},{"title":"菲律宾强震多国发布海啸预警","url":"https://www.douyin.com/hot/2526751","hotScore":9498177,"normalizedScore":8667,"source":"douyin-hot"},{"title":"985警车快被摸包浆了","url":"https://so.toutiao.com/search?keyword=985警车快被摸包浆了","hotScore":15959840,"normalizedScore":8657,"source":"toutiao-search"},{"title":"丈夫在妻子去世4个月后殉情","url":"https://www.kuaishou.com/short-video/3xkvhi27ma92fei","hotScore":10666000,"normalizedScore":8652,"source":"kuaishou-hot"},{"title":"韦雪直播怒斥员工","url":"https://s.weibo.com/weibo?q=%23%E9%9F%A6%E9%9B%AA%E7%9B%B4%E6%92%AD%E6%80%92%E6%96%A5%E5%91%98%E5%B7%A5%23&t=31&band_rank=21&Refer=top","hotScore":221930,"normalizedScore":8592,"source":"weibo-search"},{"title":"日本樱岛火山喷发引“火山灰雨”","url":"https://www.kuaishou.com/short-video/3xvehrfn4c7xs9k","hotScore":10452000,"normalizedScore":8539,"source":"kuaishou-hot"},{"title":"陕西桥梁垮塌致62死失踪事故细节公布","url":"https://so.toutiao.com/search?keyword=陕西桥梁垮塌致62死失踪事故细节公布","hotScore":14441061,"normalizedScore":8507,"source":"toutiao-search"},{"title":"当我把今年高考语文作文题喂给AI","url":"https://www.baidu.com/s?wd=%E5%BD%93%E6%88%91%E6%8A%8A%E4%BB%8A%E5%B9%B4%E9%AB%98%E8%80%83%E8%AF%AD%E6%96%87%E4%BD%9C%E6%96%87%E9%A2%98%E5%96%82%E7%BB%99AI&sa=fyb_news&rsv_dl=fyb_news","hotScore":7041094,"normalizedScore":8500,"source":"baidu-hot"},{"title":"首个坐轮椅上清华的人现在怎么样了","url":"https://www.douyin.com/hot/2527283","hotScore":9356958,"normalizedScore":8500,"source":"douyin-hot"},{"title":"跑男团全员包场白鹿莫离","url":"https://s.weibo.com/weibo?q=%23%E8%B7%91%E7%94%B7%E5%9B%A2%E5%85%A8%E5%91%98%E5%8C%85%E5%9C%BA%E7%99%BD%E9%B9%BF%E8%8E%AB%E7%A6%BB%23&t=31&band_rank=6&Refer=top","hotScore":168036,"normalizedScore":8451,"source":"weibo-search"},{"title":"合肥地铁高考暖心广播","url":"https://www.kuaishou.com/short-video/3xyzffpvh7dzjus","hotScore":10432000,"normalizedScore":8427,"source":"kuaishou-hot"},{"title":"26楼马桶里钻出1.5米长蛇","url":"https://so.toutiao.com/search?keyword=26楼马桶里钻出1.5米长蛇","hotScore":13066812,"normalizedScore":8358,"source":"toutiao-search"},{"title":"世界杯","url":"https://www.baidu.com/s?wd=%E4%B8%96%E7%95%8C%E6%9D%AF&sa=fyb_news&rsv_dl=fyb_news","hotScore":6947786,"normalizedScore":8333,"source":"baidu-hot"},{"title":"当咸甜大战遇到水果冰粽","url":"https://www.douyin.com/hot/2527142","hotScore":9309753,"normalizedScore":8333,"source":"douyin-hot"},{"title":"中国足球小将不惹事也绝不怕事","url":"https://www.kuaishou.com/short-video/3xufhnjmmd9hkdm","hotScore":10408000,"normalizedScore":8315,"source":"kuaishou-hot"},{"title":"林青霞这才是真正优雅的老去","url":"https://s.weibo.com/weibo?q=%23%E6%9E%97%E9%9D%92%E9%9C%9E%E8%BF%99%E6%89%8D%E6%98%AF%E7%9C%9F%E6%AD%A3%E4%BC%98%E9%9B%85%E7%9A%84%E8%80%81%E5%8E%BB%23&t=31&band_rank=26&Refer=top","hotScore":161618,"normalizedScore":8310,"source":"weibo-search"},{"title":"网传“人造大米有毒”不实","url":"https://so.toutiao.com/search?keyword=网传“人造大米有毒”不实","hotScore":11823340,"normalizedScore":8209,"source":"toutiao-search"},{"title":"骑电动车4000公里回家过端午","url":"https://www.kuaishou.com/short-video/3xupg2tdrq2t47e","hotScore":10381000,"normalizedScore":8202,"source":"kuaishou-hot"},{"title":"TES战胜WE","url":"https://www.zhihu.com/search?q=TES战胜WE","hotScore":9,"normalizedScore":8182,"source":"zhihu-search"},{"title":"张月方停止浪姐选歌","url":"https://s.weibo.com/weibo?q=%23%E5%BC%A0%E6%9C%88%E6%96%B9%E5%81%9C%E6%AD%A2%E6%B5%AA%E5%A7%90%E9%80%89%E6%AD%8C%23&t=31&band_rank=12&Refer=top","hotScore":156741,"normalizedScore":8169,"source":"weibo-search"},{"title":"亳州曹操运兵道开挖系谣言","url":"https://www.baidu.com/s?wd=%E4%BA%B3%E5%B7%9E%E6%9B%B9%E6%93%8D%E8%BF%90%E5%85%B5%E9%81%93%E5%BC%80%E6%8C%96%E7%B3%BB%E8%B0%A3%E8%A8%80&sa=fyb_news&rsv_dl=fyb_news","hotScore":6850132,"normalizedScore":8167,"source":"baidu-hot"},{"title":"12岁足球小将的出圈之路","url":"https://www.douyin.com/hot/2525788","hotScore":9189951,"normalizedScore":8167,"source":"douyin-hot"},{"title":"高考英语","url":"https://www.kuaishou.com/short-video/3x73j93efe4zucu","hotScore":10355000,"normalizedScore":8090,"source":"kuaishou-hot"},{"title":"电子布价格涨幅达100%","url":"https://so.toutiao.com/search?keyword=电子布价格涨幅达100%","hotScore":10698201,"normalizedScore":8060,"source":"toutiao-search"},{"title":"全世界倒数第一体面的运动","url":"https://s.weibo.com/weibo?q=%E5%85%A8%E4%B8%96%E7%95%8C%E5%80%92%E6%95%B0%E7%AC%AC%E4%B8%80%E4%BD%93%E9%9D%A2%E7%9A%84%E8%BF%90%E5%8A%A8&t=31&band_rank=11&Refer=top","hotScore":154202,"normalizedScore":8028,"source":"weibo-search"},{"title":"94岁胡枫演唱会开近5小时","url":"https://www.baidu.com/s?wd=94%E5%B2%81%E8%83%A1%E6%9E%AB%E6%BC%94%E5%94%B1%E4%BC%9A%E5%BC%80%E8%BF%915%E5%B0%8F%E6%97%B6&sa=fyb_news&rsv_dl=fyb_news","hotScore":6756271,"normalizedScore":8000,"source":"baidu-hot"},{"title":"琵琶行原唱发抖音祝福考生","url":"https://www.douyin.com/hot/2526117","hotScore":9149550,"normalizedScore":8000,"source":"douyin-hot"},{"title":"隔空猥亵也是性侵","url":"https://www.kuaishou.com/short-video/3xjx35dv6ukvu52","hotScore":10326000,"normalizedScore":7978,"source":"kuaishou-hot"},{"title":"媒体：两岸统一后台湾将不再缺电","url":"https://so.toutiao.com/search?keyword=媒体：两岸统一后台湾将不再缺电","hotScore":9680132,"normalizedScore":7910,"source":"toutiao-search"},{"title":"美股","url":"https://s.weibo.com/weibo?q=%E7%BE%8E%E8%82%A1&t=31&band_rank=16&Refer=top","hotScore":151324,"normalizedScore":7887,"source":"weibo-search"},{"title":"伊朗发射导弹打击以色列能源企业","url":"https://www.kuaishou.com/short-video/3xfpvurzmm6adsc","hotScore":10323000,"normalizedScore":7865,"source":"kuaishou-hot"},{"title":"微信灰测朋友圈搜索功能","url":"https://www.baidu.com/s?wd=%E5%BE%AE%E4%BF%A1%E7%81%B0%E6%B5%8B%E6%9C%8B%E5%8F%8B%E5%9C%88%E6%90%9C%E7%B4%A2%E5%8A%9F%E8%83%BD&sa=fyb_news&rsv_dl=fyb_news","hotScore":6663227,"normalizedScore":7833,"source":"baidu-hot"},{"title":"官方辟谣“人造大米有毒”","url":"https://www.douyin.com/hot/2527859","hotScore":9100797,"normalizedScore":7833,"source":"douyin-hot"},{"title":"女孩考完数学自信估分149到150分","url":"https://so.toutiao.com/search?keyword=女孩考完数学自信估分149到150分","hotScore":9285577,"normalizedScore":7761,"source":"toutiao-search"},{"title":"菲律宾7.9级地震现场画面","url":"https://www.kuaishou.com/short-video/3xcfgiun7ixpjes","hotScore":10269000,"normalizedScore":7753,"source":"kuaishou-hot"},{"title":"苹果开发者大会","url":"https://s.weibo.com/weibo?q=%E8%8B%B9%E6%9E%9C%E5%BC%80%E5%8F%91%E8%80%85%E5%A4%A7%E4%BC%9A&t=31&band_rank=7&Refer=top","hotScore":149142,"normalizedScore":7746,"source":"weibo-search"},{"title":"伊朗和以色列先后宣布停止袭击对方","url":"https://www.baidu.com/s?wd=%E4%BC%8A%E6%9C%97%E5%92%8C%E4%BB%A5%E8%89%B2%E5%88%97%E5%85%88%E5%90%8E%E5%AE%A3%E5%B8%83%E5%81%9C%E6%AD%A2%E8%A2%AD%E5%87%BB%E5%AF%B9%E6%96%B9&sa=fyb_news&rsv_dl=fyb_news","hotScore":6559076,"normalizedScore":7667,"source":"baidu-hot"},{"title":"看我用早茶拿捏哈兰德","url":"https://www.douyin.com/hot/2527565","hotScore":9075527,"normalizedScore":7667,"source":"douyin-hot"},{"title":"女警私盖公章诈骗获刑","url":"https://www.kuaishou.com/short-video/3x99martuvyg3m9","hotScore":10257000,"normalizedScore":7640,"source":"kuaishou-hot"},{"title":"九旬老夫妻立遗嘱把房产留给患病女儿","url":"https://so.toutiao.com/search?keyword=九旬老夫妻立遗嘱把房产留给患病女儿","hotScore":8758946,"normalizedScore":7612,"source":"toutiao-search"},{"title":"韩国爱豆看了一整晚贺峻霖粉丝直播","url":"https://s.weibo.com/weibo?q=%23%E9%9F%A9%E5%9B%BD%E7%88%B1%E8%B1%86%E7%9C%8B%E4%BA%86%E4%B8%80%E6%95%B4%E6%99%9A%E8%B4%BA%E5%B3%BB%E9%9C%96%E7%B2%89%E4%B8%9D%E7%9B%B4%E6%92%AD%23&t=31&band_rank=33&Refer=top","hotScore":145368,"normalizedScore":7606,"source":"weibo-search"},{"title":"老父亲住院含泪给钱儿子","url":"https://www.kuaishou.com/short-video/3x6vcq2s3bnh8hw","hotScore":10218000,"normalizedScore":7528,"source":"kuaishou-hot"},{"title":"四川00后班主任返还三年暂扣物品","url":"https://www.baidu.com/s?wd=%E5%9B%9B%E5%B7%9D00%E5%90%8E%E7%8F%AD%E4%B8%BB%E4%BB%BB%E8%BF%94%E8%BF%98%E4%B8%89%E5%B9%B4%E6%9A%82%E6%89%A3%E7%89%A9%E5%93%81&sa=fyb_news&rsv_dl=fyb_news","hotScore":6473124,"normalizedScore":7500,"source":"baidu-hot"},{"title":"还是忘不了本手妙手俗手","url":"https://www.douyin.com/hot/2526018","hotScore":9040189,"normalizedScore":7500,"source":"douyin-hot"},{"title":"孙红雷在埃菲尔铁塔下很想龚俊","url":"https://s.weibo.com/weibo?q=%E5%AD%99%E7%BA%A2%E9%9B%B7%E5%9C%A8%E5%9F%83%E8%8F%B2%E5%B0%94%E9%93%81%E5%A1%94%E4%B8%8B%E5%BE%88%E6%83%B3%E9%BE%9A%E4%BF%8A&t=31&band_rank=28&Refer=top","hotScore":137299,"normalizedScore":7465,"source":"weibo-search"},{"title":"胜宏科技回应董事长电梯视频传闻","url":"https://so.toutiao.com/search?keyword=胜宏科技回应董事长电梯视频传闻","hotScore":7925422,"normalizedScore":7463,"source":"toutiao-search"},{"title":"世界杯之年球迷开心了好几天","url":"https://www.kuaishou.com/short-video/3x8ebcugpba552i","hotScore":10197000,"normalizedScore":7416,"source":"kuaishou-hot"},{"title":"文科生的春天又回来了吗","url":"https://www.baidu.com/s?wd=%E6%96%87%E7%A7%91%E7%94%9F%E7%9A%84%E6%98%A5%E5%A4%A9%E5%8F%88%E5%9B%9E%E6%9D%A5%E4%BA%86%E5%90%97&sa=fyb_news&rsv_dl=fyb_news","hotScore":6375529,"normalizedScore":7333,"source":"baidu-hot"},{"title":"多地公布2026年高考查分时间","url":"https://www.douyin.com/hot/2526224","hotScore":8741881,"normalizedScore":7333,"source":"douyin-hot"},{"title":"代斯后悔没有为自己战一把","url":"https://s.weibo.com/weibo?q=%23%E4%BB%A3%E6%96%AF%E5%90%8E%E6%82%94%E6%B2%A1%E6%9C%89%E4%B8%BA%E8%87%AA%E5%B7%B1%E6%88%98%E4%B8%80%E6%8A%8A%23&t=31&band_rank=36&Refer=top","hotScore":125200,"normalizedScore":7324,"source":"weibo-search"},{"title":"贵金属专家：不要盲目抛售黄金","url":"https://so.toutiao.com/search?keyword=贵金属专家：不要盲目抛售黄金","hotScore":7324203,"normalizedScore":7313,"source":"toutiao-search"},{"title":"伊朗代表团十余人遭美国拒签","url":"https://www.kuaishou.com/short-video/3xgm75na8kijih2","hotScore":10183000,"normalizedScore":7303,"source":"kuaishou-hot"},{"title":"浪姐四公","url":"https://www.zhihu.com/search?q=浪姐四公","hotScore":8,"normalizedScore":7273,"source":"zhihu-search"},{"title":"高考数学难不难","url":"https://www.kuaishou.com/short-video/3x49c4dkzepwp49","hotScore":10173000,"normalizedScore":7191,"source":"kuaishou-hot"},{"title":"杨丽萍42岁依然这么美","url":"https://s.weibo.com/weibo?q=%E6%9D%A8%E4%B8%BD%E8%90%8D42%E5%B2%81%E4%BE%9D%E7%84%B6%E8%BF%99%E4%B9%88%E7%BE%8E&t=31&band_rank=38&Refer=top","hotScore":112520,"normalizedScore":7183,"source":"weibo-search"},{"title":"日韩股市突然暴跌 AI泡沫要破了吗","url":"https://www.baidu.com/s?wd=%E6%97%A5%E9%9F%A9%E8%82%A1%E5%B8%82%E7%AA%81%E7%84%B6%E6%9A%B4%E8%B7%8C+AI%E6%B3%A1%E6%B2%AB%E8%A6%81%E7%A0%B4%E4%BA%86%E5%90%97&sa=fyb_news&rsv_dl=fyb_news","hotScore":6285971,"normalizedScore":7167,"source":"baidu-hot"},{"title":"国资委副部级干部潘良被开除党籍","url":"https://www.douyin.com/hot/2527429","hotScore":8702818,"normalizedScore":7167,"source":"douyin-hot"},{"title":"高考首日“一张证都没办”意外火了","url":"https://so.toutiao.com/search?keyword=高考首日“一张证都没办”意外火了","hotScore":7171218,"normalizedScore":7164,"source":"toutiao-search"},{"title":"考生进场前向母亲三鞠躬","url":"https://www.kuaishou.com/short-video/3xt9tp6khwqt87m","hotScore":10155000,"normalizedScore":7079,"source":"kuaishou-hot"},{"title":"前同事离职忘记删聊天记录","url":"https://s.weibo.com/weibo?q=%E5%89%8D%E5%90%8C%E4%BA%8B%E7%A6%BB%E8%81%8C%E5%BF%98%E8%AE%B0%E5%88%A0%E8%81%8A%E5%A4%A9%E8%AE%B0%E5%BD%95&t=31&band_rank=13&Refer=top","hotScore":110184,"normalizedScore":7042,"source":"weibo-search"},{"title":"庆祝中菲建交51周年活动举行","url":"https://so.toutiao.com/search?keyword=庆祝中菲建交51周年活动举行","hotScore":6488787,"normalizedScore":7015,"source":"toutiao-search"},{"title":"长沙考生妈妈提花等女儿下考","url":"https://www.baidu.com/s?wd=%E9%95%BF%E6%B2%99%E8%80%83%E7%94%9F%E5%A6%88%E5%A6%88%E6%8F%90%E8%8A%B1%E7%AD%89%E5%A5%B3%E5%84%BF%E4%B8%8B%E8%80%83&sa=fyb_news&rsv_dl=fyb_news","hotScore":6184055,"normalizedScore":7000,"source":"baidu-hot"},{"title":"BLG 3:0战胜AL","url":"https://www.douyin.com/hot/2527740","hotScore":8301578,"normalizedScore":7000,"source":"douyin-hot"},{"title":"刘大炮爆改成古风小生","url":"https://www.kuaishou.com/short-video/3xveywwrrdhys2k","hotScore":10149000,"normalizedScore":6966,"source":"kuaishou-hot"},{"title":"李小冉 张月","url":"https://s.weibo.com/weibo?q=%E6%9D%8E%E5%B0%8F%E5%86%89%20%E5%BC%A0%E6%9C%88&t=31&band_rank=16&Refer=top","hotScore":107667,"normalizedScore":6901,"source":"weibo-search"},{"title":"男子“号脉”抓出木床内蛀虫","url":"https://so.toutiao.com/search?keyword=男子“号脉”抓出木床内蛀虫","hotScore":5871297,"normalizedScore":6866,"source":"toutiao-search"},{"title":"人大附中学生答案进考场具象化了","url":"https://www.kuaishou.com/short-video/3x74ycmf44iy4vm","hotScore":10134000,"normalizedScore":6854,"source":"kuaishou-hot"},{"title":"高考生进考场前下巴脱臼","url":"https://www.baidu.com/s?wd=%E9%AB%98%E8%80%83%E7%94%9F%E8%BF%9B%E8%80%83%E5%9C%BA%E5%89%8D%E4%B8%8B%E5%B7%B4%E8%84%B1%E8%87%BC&sa=fyb_news&rsv_dl=fyb_news","hotScore":6096232,"normalizedScore":6833,"source":"baidu-hot"},{"title":"NBA总决赛G3尼克斯vs马刺前瞻","url":"https://www.douyin.com/hot/2527145","hotScore":8025322,"normalizedScore":6833,"source":"douyin-hot"},{"title":"曾沛慈想要曾沛慈得到","url":"https://s.weibo.com/weibo?q=%23%E6%9B%BE%E6%B2%9B%E6%85%88%E6%83%B3%E8%A6%81%E6%9B%BE%E6%B2%9B%E6%85%88%E5%BE%97%E5%88%B0%23&t=31&band_rank=41&Refer=top","hotScore":107153,"normalizedScore":6761,"source":"weibo-search"},{"title":"彭冠英入驻快手","url":"https://www.kuaishou.com/short-video/3xie9r5wif5vjxk","hotScore":10112000,"normalizedScore":6742,"source":"kuaishou-hot"},{"title":"6分钱一支“脏牙刷”主要供给民宿","url":"https://so.toutiao.com/search?keyword=6分钱一支“脏牙刷”主要供给民宿","hotScore":5312569,"normalizedScore":6716,"source":"toutiao-search"},{"title":"美股三大指数涨跌不一 芯片股反弹","url":"https://www.baidu.com/s?wd=%E7%BE%8E%E8%82%A1%E4%B8%89%E5%A4%A7%E6%8C%87%E6%95%B0%E6%B6%A8%E8%B7%8C%E4%B8%8D%E4%B8%80+%E8%8A%AF%E7%89%87%E8%82%A1%E5%8F%8D%E5%BC%B9&sa=fyb_news&rsv_dl=fyb_news","hotScore":5999485,"normalizedScore":6667,"source":"baidu-hot"},{"title":"曾沛慈断层第一","url":"https://www.douyin.com/hot/2526867","hotScore":7845702,"normalizedScore":6667,"source":"douyin-hot"},{"title":"新型毒品伪装零食","url":"https://www.kuaishou.com/short-video/3x6k87n3pbqwmfs","hotScore":10102000,"normalizedScore":6629,"source":"kuaishou-hot"},{"title":"多名网络用户就造谣小米公司公开道歉","url":"https://s.weibo.com/weibo?q=%23%E5%A4%9A%E5%90%8D%E7%BD%91%E7%BB%9C%E7%94%A8%E6%88%B7%E5%B0%B1%E9%80%A0%E8%B0%A3%E5%B0%8F%E7%B1%B3%E5%85%AC%E5%8F%B8%E5%85%AC%E5%BC%80%E9%81%93%E6%AD%89%23&t=31&band_rank=42&Refer=top","hotScore":107152,"normalizedScore":6620,"source":"weibo-search"},{"title":"儿子涉嫌吃空饷医院院长放弃人才考察","url":"https://so.toutiao.com/search?keyword=儿子涉嫌吃空饷医院院长放弃人才考察","hotScore":4807011,"normalizedScore":6567,"source":"toutiao-search"},{"title":"苹果开发者大会","url":"https://www.kuaishou.com/short-video/3xg36a4musghiny","hotScore":10089000,"normalizedScore":6517,"source":"kuaishou-hot"},{"title":"马宁回应“吹罚世界杯没有软肋”","url":"https://www.baidu.com/s?wd=%E9%A9%AC%E5%AE%81%E5%9B%9E%E5%BA%94%E2%80%9C%E5%90%B9%E7%BD%9A%E4%B8%96%E7%95%8C%E6%9D%AF%E6%B2%A1%E6%9C%89%E8%BD%AF%E8%82%8B%E2%80%9D&sa=fyb_news&rsv_dl=fyb_news","hotScore":5896578,"normalizedScore":6500,"source":"baidu-hot"},{"title":"胜宏科技董事长“电梯门”事件","url":"https://www.douyin.com/hot/2527170","hotScore":7836426,"normalizedScore":6500,"source":"douyin-hot"},{"title":"内娱流量时代迎来了真正的洗牌","url":"https://s.weibo.com/weibo?q=%23%E5%86%85%E5%A8%B1%E6%B5%81%E9%87%8F%E6%97%B6%E4%BB%A3%E8%BF%8E%E6%9D%A5%E4%BA%86%E7%9C%9F%E6%AD%A3%E7%9A%84%E6%B4%97%E7%89%8C%23&t=31&band_rank=43&Refer=top","hotScore":107150,"normalizedScore":6479,"source":"weibo-search"},{"title":"女警私盖公章赊购烟茶酒获刑8年","url":"https://so.toutiao.com/search?keyword=女警私盖公章赊购烟茶酒获刑8年","hotScore":4349564,"normalizedScore":6418,"source":"toutiao-search"},{"title":"女孩考完数学自信估分149到150","url":"https://www.kuaishou.com/short-video/3xrkapx999u95xw","hotScore":10076000,"normalizedScore":6404,"source":"kuaishou-hot"},{"title":"高考注意事项","url":"https://www.zhihu.com/search?q=高考注意事项","hotScore":7,"normalizedScore":6364,"source":"zhihu-search"},{"title":"A股巨震的原因找到了","url":"https://s.weibo.com/weibo?q=%23A%E8%82%A1%E5%B7%A8%E9%9C%87%E7%9A%84%E5%8E%9F%E5%9B%A0%E6%89%BE%E5%88%B0%E4%BA%86%23&t=31&band_rank=44&Refer=top","hotScore":107150,"normalizedScore":6338,"source":"weibo-search"},{"title":"考生押中英语作文题：提前背了素材","url":"https://www.baidu.com/s?wd=%E8%80%83%E7%94%9F%E6%8A%BC%E4%B8%AD%E8%8B%B1%E8%AF%AD%E4%BD%9C%E6%96%87%E9%A2%98%EF%BC%9A%E6%8F%90%E5%89%8D%E8%83%8C%E4%BA%86%E7%B4%A0%E6%9D%90&sa=fyb_news&rsv_dl=fyb_news","hotScore":5809737,"normalizedScore":6333,"source":"baidu-hot"},{"title":"奔跑吧因安阳特辑用邯郸画面致歉","url":"https://www.douyin.com/hot/2527282","hotScore":7810638,"normalizedScore":6333,"source":"douyin-hot"},{"title":"菲律宾7.9级地震威力有多强","url":"https://www.kuaishou.com/short-video/3xf6teqdfuhpvsm","hotScore":10051000,"normalizedScore":6292,"source":"kuaishou-hot"},{"title":"郑钦文世界排名跌至第122位","url":"https://so.toutiao.com/search?keyword=郑钦文世界排名跌至第122位","hotScore":4019608,"normalizedScore":6269,"source":"toutiao-search"},{"title":"存子生图眼睛比精修大","url":"https://s.weibo.com/weibo?q=%E5%AD%98%E5%AD%90%E7%94%9F%E5%9B%BE%E7%9C%BC%E7%9D%9B%E6%AF%94%E7%B2%BE%E4%BF%AE%E5%A4%A7&t=31&band_rank=49&Refer=top","hotScore":107143,"normalizedScore":6197,"source":"weibo-search"},{"title":"高考物理","url":"https://www.kuaishou.com/short-video/3xr6pg5t8gqydrw","hotScore":10045000,"normalizedScore":6180,"source":"kuaishou-hot"},{"title":"又一国产减肥药挑战司美格鲁肽","url":"https://www.baidu.com/s?wd=%E5%8F%88%E4%B8%80%E5%9B%BD%E4%BA%A7%E5%87%8F%E8%82%A5%E8%8D%AF%E6%8C%91%E6%88%98%E5%8F%B8%E7%BE%8E%E6%A0%BC%E9%B2%81%E8%82%BD&sa=fyb_news&rsv_dl=fyb_news","hotScore":5697949,"normalizedScore":6167,"source":"baidu-hot"},{"title":"哇咔哇咔杀回来了","url":"https://www.douyin.com/hot/2527231","hotScore":7794764,"normalizedScore":6167,"source":"douyin-hot"},{"title":"奇瑞回应“与印度塔塔集团相关合作”","url":"https://so.toutiao.com/search?keyword=奇瑞回应“与印度塔塔集团相关合作”","hotScore":3935648,"normalizedScore":6119,"source":"toutiao-search"},{"title":"南方肉粽震惊东北人","url":"https://www.kuaishou.com/short-video/3xg3bqmvvmfjj8m","hotScore":10023000,"normalizedScore":6067,"source":"kuaishou-hot"},{"title":"长子病逝近6旬大爷陪幼子高考","url":"https://s.weibo.com/weibo?q=%23%E9%95%BF%E5%AD%90%E7%97%85%E9%80%9D%E8%BF%916%E6%97%AC%E5%A4%A7%E7%88%B7%E9%99%AA%E5%B9%BC%E5%AD%90%E9%AB%98%E8%80%83%23&t=31&band_rank=50&Refer=top","hotScore":107142,"normalizedScore":6056,"source":"weibo-search"},{"title":"50岁男子被蝮蛇咬伤冷静自救保命","url":"https://www.baidu.com/s?wd=50%E5%B2%81%E7%94%B7%E5%AD%90%E8%A2%AB%E8%9D%AE%E8%9B%87%E5%92%AC%E4%BC%A4%E5%86%B7%E9%9D%99%E8%87%AA%E6%95%91%E4%BF%9D%E5%91%BD&sa=fyb_news&rsv_dl=fyb_news","hotScore":5619699,"normalizedScore":6000,"source":"baidu-hot"},{"title":"小火人联动童年顶流","url":"https://www.douyin.com/hot/2527003","hotScore":7776472,"normalizedScore":6000,"source":"douyin-hot"},{"title":"全球股市黄金无差别暴跌原因是啥","url":"https://so.toutiao.com/search?keyword=全球股市黄金无差别暴跌原因是啥","hotScore":3908329,"normalizedScore":5970,"source":"toutiao-search"},{"title":"轻机枪运动目标射击","url":"https://www.kuaishou.com/short-video/3xn55tujkj7f52c","hotScore":10010000,"normalizedScore":5955,"source":"kuaishou-hot"},{"title":"金饰克价跌400元却没人买了","url":"https://s.weibo.com/weibo?q=%23%E9%87%91%E9%A5%B0%E5%85%8B%E4%BB%B7%E8%B7%8C400%E5%85%83%E5%8D%B4%E6%B2%A1%E4%BA%BA%E4%B9%B0%E4%BA%86%23&t=31&band_rank=11&Refer=top","hotScore":106068,"normalizedScore":5915,"source":"weibo-search"},{"title":"日本在最东端离岛部署导弹","url":"https://www.kuaishou.com/short-video/3xpuvpm7vkfbkdy","hotScore":9998000,"normalizedScore":5843,"source":"kuaishou-hot"},{"title":"00后运动员长期点外卖断送运动生涯","url":"https://www.baidu.com/s?wd=00%E5%90%8E%E8%BF%90%E5%8A%A8%E5%91%98%E9%95%BF%E6%9C%9F%E7%82%B9%E5%A4%96%E5%8D%96%E6%96%AD%E9%80%81%E8%BF%90%E5%8A%A8%E7%94%9F%E6%B6%AF&sa=fyb_news&rsv_dl=fyb_news","hotScore":5527268,"normalizedScore":5833,"source":"baidu-hot"},{"title":"高考结束后的出题老师","url":"https://www.douyin.com/hot/2527181","hotScore":7775070,"normalizedScore":5833,"source":"douyin-hot"},{"title":"妈妈为穿旗袍送考狂瘦22斤","url":"https://so.toutiao.com/search?keyword=妈妈为穿旗袍送考狂瘦22斤","hotScore":3561121,"normalizedScore":5821,"source":"toutiao-search"},{"title":"郑钦文vs克里斯蒂安","url":"https://s.weibo.com/weibo?q=%E9%83%91%E9%92%A6%E6%96%87vs%E5%85%8B%E9%87%8C%E6%96%AF%E8%92%82%E5%AE%89&t=31&band_rank=9&Refer=top","hotScore":99071,"normalizedScore":5775,"source":"weibo-search"},{"title":"烤肉店回应宠物狗偷吃顾客餐食","url":"https://www.kuaishou.com/short-video/3x8hzz57shhje84","hotScore":9990000,"normalizedScore":5730,"source":"kuaishou-hot"},{"title":"任泽平：科技牛的下一个光","url":"https://so.toutiao.com/search?keyword=任泽平：科技牛的下一个光","hotScore":3222236,"normalizedScore":5672,"source":"toutiao-search"},{"title":"库克最后一场WWDC：AI Siri登场","url":"https://www.baidu.com/s?wd=%E5%BA%93%E5%85%8B%E6%9C%80%E5%90%8E%E4%B8%80%E5%9C%BAWWDC%EF%BC%9AAI+Siri%E7%99%BB%E5%9C%BA&sa=fyb_news&rsv_dl=fyb_news","hotScore":5507901,"normalizedScore":5667,"source":"baidu-hot"},{"title":"想要问问你敢不敢转场挑战","url":"https://www.douyin.com/hot/2526945","hotScore":7758754,"normalizedScore":5667,"source":"douyin-hot"},{"title":"2026高考","url":"https://s.weibo.com/weibo?q=2026%E9%AB%98%E8%80%83&t=31&band_rank=19&Refer=top","hotScore":94509,"normalizedScore":5634,"source":"weibo-search"},{"title":"安徽最美婶婶抚养6个孩子","url":"https://www.kuaishou.com/short-video/3x4fcdq2283gzxg","hotScore":9944000,"normalizedScore":5618,"source":"kuaishou-hot"},{"title":"这个世界开始奖励认真做事的人了吗","url":"https://so.toutiao.com/search?keyword=这个世界开始奖励认真做事的人了吗","hotScore":2915599,"normalizedScore":5522,"source":"toutiao-search"},{"title":"日本樱岛火山灰柱高达1300米","url":"https://www.kuaishou.com/short-video/3xskpaprv83r5si","hotScore":9935000,"normalizedScore":5506,"source":"kuaishou-hot"},{"title":"被炸伤女主播否认嫌疑人是榜一大哥","url":"https://www.baidu.com/s?wd=%E8%A2%AB%E7%82%B8%E4%BC%A4%E5%A5%B3%E4%B8%BB%E6%92%AD%E5%90%A6%E8%AE%A4%E5%AB%8C%E7%96%91%E4%BA%BA%E6%98%AF%E6%A6%9C%E4%B8%80%E5%A4%A7%E5%93%A5&sa=fyb_news&rsv_dl=fyb_news","hotScore":5420951,"normalizedScore":5500,"source":"baidu-hot"},{"title":"胡枫演唱会刘德华深情演唱忘情水","url":"https://www.douyin.com/hot/2526801","hotScore":7756450,"normalizedScore":5500,"source":"douyin-hot"},{"title":"杀妻因抑郁发作被判死缓案将开庭","url":"https://s.weibo.com/weibo?q=%23%E6%9D%80%E5%A6%BB%E5%9B%A0%E6%8A%91%E9%83%81%E5%8F%91%E4%BD%9C%E8%A2%AB%E5%88%A4%E6%AD%BB%E7%BC%93%E6%A1%88%E5%B0%86%E5%BC%80%E5%BA%AD%23&t=31&band_rank=41&Refer=top","hotScore":91442,"normalizedScore":5493,"source":"weibo-search"},{"title":"BLG战胜JDG","url":"https://www.zhihu.com/search?q=BLG战胜JDG","hotScore":6,"normalizedScore":5455,"source":"zhihu-search"},{"title":"姥姥病中索吻姥爷","url":"https://www.kuaishou.com/short-video/3xq2i74i52kv2ma","hotScore":9922000,"normalizedScore":5393,"source":"kuaishou-hot"},{"title":"高考历史全国卷：创新考查方式","url":"https://so.toutiao.com/search?keyword=高考历史全国卷：创新考查方式","hotScore":2895361,"normalizedScore":5373,"source":"toutiao-search"},{"title":"男子伪装店员带走醉酒女子后性侵","url":"https://s.weibo.com/weibo?q=%23%E7%94%B7%E5%AD%90%E4%BC%AA%E8%A3%85%E5%BA%97%E5%91%98%E5%B8%A6%E8%B5%B0%E9%86%89%E9%85%92%E5%A5%B3%E5%AD%90%E5%90%8E%E6%80%A7%E4%BE%B5%23&t=31&band_rank=24&Refer=top","hotScore":91426,"normalizedScore":5352,"source":"weibo-search"},{"title":"流水的世界杯 铁打的夏奇拉","url":"https://www.baidu.com/s?wd=%E6%B5%81%E6%B0%B4%E7%9A%84%E4%B8%96%E7%95%8C%E6%9D%AF+%E9%93%81%E6%89%93%E7%9A%84%E5%A4%8F%E5%A5%87%E6%8B%89&sa=fyb_news&rsv_dl=fyb_news","hotScore":5335556,"normalizedScore":5333,"source":"baidu-hot"},{"title":"谢苗谈功夫演员断层","url":"https://www.douyin.com/hot/2527654","hotScore":7730593,"normalizedScore":5333,"source":"douyin-hot"},{"title":"小米回应SU7电吸门无防夹功能","url":"https://www.kuaishou.com/short-video/3x6qctm84a8gqv4","hotScore":9894000,"normalizedScore":5281,"source":"kuaishou-hot"},{"title":"中国籍地产商柬埔寨遇害案4嫌犯被捕","url":"https://so.toutiao.com/search?keyword=中国籍地产商柬埔寨遇害案4嫌犯被捕","hotScore":2796762,"normalizedScore":5224,"source":"toutiao-search"},{"title":"李昀锐小说眼角通红具像化了","url":"https://s.weibo.com/weibo?q=%23%E6%9D%8E%E6%98%80%E9%94%90%E5%B0%8F%E8%AF%B4%E7%9C%BC%E8%A7%92%E9%80%9A%E7%BA%A2%E5%85%B7%E5%83%8F%E5%8C%96%E4%BA%86%23&t=31&band_rank=24&Refer=top","hotScore":91147,"normalizedScore":5211,"source":"weibo-search"},{"title":"日本富士山也在 “憋大招”","url":"https://www.kuaishou.com/short-video/3xekthfpci4v946","hotScore":9892000,"normalizedScore":5169,"source":"kuaishou-hot"},{"title":"考生考场看到执勤妈妈 两人紧紧拥抱","url":"https://www.baidu.com/s?wd=%E8%80%83%E7%94%9F%E8%80%83%E5%9C%BA%E7%9C%8B%E5%88%B0%E6%89%A7%E5%8B%A4%E5%A6%88%E5%A6%88+%E4%B8%A4%E4%BA%BA%E7%B4%A7%E7%B4%A7%E6%8B%A5%E6%8A%B1&sa=fyb_news&rsv_dl=fyb_news","hotScore":5218040,"normalizedScore":5167,"source":"baidu-hot"},{"title":"前奏太好听于是想和你交换照片","url":"https://www.douyin.com/hot/2527366","hotScore":7717153,"normalizedScore":5167,"source":"douyin-hot"},{"title":"四川宜宾一村有人疑似放生大量蛇","url":"https://so.toutiao.com/search?keyword=四川宜宾一村有人疑似放生大量蛇","hotScore":2638143,"normalizedScore":5075,"source":"toutiao-search"},{"title":"Siri AI","url":"https://s.weibo.com/weibo?q=Siri%20AI&t=31&band_rank=5&Refer=top","hotScore":90177,"normalizedScore":5070,"source":"weibo-search"},{"title":"菲律宾南部地震致19死","url":"https://www.kuaishou.com/short-video/3xmyxvvfxxjvgny","hotScore":9892000,"normalizedScore":5056,"source":"kuaishou-hot"},{"title":"菲律宾地震时有变压器爆炸","url":"https://www.baidu.com/s?wd=%E8%8F%B2%E5%BE%8B%E5%AE%BE%E5%9C%B0%E9%9C%87%E6%97%B6%E6%9C%89%E5%8F%98%E5%8E%8B%E5%99%A8%E7%88%86%E7%82%B8&sa=fyb_news&rsv_dl=fyb_news","hotScore":5136063,"normalizedScore":5000,"source":"baidu-hot"},{"title":"伊朗时隔两个月再袭以色列","url":"https://www.douyin.com/hot/2526750","hotScore":7706068,"normalizedScore":5000,"source":"douyin-hot"},{"title":"喀麦隆职工子女探访项目","url":"https://www.kuaishou.com/short-video/3x7gdj5knttmtqg","hotScore":9869000,"normalizedScore":4944,"source":"kuaishou-hot"},{"title":"王鹤棣包场白鹿莫离","url":"https://s.weibo.com/weibo?q=%23%E7%8E%8B%E9%B9%A4%E6%A3%A3%E5%8C%85%E5%9C%BA%E7%99%BD%E9%B9%BF%E8%8E%AB%E7%A6%BB%23&t=31&band_rank=17&Refer=top","hotScore":84049,"normalizedScore":4930,"source":"weibo-search"},{"title":"主力资金在抛弃哪些板块","url":"https://so.toutiao.com/search?keyword=主力资金在抛弃哪些板块","hotScore":2438015,"normalizedScore":4925,"source":"toutiao-search"},{"title":"全球市场在恐惧什么","url":"https://www.baidu.com/s?wd=%E5%85%A8%E7%90%83%E5%B8%82%E5%9C%BA%E5%9C%A8%E6%81%90%E6%83%A7%E4%BB%80%E4%B9%88&sa=fyb_news&rsv_dl=fyb_news","hotScore":5128969,"normalizedScore":4833,"source":"baidu-hot"},{"title":"我曾踏平了孤川 西风走马","url":"https://www.douyin.com/hot/2527657","hotScore":7705491,"normalizedScore":4833,"source":"douyin-hot"},{"title":"阿姨买充电宝被问要一万还是两万","url":"https://www.kuaishou.com/short-video/3xncgqsqgthi5bi","hotScore":9867000,"normalizedScore":4831,"source":"kuaishou-hot"},{"title":"李小冉咋了","url":"https://s.weibo.com/weibo?q=%23%E6%9D%8E%E5%B0%8F%E5%86%89%E5%92%8B%E4%BA%86%23&t=31&band_rank=25&Refer=top","hotScore":80209,"normalizedScore":4789,"source":"weibo-search"},{"title":"何超琼清仓美高梅股份","url":"https://so.toutiao.com/search?keyword=何超琼清仓美高梅股份","hotScore":2387091,"normalizedScore":4776,"source":"toutiao-search"},{"title":"潘良被开除党籍","url":"https://www.kuaishou.com/short-video/3xikqp2d2s9xhwq","hotScore":9842000,"normalizedScore":4719,"source":"kuaishou-hot"},{"title":"三峡水运新通道开工","url":"https://www.baidu.com/s?wd=%E4%B8%89%E5%B3%A1%E6%B0%B4%E8%BF%90%E6%96%B0%E9%80%9A%E9%81%93%E5%BC%80%E5%B7%A5&sa=fyb_news&rsv_dl=fyb_news","hotScore":5042969,"normalizedScore":4667,"source":"baidu-hot"},{"title":"我的电蚊拍比烟花闪","url":"https://www.douyin.com/hot/2526642","hotScore":7705301,"normalizedScore":4667,"source":"douyin-hot"},{"title":"现货黄金跌破4300美元关口","url":"https://s.weibo.com/weibo?q=%23%E7%8E%B0%E8%B4%A7%E9%BB%84%E9%87%91%E8%B7%8C%E7%A0%B44300%E7%BE%8E%E5%85%83%E5%85%B3%E5%8F%A3%23&t=31&band_rank=23&Refer=top","hotScore":80157,"normalizedScore":4648,"source":"weibo-search"},{"title":"《奔跑吧》节目组致歉","url":"https://so.toutiao.com/search?keyword=《奔跑吧》节目组致歉","hotScore":2159929,"normalizedScore":4627,"source":"toutiao-search"},{"title":"高考作文","url":"https://www.kuaishou.com/short-video/3xsarjc4xa6evuy","hotScore":9819000,"normalizedScore":4607,"source":"kuaishou-hot"},{"title":"BLG 1:3 不敌 WE","url":"https://www.zhihu.com/search?q=BLG 1:3 不敌 WE","hotScore":5,"normalizedScore":4545,"source":"zhihu-search"},{"title":"奔跑吧","url":"https://s.weibo.com/weibo?q=%E5%A5%94%E8%B7%91%E5%90%A7&t=31&band_rank=23&Refer=top","hotScore":80110,"normalizedScore":4507,"source":"weibo-search"},{"title":"智能眼镜成偷拍“神器”？Rokid回应","url":"https://www.baidu.com/s?wd=%E6%99%BA%E8%83%BD%E7%9C%BC%E9%95%9C%E6%88%90%E5%81%B7%E6%8B%8D%E2%80%9C%E7%A5%9E%E5%99%A8%E2%80%9D%EF%BC%9FRokid%E5%9B%9E%E5%BA%94&sa=fyb_news&rsv_dl=fyb_news","hotScore":4954902,"normalizedScore":4500,"source":"baidu-hot"},{"title":"为什么家长不能接受孩子是普通人","url":"https://www.douyin.com/hot/2527559","hotScore":7704681,"normalizedScore":4500,"source":"douyin-hot"},{"title":"暂无在菲中国公民伤亡","url":"https://www.kuaishou.com/short-video/3xnt7ayt4yppv5g","hotScore":9796000,"normalizedScore":4494,"source":"kuaishou-hot"},{"title":"考生谈高考英语：出题人很“温柔”","url":"https://so.toutiao.com/search?keyword=考生谈高考英语：出题人很“温柔”","hotScore":2071892,"normalizedScore":4478,"source":"toutiao-search"},{"title":"我不是他妈 我只是被感动的路人","url":"https://www.kuaishou.com/short-video/3x4xdfe276nujsk","hotScore":9788000,"normalizedScore":4382,"source":"kuaishou-hot"},{"title":"伊朗打击以色列两处军事基地","url":"https://s.weibo.com/weibo?q=%23%E4%BC%8A%E6%9C%97%E6%89%93%E5%87%BB%E4%BB%A5%E8%89%B2%E5%88%97%E4%B8%A4%E5%A4%84%E5%86%9B%E4%BA%8B%E5%9F%BA%E5%9C%B0%23&t=31&band_rank=36&Refer=top","hotScore":80043,"normalizedScore":4366,"source":"weibo-search"},{"title":"伊朗宣布停止对以色列的军事行动","url":"https://www.baidu.com/s?wd=%E4%BC%8A%E6%9C%97%E5%AE%A3%E5%B8%83%E5%81%9C%E6%AD%A2%E5%AF%B9%E4%BB%A5%E8%89%B2%E5%88%97%E7%9A%84%E5%86%9B%E4%BA%8B%E8%A1%8C%E5%8A%A8&sa=fyb_news&rsv_dl=fyb_news","hotScore":4830960,"normalizedScore":4333,"source":"baidu-hot"},{"title":"叹不尽相思苦忆华年","url":"https://www.douyin.com/hot/2527360","hotScore":7702808,"normalizedScore":4333,"source":"douyin-hot"},{"title":"四赴高考数学老师晒三年高考成绩单","url":"https://so.toutiao.com/search?keyword=四赴高考数学老师晒三年高考成绩单","hotScore":1954385,"normalizedScore":4328,"source":"toutiao-search"},{"title":"雷霆阴乐家","url":"https://www.kuaishou.com/short-video/3x9ymn2fzxg989i","hotScore":9774000,"normalizedScore":4270,"source":"kuaishou-hot"},{"title":"司机避开远光灯惊见多人车道聚餐","url":"https://s.weibo.com/weibo?q=%23%E5%8F%B8%E6%9C%BA%E9%81%BF%E5%BC%80%E8%BF%9C%E5%85%89%E7%81%AF%E6%83%8A%E8%A7%81%E5%A4%9A%E4%BA%BA%E8%BD%A6%E9%81%93%E8%81%9A%E9%A4%90%23&t=31&band_rank=19&Refer=top","hotScore":79974,"normalizedScore":4225,"source":"weibo-search"},{"title":"考生出考场被问问题只说了“难”字","url":"https://so.toutiao.com/search?keyword=考生出考场被问问题只说了“难”字","hotScore":1768400,"normalizedScore":4179,"source":"toutiao-search"},{"title":"李小冉发文回应与张月撞歌","url":"https://www.baidu.com/s?wd=%E6%9D%8E%E5%B0%8F%E5%86%89%E5%8F%91%E6%96%87%E5%9B%9E%E5%BA%94%E4%B8%8E%E5%BC%A0%E6%9C%88%E6%92%9E%E6%AD%8C&sa=fyb_news&rsv_dl=fyb_news","hotScore":4751403,"normalizedScore":4167,"source":"baidu-hot"},{"title":"王源文淇新片怀疑世界是剧本","url":"https://www.douyin.com/hot/2526938","hotScore":7702255,"normalizedScore":4167,"source":"douyin-hot"},{"title":"12岁足球小将的出圈之路","url":"https://www.kuaishou.com/short-video/3xws8n8gwj9vguc","hotScore":9770000,"normalizedScore":4157,"source":"kuaishou-hot"},{"title":"女子减肥戒碳水暴瘦头秃了一大片","url":"https://s.weibo.com/weibo?q=%23%E5%A5%B3%E5%AD%90%E5%87%8F%E8%82%A5%E6%88%92%E7%A2%B3%E6%B0%B4%E6%9A%B4%E7%98%A6%E5%A4%B4%E7%A7%83%E4%BA%86%E4%B8%80%E5%A4%A7%E7%89%87%23&t=31&band_rank=27&Refer=top","hotScore":79905,"normalizedScore":4085,"source":"weibo-search"},{"title":"高考作文恋爱脑掉沟里","url":"https://www.kuaishou.com/short-video/3xbg9m3sq4ur6e9","hotScore":9761000,"normalizedScore":4045,"source":"kuaishou-hot"},{"title":"《给阿嬷的情书》看哭中天小姐姐","url":"https://so.toutiao.com/search?keyword=《给阿嬷的情书》看哭中天小姐姐","hotScore":1600115,"normalizedScore":4030,"source":"toutiao-search"},{"title":"为什么汽车公司要忙着自研智驾芯片","url":"https://www.baidu.com/s?wd=%E4%B8%BA%E4%BB%80%E4%B9%88%E6%B1%BD%E8%BD%A6%E5%85%AC%E5%8F%B8%E8%A6%81%E5%BF%99%E7%9D%80%E8%87%AA%E7%A0%94%E6%99%BA%E9%A9%BE%E8%8A%AF%E7%89%87&sa=fyb_news&rsv_dl=fyb_news","hotScore":4645408,"normalizedScore":4000,"source":"baidu-hot"},{"title":"新疆小羊哥的班味肉眼可见地浓了","url":"https://www.douyin.com/hot/2527717","hotScore":7700181,"normalizedScore":4000,"source":"douyin-hot"},{"title":"千万别和年纪大的导师开玩笑","url":"https://s.weibo.com/weibo?q=%E5%8D%83%E4%B8%87%E5%88%AB%E5%92%8C%E5%B9%B4%E7%BA%AA%E5%A4%A7%E7%9A%84%E5%AF%BC%E5%B8%88%E5%BC%80%E7%8E%A9%E7%AC%91&t=31&band_rank=22&Refer=top","hotScore":79787,"normalizedScore":3944,"source":"weibo-search"},{"title":"弥勒特警护送考生取回证件","url":"https://www.kuaishou.com/short-video/3xz88gpwy4nsgve","hotScore":9747000,"normalizedScore":3933,"source":"kuaishou-hot"},{"title":"房子的旧逻辑真的要结束了吗","url":"https://so.toutiao.com/search?keyword=房子的旧逻辑真的要结束了吗","hotScore":1447844,"normalizedScore":3881,"source":"toutiao-search"},{"title":"医生称孩子长大自然瘦是认识误区","url":"https://www.baidu.com/s?wd=%E5%8C%BB%E7%94%9F%E7%A7%B0%E5%AD%A9%E5%AD%90%E9%95%BF%E5%A4%A7%E8%87%AA%E7%84%B6%E7%98%A6%E6%98%AF%E8%AE%A4%E8%AF%86%E8%AF%AF%E5%8C%BA&sa=fyb_news&rsv_dl=fyb_news","hotScore":4574316,"normalizedScore":3833,"source":"baidu-hot"},{"title":"历史二卷 盲人摸象","url":"https://www.douyin.com/hot/2527227","hotScore":7693933,"normalizedScore":3833,"source":"douyin-hot"},{"title":"华哥良子花胖体验三人自行车","url":"https://www.kuaishou.com/short-video/3x3wxb7mz8csgzk","hotScore":9741000,"normalizedScore":3820,"source":"kuaishou-hot"},{"title":"人一旦有了电动车就定型了","url":"https://s.weibo.com/weibo?q=%E4%BA%BA%E4%B8%80%E6%97%A6%E6%9C%89%E4%BA%86%E7%94%B5%E5%8A%A8%E8%BD%A6%E5%B0%B1%E5%AE%9A%E5%9E%8B%E4%BA%86&t=31&band_rank=25&Refer=top","hotScore":79739,"normalizedScore":3803,"source":"weibo-search"},{"title":"53岁老师背起一米八受伤学生赴考","url":"https://so.toutiao.com/search?keyword=53岁老师背起一米八受伤学生赴考","hotScore":1310063,"normalizedScore":3731,"source":"toutiao-search"},{"title":"零交流搭档干活默契","url":"https://www.kuaishou.com/short-video/3xyqdpmxafi34aa","hotScore":9723000,"normalizedScore":3708,"source":"kuaishou-hot"},{"title":"高考答题时间有人搞特殊？这个可以有","url":"https://www.baidu.com/s?wd=%E9%AB%98%E8%80%83%E7%AD%94%E9%A2%98%E6%97%B6%E9%97%B4%E6%9C%89%E4%BA%BA%E6%90%9E%E7%89%B9%E6%AE%8A%EF%BC%9F%E8%BF%99%E4%B8%AA%E5%8F%AF%E4%BB%A5%E6%9C%89&sa=fyb_news&rsv_dl=fyb_news","hotScore":4461198,"normalizedScore":3667,"source":"baidu-hot"},{"title":"三角洲S10新干员曝光","url":"https://www.douyin.com/hot/2527123","hotScore":7690953,"normalizedScore":3667,"source":"douyin-hot"},{"title":"多省历史试卷文白倒挂","url":"https://s.weibo.com/weibo?q=%E5%A4%9A%E7%9C%81%E5%8E%86%E5%8F%B2%E8%AF%95%E5%8D%B7%E6%96%87%E7%99%BD%E5%80%92%E6%8C%82&t=31&band_rank=47&Refer=top","hotScore":79672,"normalizedScore":3662,"source":"weibo-search"},{"title":"高考时间","url":"https://www.zhihu.com/search?q=高考时间","hotScore":4,"normalizedScore":3636,"source":"zhihu-search"},{"title":"福建高考生驾考免体检","url":"https://www.kuaishou.com/short-video/3xq8tqiq3m8t7va","hotScore":9720000,"normalizedScore":3596,"source":"kuaishou-hot"},{"title":"重庆女生自信发言：英语so easy","url":"https://so.toutiao.com/search?keyword=重庆女生自信发言：英语so%20easy","hotScore":1185394,"normalizedScore":3582,"source":"toutiao-search"},{"title":"农村自建房的真实成本","url":"https://s.weibo.com/weibo?q=%E5%86%9C%E6%9D%91%E8%87%AA%E5%BB%BA%E6%88%BF%E7%9A%84%E7%9C%9F%E5%AE%9E%E6%88%90%E6%9C%AC&t=31&band_rank=37&Refer=top","hotScore":79583,"normalizedScore":3521,"source":"weibo-search"},{"title":"苏炳添拟获广东省自然科学奖二等奖","url":"https://www.baidu.com/s?wd=%E8%8B%8F%E7%82%B3%E6%B7%BB%E6%8B%9F%E8%8E%B7%E5%B9%BF%E4%B8%9C%E7%9C%81%E8%87%AA%E7%84%B6%E7%A7%91%E5%AD%A6%E5%A5%96%E4%BA%8C%E7%AD%89%E5%A5%96&sa=fyb_news&rsv_dl=fyb_news","hotScore":4367713,"normalizedScore":3500,"source":"baidu-hot"},{"title":"青春是本写不完的旧书","url":"https://www.douyin.com/hot/2527254","hotScore":7690030,"normalizedScore":3500,"source":"douyin-hot"},{"title":"安徽考场外满身泥的父亲找到了","url":"https://www.kuaishou.com/short-video/3xapzyhd4e3cbc2","hotScore":9719000,"normalizedScore":3483,"source":"kuaishou-hot"},{"title":"尼克斯晒总决赛主场地板和灯光效果","url":"https://so.toutiao.com/search?keyword=尼克斯晒总决赛主场地板和灯光效果","hotScore":1177166,"normalizedScore":3433,"source":"toutiao-search"},{"title":"黄灿灿陈凯琳是妈妈是女儿","url":"https://s.weibo.com/weibo?q=%23%E9%BB%84%E7%81%BF%E7%81%BF%E9%99%88%E5%87%AF%E7%90%B3%E6%98%AF%E5%A6%88%E5%A6%88%E6%98%AF%E5%A5%B3%E5%84%BF%23&t=31&band_rank=15&Refer=top","hotScore":79519,"normalizedScore":3380,"source":"weibo-search"},{"title":"日本已实现 “火山自由”","url":"https://www.kuaishou.com/short-video/3xjfabd3yi2ni4m","hotScore":9694000,"normalizedScore":3371,"source":"kuaishou-hot"},{"title":"工地小伙用水泥自制器材坚持健身","url":"https://www.baidu.com/s?wd=%E5%B7%A5%E5%9C%B0%E5%B0%8F%E4%BC%99%E7%94%A8%E6%B0%B4%E6%B3%A5%E8%87%AA%E5%88%B6%E5%99%A8%E6%9D%90%E5%9D%9A%E6%8C%81%E5%81%A5%E8%BA%AB&sa=fyb_news&rsv_dl=fyb_news","hotScore":4276326,"normalizedScore":3333,"source":"baidu-hot"},{"title":"安妮海瑟薇逃出绝命街定档暑期","url":"https://www.douyin.com/hot/2526921","hotScore":7680040,"normalizedScore":3333,"source":"douyin-hot"},{"title":"张月直接离场了","url":"https://so.toutiao.com/search?keyword=张月直接离场了","hotScore":1072589,"normalizedScore":3284,"source":"toutiao-search"},{"title":"浙江高考技术不难","url":"https://www.kuaishou.com/short-video/3xmmrsp7hjcp8f2","hotScore":9671000,"normalizedScore":3258,"source":"kuaishou-hot"},{"title":"朋友圈新增搜索功能","url":"https://s.weibo.com/weibo?q=%23%E6%9C%8B%E5%8F%8B%E5%9C%88%E6%96%B0%E5%A2%9E%E6%90%9C%E7%B4%A2%E5%8A%9F%E8%83%BD%23&t=31&band_rank=45&Refer=top","hotScore":79453,"normalizedScore":3239,"source":"weibo-search"},{"title":"南宁一物流园遭遇超15级龙卷风","url":"https://www.baidu.com/s?wd=%E5%8D%97%E5%AE%81%E4%B8%80%E7%89%A9%E6%B5%81%E5%9B%AD%E9%81%AD%E9%81%87%E8%B6%8515%E7%BA%A7%E9%BE%99%E5%8D%B7%E9%A3%8E&sa=fyb_news&rsv_dl=fyb_news","hotScore":4191166,"normalizedScore":3167,"source":"baidu-hot"},{"title":"苹果iOS 27看点前瞻","url":"https://www.douyin.com/hot/2526458","hotScore":7678295,"normalizedScore":3167,"source":"douyin-hot"},{"title":"李在明：日方应先向韩方真诚道歉","url":"https://www.kuaishou.com/short-video/3xhre3bbrk9dxam","hotScore":9665000,"normalizedScore":3146,"source":"kuaishou-hot"},{"title":"媒体：高考作文命题改革让人耳目一新","url":"https://so.toutiao.com/search?keyword=媒体：高考作文命题改革让人耳目一新","hotScore":1065144,"normalizedScore":3134,"source":"toutiao-search"},{"title":"浪七暂停浪三强势回归","url":"https://s.weibo.com/weibo?q=%E6%B5%AA%E4%B8%83%E6%9A%82%E5%81%9C%E6%B5%AA%E4%B8%89%E5%BC%BA%E5%8A%BF%E5%9B%9E%E5%BD%92&t=31&band_rank=2&Refer=top","hotScore":79339,"normalizedScore":3099,"source":"weibo-search"},{"title":"牵丝戏翻唱","url":"https://www.kuaishou.com/short-video/3xbwtr7ggd7vmm9","hotScore":9660000,"normalizedScore":3034,"source":"kuaishou-hot"},{"title":"藏马熊当牧民面捕食牦牛 当地回应","url":"https://www.baidu.com/s?wd=%E8%97%8F%E9%A9%AC%E7%86%8A%E5%BD%93%E7%89%A7%E6%B0%91%E9%9D%A2%E6%8D%95%E9%A3%9F%E7%89%A6%E7%89%9B+%E5%BD%93%E5%9C%B0%E5%9B%9E%E5%BA%94&sa=fyb_news&rsv_dl=fyb_news","hotScore":4071916,"normalizedScore":3000,"source":"baidu-hot"},{"title":"哈兰德想来重庆吃轻轨","url":"https://www.douyin.com/hot/2527104","hotScore":7677515,"normalizedScore":3000,"source":"douyin-hot"},{"title":"膳魔师在中美召回百万件产品","url":"https://so.toutiao.com/search?keyword=膳魔师在中美召回百万件产品","hotScore":970518,"normalizedScore":2985,"source":"toutiao-search"},{"title":"刺棠 卢昱晓","url":"https://s.weibo.com/weibo?q=%E5%88%BA%E6%A3%A0%20%E5%8D%A2%E6%98%B1%E6%99%93&t=31&band_rank=14&Refer=top","hotScore":79298,"normalizedScore":2958,"source":"weibo-search"},{"title":"日本富士山演习引警惕","url":"https://www.kuaishou.com/short-video/3xxjfpgnih3g2c6","hotScore":9643000,"normalizedScore":2921,"source":"kuaishou-hot"},{"title":"胜宏科技“电梯门”风波影响几何","url":"https://so.toutiao.com/search?keyword=胜宏科技“电梯门”风波影响几何","hotScore":930961,"normalizedScore":2836,"source":"toutiao-search"},{"title":"考生眼镜“散架” 警医联动成功抢修","url":"https://www.baidu.com/s?wd=%E8%80%83%E7%94%9F%E7%9C%BC%E9%95%9C%E2%80%9C%E6%95%A3%E6%9E%B6%E2%80%9D+%E8%AD%A6%E5%8C%BB%E8%81%94%E5%8A%A8%E6%88%90%E5%8A%9F%E6%8A%A2%E4%BF%AE&sa=fyb_news&rsv_dl=fyb_news","hotScore":3972084,"normalizedScore":2833,"source":"baidu-hot"},{"title":"高考历史","url":"https://www.douyin.com/hot/2526768","hotScore":7676249,"normalizedScore":2833,"source":"douyin-hot"},{"title":"WBG无缘EWC","url":"https://s.weibo.com/weibo?q=%23WBG%E6%97%A0%E7%BC%98EWC%23&t=31&band_rank=49&Refer=top","hotScore":79215,"normalizedScore":2817,"source":"weibo-search"},{"title":"咱们家的瓶子能生财","url":"https://www.kuaishou.com/short-video/3x6xtf4di4pu5ka","hotScore":9622000,"normalizedScore":2809,"source":"kuaishou-hot"},{"title":"2026高考日程表","url":"https://www.zhihu.com/search?q=2026高考日程表","hotScore":3,"normalizedScore":2727,"source":"zhihu-search"},{"title":"宝鸡多部门高考现场护航","url":"https://www.kuaishou.com/short-video/3xzu6rucz7e7e92","hotScore":9616000,"normalizedScore":2697,"source":"kuaishou-hot"},{"title":"吴磊被河南的菜量惊到了","url":"https://so.toutiao.com/search?keyword=吴磊被河南的菜量惊到了","hotScore":878161,"normalizedScore":2687,"source":"toutiao-search"},{"title":"Jennie这个舞台疯子","url":"https://s.weibo.com/weibo?q=Jennie%E8%BF%99%E4%B8%AA%E8%88%9E%E5%8F%B0%E7%96%AF%E5%AD%90&t=31&band_rank=35&Refer=top","hotScore":79135,"normalizedScore":2676,"source":"weibo-search"},{"title":"南宁一小区楼顶露台柱子被雷劈碎","url":"https://www.baidu.com/s?wd=%E5%8D%97%E5%AE%81%E4%B8%80%E5%B0%8F%E5%8C%BA%E6%A5%BC%E9%A1%B6%E9%9C%B2%E5%8F%B0%E6%9F%B1%E5%AD%90%E8%A2%AB%E9%9B%B7%E5%8A%88%E7%A2%8E&sa=fyb_news&rsv_dl=fyb_news","hotScore":3970596,"normalizedScore":2667,"source":"baidu-hot"},{"title":"世界杯应援妆轻松get","url":"https://www.douyin.com/hot/2527454","hotScore":7674030,"normalizedScore":2667,"source":"douyin-hot"},{"title":"来听听考生们高考后最想做什么","url":"https://www.kuaishou.com/short-video/3xtgcy9es6r23em","hotScore":9589000,"normalizedScore":2584,"source":"kuaishou-hot"},{"title":"马来西亚女子徒步失踪14天后被发现","url":"https://so.toutiao.com/search?keyword=马来西亚女子徒步失踪14天后被发现","hotScore":794593,"normalizedScore":2537,"source":"toutiao-search"},{"title":"十二星座本周好运tips","url":"https://s.weibo.com/weibo?q=%E5%8D%81%E4%BA%8C%E6%98%9F%E5%BA%A7%E6%9C%AC%E5%91%A8%E5%A5%BD%E8%BF%90tips&t=31&band_rank=31&Refer=top","hotScore":79049,"normalizedScore":2535,"source":"weibo-search"},{"title":"多位市民路遇三轮车侧翻救下爷孙","url":"https://www.baidu.com/s?wd=%E5%A4%9A%E4%BD%8D%E5%B8%82%E6%B0%91%E8%B7%AF%E9%81%87%E4%B8%89%E8%BD%AE%E8%BD%A6%E4%BE%A7%E7%BF%BB%E6%95%91%E4%B8%8B%E7%88%B7%E5%AD%99&sa=fyb_news&rsv_dl=fyb_news","hotScore":3882862,"normalizedScore":2500,"source":"baidu-hot"},{"title":"高考物理","url":"https://www.douyin.com/hot/2526766","hotScore":7668777,"normalizedScore":2500,"source":"douyin-hot"},{"title":"山东乐陵6村土地被悄卖","url":"https://www.kuaishou.com/short-video/3xa8ncqg3d782ec","hotScore":9573000,"normalizedScore":2472,"source":"kuaishou-hot"},{"title":"朝鲜欢迎最尊重的贵宾","url":"https://s.weibo.com/weibo?q=%23%E6%9C%9D%E9%B2%9C%E6%AC%A2%E8%BF%8E%E6%9C%80%E5%B0%8A%E9%87%8D%E7%9A%84%E8%B4%B5%E5%AE%BE%23&t=31&band_rank=30&Refer=top","hotScore":79002,"normalizedScore":2394,"source":"weibo-search"},{"title":"外交部回应对朝鲜半岛问题立场","url":"https://so.toutiao.com/search?keyword=外交部回应对朝鲜半岛问题立场","hotScore":718978,"normalizedScore":2388,"source":"toutiao-search"},{"title":"老铁在菲律宾出差称被晃飞好几次","url":"https://www.kuaishou.com/short-video/3x8t6jxvr5q45v9","hotScore":9569000,"normalizedScore":2360,"source":"kuaishou-hot"},{"title":"五粮液换帅 56岁本土国企老将接棒","url":"https://www.baidu.com/s?wd=%E4%BA%94%E7%B2%AE%E6%B6%B2%E6%8D%A2%E5%B8%85+56%E5%B2%81%E6%9C%AC%E5%9C%9F%E5%9B%BD%E4%BC%81%E8%80%81%E5%B0%86%E6%8E%A5%E6%A3%92&sa=fyb_news&rsv_dl=fyb_news","hotScore":3874356,"normalizedScore":2333,"source":"baidu-hot"},{"title":"光绕过你天使般的脸","url":"https://www.douyin.com/hot/2526573","hotScore":7660422,"normalizedScore":2333,"source":"douyin-hot"},{"title":"刘浩存主角收官发文","url":"https://s.weibo.com/weibo?q=%23%E5%88%98%E6%B5%A9%E5%AD%98%E4%B8%BB%E8%A7%92%E6%94%B6%E5%AE%98%E5%8F%91%E6%96%87%23&t=31&band_rank=48&Refer=top","hotScore":78880,"normalizedScore":2254,"source":"weibo-search"},{"title":"代露娃跳手势舞美得很轻松","url":"https://www.kuaishou.com/short-video/3xm68dqynxdnrci","hotScore":9567000,"normalizedScore":2247,"source":"kuaishou-hot"},{"title":"今年高考英语难不难","url":"https://so.toutiao.com/search?keyword=今年高考英语难不难","hotScore":650558,"normalizedScore":2239,"source":"toutiao-search"},{"title":"王鹤棣杰伦布朗探班合照曝光","url":"https://www.baidu.com/s?wd=%E7%8E%8B%E9%B9%A4%E6%A3%A3%E6%9D%B0%E4%BC%A6%E5%B8%83%E6%9C%97%E6%8E%A2%E7%8F%AD%E5%90%88%E7%85%A7%E6%9B%9D%E5%85%89&sa=fyb_news&rsv_dl=fyb_news","hotScore":3782999,"normalizedScore":2167,"source":"baidu-hot"},{"title":"南部档案小分队集合","url":"https://www.douyin.com/hot/2527725","hotScore":7660369,"normalizedScore":2167,"source":"douyin-hot"},{"title":"陕西高速桥梁垮塌系未按图纸施工","url":"https://www.kuaishou.com/short-video/3xumg843up8nk84","hotScore":9550000,"normalizedScore":2135,"source":"kuaishou-hot"},{"title":"高考特别有宿命感","url":"https://s.weibo.com/weibo?q=%E9%AB%98%E8%80%83%E7%89%B9%E5%88%AB%E6%9C%89%E5%AE%BF%E5%91%BD%E6%84%9F&t=31&band_rank=27&Refer=top","hotScore":78800,"normalizedScore":2113,"source":"weibo-search"},{"title":"日本开始在南鸟岛部署导弹发射装置","url":"https://so.toutiao.com/search?keyword=日本开始在南鸟岛部署导弹发射装置","hotScore":588649,"normalizedScore":2090,"source":"toutiao-search"},{"title":"海事执法人员霸气喊话台舰","url":"https://www.kuaishou.com/short-video/3xkejrycu9hpa8e","hotScore":9541000,"normalizedScore":2022,"source":"kuaishou-hot"},{"title":"报告称全球60%流量来自AI和机器人","url":"https://www.baidu.com/s?wd=%E6%8A%A5%E5%91%8A%E7%A7%B0%E5%85%A8%E7%90%8360%25%E6%B5%81%E9%87%8F%E6%9D%A5%E8%87%AAAI%E5%92%8C%E6%9C%BA%E5%99%A8%E4%BA%BA&sa=fyb_news&rsv_dl=fyb_news","hotScore":3679839,"normalizedScore":2000,"source":"baidu-hot"},{"title":"新疆小羊哥19岁累成了39岁","url":"https://www.douyin.com/hot/2527161","hotScore":7658732,"normalizedScore":2000,"source":"douyin-hot"},{"title":"郑钦文世界排名跌至第122位","url":"https://s.weibo.com/weibo?q=%23%E9%83%91%E9%92%A6%E6%96%87%E4%B8%96%E7%95%8C%E6%8E%92%E5%90%8D%E8%B7%8C%E8%87%B3%E7%AC%AC122%E4%BD%8D%23&t=31&band_rank=34&Refer=top","hotScore":78750,"normalizedScore":1972,"source":"weibo-search"},{"title":"考完理综考生直呼太简单","url":"https://so.toutiao.com/search?keyword=考完理综考生直呼太简单","hotScore":584563,"normalizedScore":1940,"source":"toutiao-search"},{"title":"驻菲大使馆提醒中国公民远离海边","url":"https://www.kuaishou.com/short-video/3xr34fd6fw5aff9","hotScore":9518000,"normalizedScore":1910,"source":"kuaishou-hot"},{"title":"《歌手》全员回应排名","url":"https://www.baidu.com/s?wd=%E3%80%8A%E6%AD%8C%E6%89%8B%E3%80%8B%E5%85%A8%E5%91%98%E5%9B%9E%E5%BA%94%E6%8E%92%E5%90%8D&sa=fyb_news&rsv_dl=fyb_news","hotScore":3677418,"normalizedScore":1833,"source":"baidu-hot"},{"title":"翘楚男团喊麦特别的你笑疯了","url":"https://www.douyin.com/hot/2527621","hotScore":7657255,"normalizedScore":1833,"source":"douyin-hot"},{"title":"史上最贵的吻","url":"https://s.weibo.com/weibo?q=%23%E5%8F%B2%E4%B8%8A%E6%9C%80%E8%B4%B5%E7%9A%84%E5%90%BB%23&t=31&band_rank=40&Refer=top","hotScore":78647,"normalizedScore":1831,"source":"weibo-search"},{"title":"监考时怎么打发时间","url":"https://www.zhihu.com/search?q=监考时怎么打发时间","hotScore":2,"normalizedScore":1818,"source":"zhihu-search"},{"title":"考生出考场第一件事：我妈呢","url":"https://www.kuaishou.com/short-video/3x3xwfwcsmjsvha","hotScore":9509000,"normalizedScore":1798,"source":"kuaishou-hot"},{"title":"李在明批评以色列侵犯人权主权","url":"https://so.toutiao.com/search?keyword=李在明批评以色列侵犯人权主权","hotScore":532632,"normalizedScore":1791,"source":"toutiao-search"},{"title":"新能源小车卖不动了","url":"https://s.weibo.com/weibo?q=%23%E6%96%B0%E8%83%BD%E6%BA%90%E5%B0%8F%E8%BD%A6%E5%8D%96%E4%B8%8D%E5%8A%A8%E4%BA%86%23&t=31&band_rank=8&Refer=top","hotScore":78615,"normalizedScore":1690,"source":"weibo-search"},{"title":"黄仁勋建议趁便宜买入半导体","url":"https://www.kuaishou.com/short-video/3xqz9ey2simm7rw","hotScore":9500000,"normalizedScore":1685,"source":"kuaishou-hot"},{"title":"西藏文旅：发视频图文点赞达标打钱","url":"https://www.baidu.com/s?wd=%E8%A5%BF%E8%97%8F%E6%96%87%E6%97%85%EF%BC%9A%E5%8F%91%E8%A7%86%E9%A2%91%E5%9B%BE%E6%96%87%E7%82%B9%E8%B5%9E%E8%BE%BE%E6%A0%87%E6%89%93%E9%92%B1&sa=fyb_news&rsv_dl=fyb_news","hotScore":3585738,"normalizedScore":1667,"source":"baidu-hot"},{"title":"西湖的荷花开了 我们什么时候去看","url":"https://www.douyin.com/hot/2526835","hotScore":7656250,"normalizedScore":1667,"source":"douyin-hot"},{"title":"湖北宜昌生态移栽2000多棵树木","url":"https://so.toutiao.com/search?keyword=湖北宜昌生态移栽2000多棵树木","hotScore":481945,"normalizedScore":1642,"source":"toutiao-search"},{"title":"我才退网X个月你咋长这样了","url":"https://www.kuaishou.com/short-video/3xfcv6syq498iyw","hotScore":9474000,"normalizedScore":1573,"source":"kuaishou-hot"},{"title":"高考英语","url":"https://s.weibo.com/weibo?q=%E9%AB%98%E8%80%83%E8%8B%B1%E8%AF%AD&t=31&band_rank=29&Refer=top","hotScore":78519,"normalizedScore":1549,"source":"weibo-search"},{"title":"北京高考英语作文：帮李华写信谈AI","url":"https://www.baidu.com/s?wd=%E5%8C%97%E4%BA%AC%E9%AB%98%E8%80%83%E8%8B%B1%E8%AF%AD%E4%BD%9C%E6%96%87%EF%BC%9A%E5%B8%AE%E6%9D%8E%E5%8D%8E%E5%86%99%E4%BF%A1%E8%B0%88AI&sa=fyb_news&rsv_dl=fyb_news","hotScore":3508765,"normalizedScore":1500,"source":"baidu-hot"},{"title":"高考作文为何每年刷屏","url":"https://www.douyin.com/hot/2526376","hotScore":7654486,"normalizedScore":1500,"source":"douyin-hot"},{"title":"NBA总决赛正变成唐斯的正名之战吗","url":"https://so.toutiao.com/search?keyword=NBA总决赛正变成唐斯的正名之战吗","hotScore":478600,"normalizedScore":1493,"source":"toutiao-search"},{"title":"理想L9等红灯冒烟","url":"https://www.kuaishou.com/short-video/3xk5gvwn6ked3x9","hotScore":9473000,"normalizedScore":1461,"source":"kuaishou-hot"},{"title":"喜笑颜凯","url":"https://s.weibo.com/weibo?q=%E5%96%9C%E7%AC%91%E9%A2%9C%E5%87%AF&t=31&band_rank=21&Refer=top","hotScore":78481,"normalizedScore":1408,"source":"weibo-search"},{"title":"沈阳交警40分钟取回证件","url":"https://www.kuaishou.com/short-video/3xvijtd8uwmax2s","hotScore":9453000,"normalizedScore":1348,"source":"kuaishou-hot"},{"title":"高考物理结束有考生直呼“难爆了”","url":"https://so.toutiao.com/search?keyword=高考物理结束有考生直呼“难爆了”","hotScore":436082,"normalizedScore":1343,"source":"toutiao-search"},{"title":"阿里新设Token Foundry事业部","url":"https://www.baidu.com/s?wd=%E9%98%BF%E9%87%8C%E6%96%B0%E8%AE%BEToken+Foundry%E4%BA%8B%E4%B8%9A%E9%83%A8&sa=fyb_news&rsv_dl=fyb_news","hotScore":3497728,"normalizedScore":1333,"source":"baidu-hot"},{"title":"小米17T Pro首发评测","url":"https://www.douyin.com/hot/2527420","hotScore":7651799,"normalizedScore":1333,"source":"douyin-hot"},{"title":"代斯回复陈凯琳","url":"https://s.weibo.com/weibo?q=%23%E4%BB%A3%E6%96%AF%E5%9B%9E%E5%A4%8D%E9%99%88%E5%87%AF%E7%90%B3%23&t=31&band_rank=38&Refer=top","hotScore":78366,"normalizedScore":1268,"source":"weibo-search"},{"title":"琵琶行原唱祝福考生","url":"https://www.kuaishou.com/short-video/3xm354x3vs7rabk","hotScore":9450000,"normalizedScore":1236,"source":"kuaishou-hot"},{"title":"“馆长”喊台湾民众去大陆看看","url":"https://so.toutiao.com/search?keyword=“馆长”喊台湾民众去大陆看看","hotScore":394583,"normalizedScore":1194,"source":"toutiao-search"},{"title":"一图看懂美加墨世界杯","url":"https://www.baidu.com/s?wd=%E4%B8%80%E5%9B%BE%E7%9C%8B%E6%87%82%E7%BE%8E%E5%8A%A0%E5%A2%A8%E4%B8%96%E7%95%8C%E6%9D%AF&sa=fyb_news&rsv_dl=fyb_news","hotScore":3418562,"normalizedScore":1167,"source":"baidu-hot"},{"title":"晒出我的报恩榴莲","url":"https://www.douyin.com/hot/2526791","hotScore":7650906,"normalizedScore":1167,"source":"douyin-hot"},{"title":"张月的情商","url":"https://s.weibo.com/weibo?q=%23%E5%BC%A0%E6%9C%88%E7%9A%84%E6%83%85%E5%95%86%23&t=31&band_rank=4&Refer=top","hotScore":53959,"normalizedScore":1127,"source":"weibo-search"},{"title":"诡秘身高差这一块","url":"https://www.kuaishou.com/short-video/3x5vv6jwdrhnvn2","hotScore":9443000,"normalizedScore":1124,"source":"kuaishou-hot"},{"title":"货车司机与他的狗搭子“五福”","url":"https://so.toutiao.com/search?keyword=货车司机与他的狗搭子“五福”","hotScore":357033,"normalizedScore":1045,"source":"toutiao-search"},{"title":"跳绳一分钟多少个","url":"https://www.kuaishou.com/short-video/3x3rs7nb6byeize","hotScore":9437000,"normalizedScore":1011,"source":"kuaishou-hot"},{"title":"哈兰德听了中国球迷创作的哈兰德之歌","url":"https://www.baidu.com/s?wd=%E5%93%88%E5%85%B0%E5%BE%B7%E5%90%AC%E4%BA%86%E4%B8%AD%E5%9B%BD%E7%90%83%E8%BF%B7%E5%88%9B%E4%BD%9C%E7%9A%84%E5%93%88%E5%85%B0%E5%BE%B7%E4%B9%8B%E6%AD%8C&sa=fyb_news&rsv_dl=fyb_news","hotScore":3339890,"normalizedScore":1000,"source":"baidu-hot"},{"title":"全球泡面争霸赛来袭","url":"https://www.douyin.com/hot/2526995","hotScore":7649733,"normalizedScore":1000,"source":"douyin-hot"},{"title":"全新Siri暂未入华","url":"https://s.weibo.com/weibo?q=%23%E5%85%A8%E6%96%B0Siri%E6%9A%82%E6%9C%AA%E5%85%A5%E5%8D%8E%23&t=31&band_rank=14&Refer=top","hotScore":45581,"normalizedScore":986,"source":"weibo-search"},{"title":"高考押题","url":"https://www.zhihu.com/search?q=高考押题","hotScore":1,"normalizedScore":909,"source":"zhihu-search"},{"title":"膳魔师中国召回400万食物罐","url":"https://www.kuaishou.com/short-video/3x7k8t3rqfyfub2","hotScore":9431000,"normalizedScore":899,"source":"kuaishou-hot"},{"title":"广东高考英语作文李华缺席","url":"https://so.toutiao.com/search?keyword=广东高考英语作文李华缺席","hotScore":329949,"normalizedScore":896,"source":"toutiao-search"},{"title":"李小冉 我不配","url":"https://s.weibo.com/weibo?q=%E6%9D%8E%E5%B0%8F%E5%86%89%20%E6%88%91%E4%B8%8D%E9%85%8D&t=31&band_rank=32&Refer=top","hotScore":41370,"normalizedScore":845,"source":"weibo-search"},{"title":"司机不熟悉路线 考生求助骁骑送考","url":"https://www.baidu.com/s?wd=%E5%8F%B8%E6%9C%BA%E4%B8%8D%E7%86%9F%E6%82%89%E8%B7%AF%E7%BA%BF+%E8%80%83%E7%94%9F%E6%B1%82%E5%8A%A9%E9%AA%81%E9%AA%91%E9%80%81%E8%80%83&sa=fyb_news&rsv_dl=fyb_news","hotScore":3300601,"normalizedScore":833,"source":"baidu-hot"},{"title":"BABYMONSTER回归","url":"https://www.douyin.com/hot/2526954","hotScore":7641060,"normalizedScore":833,"source":"douyin-hot"},{"title":"伊朗民众集会庆祝回击以色列","url":"https://www.kuaishou.com/short-video/3xgspm7abh3mheg","hotScore":9424000,"normalizedScore":787,"source":"kuaishou-hot"},{"title":"猴哥花篮掉了假装撒花","url":"https://so.toutiao.com/search?keyword=猴哥花篮掉了假装撒花","hotScore":323057,"normalizedScore":746,"source":"toutiao-search"},{"title":"熬夜看WWDC26","url":"https://s.weibo.com/weibo?q=%E7%86%AC%E5%A4%9C%E7%9C%8BWWDC26&t=31&band_rank=37&Refer=top","hotScore":41369,"normalizedScore":704,"source":"weibo-search"},{"title":"朝方举行盛大欢迎仪式","url":"https://www.kuaishou.com/short-video/3xdvxv5ytq8vzck","hotScore":9395000,"normalizedScore":674,"source":"kuaishou-hot"},{"title":"西安一考生物理增加23分钟作答时间","url":"https://www.baidu.com/s?wd=%E8%A5%BF%E5%AE%89%E4%B8%80%E8%80%83%E7%94%9F%E7%89%A9%E7%90%86%E5%A2%9E%E5%8A%A023%E5%88%86%E9%92%9F%E4%BD%9C%E7%AD%94%E6%97%B6%E9%97%B4&sa=fyb_news&rsv_dl=fyb_news","hotScore":3242246,"normalizedScore":667,"source":"baidu-hot"},{"title":"当我尝试做汉尼拔的菜谱","url":"https://www.douyin.com/hot/2526284","hotScore":7640232,"normalizedScore":667,"source":"douyin-hot"},{"title":"菲律宾强震已造成32人死亡","url":"https://so.toutiao.com/search?keyword=菲律宾强震已造成32人死亡","hotScore":292314,"normalizedScore":597,"source":"toutiao-search"},{"title":"张慧雯凌晨五点多收到姐姐们的安慰信息","url":"https://s.weibo.com/weibo?q=%23%E5%BC%A0%E6%85%A7%E9%9B%AF%E5%87%8C%E6%99%A8%E4%BA%94%E7%82%B9%E5%A4%9A%E6%94%B6%E5%88%B0%E5%A7%90%E5%A7%90%E4%BB%AC%E7%9A%84%E5%AE%89%E6%85%B0%E4%BF%A1%E6%81%AF%23&t=31&band_rank=48&Refer=top","hotScore":41365,"normalizedScore":563,"source":"weibo-search"},{"title":"高考期间谁来了都得静音","url":"https://www.kuaishou.com/short-video/3xh2dsepu5s9r7a","hotScore":9366000,"normalizedScore":562,"source":"kuaishou-hot"},{"title":"世界杯产品义乌为何能卖出“溢价”","url":"https://www.baidu.com/s?wd=%E4%B8%96%E7%95%8C%E6%9D%AF%E4%BA%A7%E5%93%81%E4%B9%89%E4%B9%8C%E4%B8%BA%E4%BD%95%E8%83%BD%E5%8D%96%E5%87%BA%E2%80%9C%E6%BA%A2%E4%BB%B7%E2%80%9D&sa=fyb_news&rsv_dl=fyb_news","hotScore":3211896,"normalizedScore":500,"source":"baidu-hot"},{"title":"在郑州也是吃上冰牛奶了","url":"https://www.douyin.com/hot/2526251","hotScore":7639109,"normalizedScore":500,"source":"douyin-hot"},{"title":"张月方停止浪姐选歌","url":"https://www.kuaishou.com/short-video/3xez4uzfzrci5su","hotScore":9344000,"normalizedScore":449,"source":"kuaishou-hot"},{"title":"以色列暂停对伊朗袭击","url":"https://so.toutiao.com/search?keyword=以色列暂停对伊朗袭击","hotScore":264497,"normalizedScore":448,"source":"toutiao-search"},{"title":"黄灿灿说曾沛慈的好有目共睹","url":"https://s.weibo.com/weibo?q=%23%E9%BB%84%E7%81%BF%E7%81%BF%E8%AF%B4%E6%9B%BE%E6%B2%9B%E6%85%88%E7%9A%84%E5%A5%BD%E6%9C%89%E7%9B%AE%E5%85%B1%E7%9D%B9%23&t=31&band_rank=46&Refer=top","hotScore":41364,"normalizedScore":423,"source":"weibo-search"},{"title":"华彩台球世界公开赛刘俊岩夺冠","url":"https://www.kuaishou.com/short-video/3xbjn2r5nfzffui","hotScore":9323000,"normalizedScore":337,"source":"kuaishou-hot"},{"title":"苹果：中国大陆暂不提供最新Siri AI","url":"https://www.baidu.com/s?wd=%E8%8B%B9%E6%9E%9C%EF%BC%9A%E4%B8%AD%E5%9B%BD%E5%A4%A7%E9%99%86%E6%9A%82%E4%B8%8D%E6%8F%90%E4%BE%9B%E6%9C%80%E6%96%B0Siri+AI&sa=fyb_news&rsv_dl=fyb_news","hotScore":3201006,"normalizedScore":333,"source":"baidu-hot"},{"title":"不是我忧郁是滤镜太高级","url":"https://www.douyin.com/hot/2527655","hotScore":7631531,"normalizedScore":333,"source":"douyin-hot"},{"title":"英伟达数据中心成本大涨影响几何","url":"https://so.toutiao.com/search?keyword=英伟达数据中心成本大涨影响几何","hotScore":237665,"normalizedScore":299,"source":"toutiao-search"},{"title":"浪姐选歌结果","url":"https://s.weibo.com/weibo?q=%23%E6%B5%AA%E5%A7%90%E9%80%89%E6%AD%8C%E7%BB%93%E6%9E%9C%23&t=31&band_rank=39&Refer=top","hotScore":41361,"normalizedScore":282,"source":"weibo-search"},{"title":"大厂月薪13万疯抢AI人才","url":"https://www.kuaishou.com/short-video/3xvf4p96pnftaq9","hotScore":9300000,"normalizedScore":225,"source":"kuaishou-hot"},{"title":"苹果终于有节假日闹钟了","url":"https://www.baidu.com/s?wd=%E8%8B%B9%E6%9E%9C%E7%BB%88%E4%BA%8E%E6%9C%89%E8%8A%82%E5%81%87%E6%97%A5%E9%97%B9%E9%92%9F%E4%BA%86&sa=fyb_news&rsv_dl=fyb_news","hotScore":3120718,"normalizedScore":167,"source":"baidu-hot"},{"title":"12岁上中科大的他后悔了吗","url":"https://www.douyin.com/hot/2526977","hotScore":7630807,"normalizedScore":167,"source":"douyin-hot"},{"title":"大摩为何喊出“抛售是健康调整”","url":"https://so.toutiao.com/search?keyword=大摩为何喊出“抛售是健康调整”","hotScore":229572,"normalizedScore":149,"source":"toutiao-search"},{"title":"曝浪姐节目组劝李小冉换歌","url":"https://s.weibo.com/weibo?q=%23%E6%9B%9D%E6%B5%AA%E5%A7%90%E8%8A%82%E7%9B%AE%E7%BB%84%E5%8A%9D%E6%9D%8E%E5%B0%8F%E5%86%89%E6%8D%A2%E6%AD%8C%23&t=31&band_rank=20&Refer=top","hotScore":27821,"normalizedScore":141,"source":"weibo-search"},{"title":"朝方礼宾车队护卫驶过凯旋门","url":"https://www.kuaishou.com/short-video/3xax2rrbshnyjcg","hotScore":9233000,"normalizedScore":112,"source":"kuaishou-hot"}]