[{"title":"Babycare山茶花检出甲酰胺","url":"https://s.weibo.com/weibo?q=%23Babycare%E5%B1%B1%E8%8C%B6%E8%8A%B1%E6%A3%80%E5%87%BA%E7%94%B2%E9%85%B0%E8%83%BA%23&t=31&band_rank=1&Refer=top","hotScore":1161153,"normalizedScore":9855,"source":"weibo-search"},{"title":"少年拿下高考数学满分已被清华录取","url":"https://so.toutiao.com/search?keyword=少年拿下高考数学满分已被清华录取","hotScore":30531424,"normalizedScore":9855,"source":"toutiao-search"},{"title":"“吃住行全管、免学费、月发1200元”","url":"https://www.baidu.com/s?wd=%E2%80%9C%E5%90%83%E4%BD%8F%E8%A1%8C%E5%85%A8%E7%AE%A1%E3%80%81%E5%85%8D%E5%AD%A6%E8%B4%B9%E3%80%81%E6%9C%88%E5%8F%911200%E5%85%83%E2%80%9D&sa=fyb_news&rsv_dl=fyb_news","hotScore":7808700,"normalizedScore":9833,"source":"baidu-hot"},{"title":"四川2026高考分数线公布","url":"https://www.douyin.com/hot/2547489","hotScore":12126600,"normalizedScore":9831,"source":"douyin-hot"},{"title":"晗少高考成绩","url":"https://www.kuaishou.com/short-video/3xt3jjj2qdqvncg","hotScore":13251000,"normalizedScore":9800,"source":"kuaishou-hot"},{"title":"6图看电子商务如何做强做优做大","url":"https://s.weibo.com/weibo?q=%236%E5%9B%BE%E7%9C%8B%E7%94%B5%E5%AD%90%E5%95%86%E5%8A%A1%E5%A6%82%E4%BD%95%E5%81%9A%E5%BC%BA%E5%81%9A%E4%BC%98%E5%81%9A%E5%A4%A7%23&t=31&band_rank=3&Refer=top","hotScore":748209,"normalizedScore":9710,"source":"weibo-search"},{"title":"警方回应多人拉女子“浸猪笼”游行","url":"https://so.toutiao.com/search?keyword=警方回应多人拉女子“浸猪笼”游行","hotScore":27625975,"normalizedScore":9710,"source":"toutiao-search"},{"title":"作文以去世父亲为题男生高考653分","url":"https://www.baidu.com/s?wd=%E4%BD%9C%E6%96%87%E4%BB%A5%E5%8E%BB%E4%B8%96%E7%88%B6%E4%BA%B2%E4%B8%BA%E9%A2%98%E7%94%B7%E7%94%9F%E9%AB%98%E8%80%83653%E5%88%86&sa=fyb_news&rsv_dl=fyb_news","hotScore":7713133,"normalizedScore":9667,"source":"baidu-hot"},{"title":"当我把旅行做成票根","url":"https://www.douyin.com/hot/2545739","hotScore":12105298,"normalizedScore":9661,"source":"douyin-hot"},{"title":"07年少女贩毒208次","url":"https://www.kuaishou.com/short-video/3xzehuyuy2adyik","hotScore":12604000,"normalizedScore":9600,"source":"kuaishou-hot"},{"title":"吴谨言 产后发胖受益人","url":"https://s.weibo.com/weibo?q=%E5%90%B4%E8%B0%A8%E8%A8%80%20%E4%BA%A7%E5%90%8E%E5%8F%91%E8%83%96%E5%8F%97%E7%9B%8A%E4%BA%BA&t=31&band_rank=11&Refer=top","hotScore":399874,"normalizedScore":9565,"source":"weibo-search"},{"title":"“中国链”何以成为链接未来的必选项","url":"https://so.toutiao.com/search?keyword=“中国链”何以成为链接未来的必选项","hotScore":24997016,"normalizedScore":9565,"source":"toutiao-search"},{"title":"看绿色农业链如何变废为宝","url":"https://www.baidu.com/s?wd=%E7%9C%8B%E7%BB%BF%E8%89%B2%E5%86%9C%E4%B8%9A%E9%93%BE%E5%A6%82%E4%BD%95%E5%8F%98%E5%BA%9F%E4%B8%BA%E5%AE%9D&sa=fyb_news&rsv_dl=fyb_news","hotScore":7616654,"normalizedScore":9500,"source":"baidu-hot"},{"title":"高考出分名场面","url":"https://www.douyin.com/hot/2546588","hotScore":11859490,"normalizedScore":9492,"source":"douyin-hot"},{"title":"田曦薇张凌赫 格子衬衫粉色内搭","url":"https://s.weibo.com/weibo?q=%E7%94%B0%E6%9B%A6%E8%96%87%E5%BC%A0%E5%87%8C%E8%B5%AB%20%E6%A0%BC%E5%AD%90%E8%A1%AC%E8%A1%AB%E7%B2%89%E8%89%B2%E5%86%85%E6%90%AD&t=31&band_rank=14&Refer=top","hotScore":390063,"normalizedScore":9420,"source":"weibo-search"},{"title":"13岁女孩称遭强奸警方已刑事立案","url":"https://so.toutiao.com/search?keyword=13岁女孩称遭强奸警方已刑事立案","hotScore":22618235,"normalizedScore":9420,"source":"toutiao-search"},{"title":"我国发电装机突破40亿千瓦","url":"https://www.kuaishou.com/short-video/3x4kubnw8cpes9c","hotScore":12279000,"normalizedScore":9400,"source":"kuaishou-hot"},{"title":"奶奶微信上有77万条未读消息","url":"https://www.baidu.com/s?wd=%E5%A5%B6%E5%A5%B6%E5%BE%AE%E4%BF%A1%E4%B8%8A%E6%9C%8977%E4%B8%87%E6%9D%A1%E6%9C%AA%E8%AF%BB%E6%B6%88%E6%81%AF&sa=fyb_news&rsv_dl=fyb_news","hotScore":7521476,"normalizedScore":9333,"source":"baidu-hot"},{"title":"今年全国小麦再获丰收","url":"https://www.douyin.com/hot/2547693","hotScore":11826177,"normalizedScore":9322,"source":"douyin-hot"},{"title":"问心2被打码的医生是谁","url":"https://s.weibo.com/weibo?q=%23%E9%97%AE%E5%BF%832%E8%A2%AB%E6%89%93%E7%A0%81%E7%9A%84%E5%8C%BB%E7%94%9F%E6%98%AF%E8%B0%81%23&t=31&band_rank=10&Refer=top","hotScore":367981,"normalizedScore":9275,"source":"weibo-search"},{"title":"香港演员苗金凤离世","url":"https://so.toutiao.com/search?keyword=香港演员苗金凤离世","hotScore":20465826,"normalizedScore":9275,"source":"toutiao-search"},{"title":"苹果官宣多款产品涨价","url":"https://www.kuaishou.com/short-video/3x32js95bui8zjm","hotScore":11954000,"normalizedScore":9200,"source":"kuaishou-hot"},{"title":"你对AI脸产生生理性厌恶了吗","url":"https://www.baidu.com/s?wd=%E4%BD%A0%E5%AF%B9AI%E8%84%B8%E4%BA%A7%E7%94%9F%E7%94%9F%E7%90%86%E6%80%A7%E5%8E%8C%E6%81%B6%E4%BA%86%E5%90%97&sa=fyb_news&rsv_dl=fyb_news","hotScore":7424265,"normalizedScore":9167,"source":"baidu-hot"},{"title":"第一视角体验毕业典礼","url":"https://www.douyin.com/hot/2546974","hotScore":11618686,"normalizedScore":9153,"source":"douyin-hot"},{"title":"杨超越 代言口碑","url":"https://s.weibo.com/weibo?q=%E6%9D%A8%E8%B6%85%E8%B6%8A%20%E4%BB%A3%E8%A8%80%E5%8F%A3%E7%A2%91&t=31&band_rank=19&Refer=top","hotScore":323096,"normalizedScore":9130,"source":"weibo-search"},{"title":"两男女要求转账500亿在香港银行被抓","url":"https://so.toutiao.com/search?keyword=两男女要求转账500亿在香港银行被抓","hotScore":18518245,"normalizedScore":9130,"source":"toutiao-search"},{"title":"河南高考出分","url":"https://www.zhihu.com/search?q=河南高考出分","hotScore":10,"normalizedScore":9091,"source":"zhihu-search"},{"title":"世界杯套餐3块薯饼500元人民币","url":"https://www.baidu.com/s?wd=%E4%B8%96%E7%95%8C%E6%9D%AF%E5%A5%97%E9%A4%903%E5%9D%97%E8%96%AF%E9%A5%BC500%E5%85%83%E4%BA%BA%E6%B0%91%E5%B8%81&sa=fyb_news&rsv_dl=fyb_news","hotScore":7331271,"normalizedScore":9000,"source":"baidu-hot"},{"title":"侮辱张桂梅网民被行拘","url":"https://www.kuaishou.com/short-video/3xujjnuxe7ubj7i","hotScore":11734000,"normalizedScore":9000,"source":"kuaishou-hot"},{"title":"曝童锦程认孩子了","url":"https://s.weibo.com/weibo?q=%23%E6%9B%9D%E7%AB%A5%E9%94%A6%E7%A8%8B%E8%AE%A4%E5%AD%A9%E5%AD%90%E4%BA%86%23&t=31&band_rank=24&Refer=top","hotScore":304935,"normalizedScore":8986,"source":"weibo-search"},{"title":"苹果官宣涨价","url":"https://so.toutiao.com/search?keyword=苹果官宣涨价","hotScore":16756001,"normalizedScore":8986,"source":"toutiao-search"},{"title":"高考后的独白","url":"https://www.douyin.com/hot/2546594","hotScore":10950916,"normalizedScore":8983,"source":"douyin-hot"},{"title":"田曦薇爱豆级别的机场出发图","url":"https://s.weibo.com/weibo?q=%23%E7%94%B0%E6%9B%A6%E8%96%87%E7%88%B1%E8%B1%86%E7%BA%A7%E5%88%AB%E7%9A%84%E6%9C%BA%E5%9C%BA%E5%87%BA%E5%8F%91%E5%9B%BE%23&t=31&band_rank=28&Refer=top","hotScore":248899,"normalizedScore":8841,"source":"weibo-search"},{"title":"电影《抓特务》差在了哪","url":"https://so.toutiao.com/search?keyword=电影《抓特务》差在了哪","hotScore":16433306,"normalizedScore":8841,"source":"toutiao-search"},{"title":"高考分数线全部公布！汇总来了","url":"https://www.baidu.com/s?wd=%E9%AB%98%E8%80%83%E5%88%86%E6%95%B0%E7%BA%BF%E5%85%A8%E9%83%A8%E5%85%AC%E5%B8%83%EF%BC%81%E6%B1%87%E6%80%BB%E6%9D%A5%E4%BA%86&sa=fyb_news&rsv_dl=fyb_news","hotScore":7238520,"normalizedScore":8833,"source":"baidu-hot"},{"title":"第一视角查分vlog","url":"https://www.douyin.com/hot/2546586","hotScore":10794344,"normalizedScore":8814,"source":"douyin-hot"},{"title":"印度女子和情人将未婚夫推下山谷","url":"https://www.kuaishou.com/short-video/3x2qbic9be6g4sc","hotScore":11296000,"normalizedScore":8800,"source":"kuaishou-hot"},{"title":"赵丽颖不进组被认为明智","url":"https://s.weibo.com/weibo?q=%E8%B5%B5%E4%B8%BD%E9%A2%96%E4%B8%8D%E8%BF%9B%E7%BB%84%E8%A2%AB%E8%AE%A4%E4%B8%BA%E6%98%8E%E6%99%BA&t=31&band_rank=31&Refer=top","hotScore":218913,"normalizedScore":8696,"source":"weibo-search"},{"title":"男子田里遇眼镜蛇直接上手弹脑瓜崩","url":"https://so.toutiao.com/search?keyword=男子田里遇眼镜蛇直接上手弹脑瓜崩","hotScore":15161456,"normalizedScore":8696,"source":"toutiao-search"},{"title":"两男女欲转账500亿在香港银行被抓","url":"https://www.baidu.com/s?wd=%E4%B8%A4%E7%94%B7%E5%A5%B3%E6%AC%B2%E8%BD%AC%E8%B4%A6500%E4%BA%BF%E5%9C%A8%E9%A6%99%E6%B8%AF%E9%93%B6%E8%A1%8C%E8%A2%AB%E6%8A%93&sa=fyb_news&rsv_dl=fyb_news","hotScore":7140432,"normalizedScore":8667,"source":"baidu-hot"},{"title":"柯秉逸说回去必须加练","url":"https://www.douyin.com/hot/2547485","hotScore":9510388,"normalizedScore":8644,"source":"douyin-hot"},{"title":"委内瑞拉设2亿美元初始基金赈灾","url":"https://www.kuaishou.com/short-video/3xhxwvzfasvkgy4","hotScore":11085000,"normalizedScore":8600,"source":"kuaishou-hot"},{"title":"苗金凤去世","url":"https://s.weibo.com/weibo?q=%23%E8%8B%97%E9%87%91%E5%87%A4%E5%8E%BB%E4%B8%96%23&t=31&band_rank=32&Refer=top","hotScore":218693,"normalizedScore":8551,"source":"weibo-search"},{"title":"693分高考生刚上高中时成绩全校中游","url":"https://so.toutiao.com/search?keyword=693分高考生刚上高中时成绩全校中游","hotScore":13718653,"normalizedScore":8551,"source":"toutiao-search"},{"title":"13岁男孩失联多日被找到：靠喝水存活","url":"https://www.baidu.com/s?wd=13%E5%B2%81%E7%94%B7%E5%AD%A9%E5%A4%B1%E8%81%94%E5%A4%9A%E6%97%A5%E8%A2%AB%E6%89%BE%E5%88%B0%EF%BC%9A%E9%9D%A0%E5%96%9D%E6%B0%B4%E5%AD%98%E6%B4%BB&sa=fyb_news&rsv_dl=fyb_news","hotScore":7045256,"normalizedScore":8500,"source":"baidu-hot"},{"title":"火影玩家全员兄弟佐助","url":"https://www.douyin.com/hot/2547157","hotScore":9406688,"normalizedScore":8475,"source":"douyin-hot"},{"title":"有家长自费送检纸尿裤检出甲酰胺","url":"https://s.weibo.com/weibo?q=%23%E6%9C%89%E5%AE%B6%E9%95%BF%E8%87%AA%E8%B4%B9%E9%80%81%E6%A3%80%E7%BA%B8%E5%B0%BF%E8%A3%A4%E6%A3%80%E5%87%BA%E7%94%B2%E9%85%B0%E8%83%BA%23&t=31&band_rank=33&Refer=top","hotScore":217751,"normalizedScore":8406,"source":"weibo-search"},{"title":"专家：东风快递可摧毁10万吨核航母","url":"https://so.toutiao.com/search?keyword=专家：东风快递可摧毁10万吨核航母","hotScore":12413150,"normalizedScore":8406,"source":"toutiao-search"},{"title":"≈","url":"https://www.kuaishou.com/short-video/3xdrm62asptjjtu","hotScore":10875000,"normalizedScore":8400,"source":"kuaishou-hot"},{"title":"海南考生高考794分 称发挥失常","url":"https://www.baidu.com/s?wd=%E6%B5%B7%E5%8D%97%E8%80%83%E7%94%9F%E9%AB%98%E8%80%83794%E5%88%86+%E7%A7%B0%E5%8F%91%E6%8C%A5%E5%A4%B1%E5%B8%B8&sa=fyb_news&rsv_dl=fyb_news","hotScore":6953617,"normalizedScore":8333,"source":"baidu-hot"},{"title":"萍乡小炒一口鲜辣香到上头","url":"https://www.douyin.com/hot/2547360","hotScore":9389089,"normalizedScore":8305,"source":"douyin-hot"},{"title":"王一博窦靖童香奈儿七夕大片","url":"https://s.weibo.com/weibo?q=%E7%8E%8B%E4%B8%80%E5%8D%9A%E7%AA%A6%E9%9D%96%E7%AB%A5%E9%A6%99%E5%A5%88%E5%84%BF%E4%B8%83%E5%A4%95%E5%A4%A7%E7%89%87&t=31&band_rank=36&Refer=top","hotScore":216544,"normalizedScore":8261,"source":"weibo-search"},{"title":"“天津大港区域即将通地铁”不实","url":"https://so.toutiao.com/search?keyword=“天津大港区域即将通地铁”不实","hotScore":11231883,"normalizedScore":8261,"source":"toutiao-search"},{"title":"高考出分名场面","url":"https://www.kuaishou.com/short-video/3xth3tjcbnycfti","hotScore":10673000,"normalizedScore":8200,"source":"kuaishou-hot"},{"title":"gta6","url":"https://www.zhihu.com/search?q=gta6","hotScore":9,"normalizedScore":8182,"source":"zhihu-search"},{"title":"“天津大港区域即将通地铁”不实","url":"https://www.baidu.com/s?wd=%E2%80%9C%E5%A4%A9%E6%B4%A5%E5%A4%A7%E6%B8%AF%E5%8C%BA%E5%9F%9F%E5%8D%B3%E5%B0%86%E9%80%9A%E5%9C%B0%E9%93%81%E2%80%9D%E4%B8%8D%E5%AE%9E&sa=fyb_news&rsv_dl=fyb_news","hotScore":6848472,"normalizedScore":8167,"source":"baidu-hot"},{"title":"59岁梁实第30次高考423分","url":"https://www.douyin.com/hot/2547701","hotScore":9315730,"normalizedScore":8136,"source":"douyin-hot"},{"title":"三球交易至森林狼","url":"https://s.weibo.com/weibo?q=%23%E4%B8%89%E7%90%83%E4%BA%A4%E6%98%93%E8%87%B3%E6%A3%AE%E6%9E%97%E7%8B%BC%23&t=31&band_rank=37&Refer=top","hotScore":207561,"normalizedScore":8116,"source":"weibo-search"},{"title":"男生复读一年从400多分到630分","url":"https://so.toutiao.com/search?keyword=男生复读一年从400多分到630分","hotScore":10163028,"normalizedScore":8116,"source":"toutiao-search"},{"title":"女孩网红景点坠湖身亡 前天刚中考完","url":"https://www.baidu.com/s?wd=%E5%A5%B3%E5%AD%A9%E7%BD%91%E7%BA%A2%E6%99%AF%E7%82%B9%E5%9D%A0%E6%B9%96%E8%BA%AB%E4%BA%A1+%E5%89%8D%E5%A4%A9%E5%88%9A%E4%B8%AD%E8%80%83%E5%AE%8C&sa=fyb_news&rsv_dl=fyb_news","hotScore":6751856,"normalizedScore":8000,"source":"baidu-hot"},{"title":"阿里巴巴市值跌破2万亿港元","url":"https://www.kuaishou.com/short-video/3xm8gns6whf79xw","hotScore":10446000,"normalizedScore":8000,"source":"kuaishou-hot"},{"title":"王橹杰眉眼","url":"https://s.weibo.com/weibo?q=%E7%8E%8B%E6%A9%B9%E6%9D%B0%E7%9C%89%E7%9C%BC&t=31&band_rank=42&Refer=top","hotScore":154051,"normalizedScore":7971,"source":"weibo-search"},{"title":"男子让情人与丈夫分居被拒后拽其跳桥","url":"https://so.toutiao.com/search?keyword=男子让情人与丈夫分居被拒后拽其跳桥","hotScore":9195888,"normalizedScore":7971,"source":"toutiao-search"},{"title":"苹果官宣涨价：iPad和Mac率先调价","url":"https://www.douyin.com/hot/2547734","hotScore":9299034,"normalizedScore":7966,"source":"douyin-hot"},{"title":"警方回应多人拉两女子“浸猪笼”游行","url":"https://www.baidu.com/s?wd=%E8%AD%A6%E6%96%B9%E5%9B%9E%E5%BA%94%E5%A4%9A%E4%BA%BA%E6%8B%89%E4%B8%A4%E5%A5%B3%E5%AD%90%E2%80%9C%E6%B5%B8%E7%8C%AA%E7%AC%BC%E2%80%9D%E6%B8%B8%E8%A1%8C&sa=fyb_news&rsv_dl=fyb_news","hotScore":6751467,"normalizedScore":7833,"source":"baidu-hot"},{"title":"学生平时考500多分高考出分考了666","url":"https://s.weibo.com/weibo?q=%23%E5%AD%A6%E7%94%9F%E5%B9%B3%E6%97%B6%E8%80%83500%E5%A4%9A%E5%88%86%E9%AB%98%E8%80%83%E5%87%BA%E5%88%86%E8%80%83%E4%BA%86666%23&t=31&band_rank=43&Refer=top","hotScore":150724,"normalizedScore":7826,"source":"weibo-search"},{"title":"国防部回应东风-17发射画面震惊美军","url":"https://so.toutiao.com/search?keyword=国防部回应东风-17发射画面震惊美军","hotScore":8320783,"normalizedScore":7826,"source":"toutiao-search"},{"title":"内蒙古自治区拨党费慰问","url":"https://www.kuaishou.com/short-video/3xzkwgtyffh4fty","hotScore":10418000,"normalizedScore":7800,"source":"kuaishou-hot"},{"title":"楚秉杰战胜柯秉逸晋级半决赛","url":"https://www.douyin.com/hot/2547344","hotScore":9238323,"normalizedScore":7797,"source":"douyin-hot"},{"title":"吴尊发文控诉国泰航空","url":"https://s.weibo.com/weibo?q=%23%E5%90%B4%E5%B0%8A%E5%8F%91%E6%96%87%E6%8E%A7%E8%AF%89%E5%9B%BD%E6%B3%B0%E8%88%AA%E7%A9%BA%23&t=31&band_rank=44&Refer=top","hotScore":148577,"normalizedScore":7681,"source":"weibo-search"},{"title":"高一学生花1个多月备战高考考620分","url":"https://so.toutiao.com/search?keyword=高一学生花1个多月备战高考考620分","hotScore":7528956,"normalizedScore":7681,"source":"toutiao-search"},{"title":"《步步惊心》播出15年后“塌房”","url":"https://www.baidu.com/s?wd=%E3%80%8A%E6%AD%A5%E6%AD%A5%E6%83%8A%E5%BF%83%E3%80%8B%E6%92%AD%E5%87%BA15%E5%B9%B4%E5%90%8E%E2%80%9C%E5%A1%8C%E6%88%BF%E2%80%9D&sa=fyb_news&rsv_dl=fyb_news","hotScore":6662313,"normalizedScore":7667,"source":"baidu-hot"},{"title":"黄健翔孙继海预测世界杯出线局势","url":"https://www.douyin.com/hot/2547030","hotScore":9192802,"normalizedScore":7627,"source":"douyin-hot"},{"title":"豆包定价最高一年6000元","url":"https://www.kuaishou.com/short-video/3xp8x6kqesqeynm","hotScore":10395000,"normalizedScore":7600,"source":"kuaishou-hot"},{"title":"白玉兰提名晚宴","url":"https://s.weibo.com/weibo?q=%E7%99%BD%E7%8E%89%E5%85%B0%E6%8F%90%E5%90%8D%E6%99%9A%E5%AE%B4&t=31&band_rank=47&Refer=top","hotScore":138740,"normalizedScore":7536,"source":"weibo-search"},{"title":"中国足协：7月1日起将启用新规","url":"https://so.toutiao.com/search?keyword=中国足协：7月1日起将启用新规","hotScore":6812481,"normalizedScore":7536,"source":"toutiao-search"},{"title":"“8枚鸡蛋接考”考生高考526分","url":"https://www.baidu.com/s?wd=%E2%80%9C8%E6%9E%9A%E9%B8%A1%E8%9B%8B%E6%8E%A5%E8%80%83%E2%80%9D%E8%80%83%E7%94%9F%E9%AB%98%E8%80%83526%E5%88%86&sa=fyb_news&rsv_dl=fyb_news","hotScore":6565790,"normalizedScore":7500,"source":"baidu-hot"},{"title":"委内瑞拉强震遇难人数升至164人","url":"https://www.douyin.com/hot/2547533","hotScore":9175398,"normalizedScore":7458,"source":"douyin-hot"},{"title":"警方回应两女子被关笼中游街","url":"https://www.kuaishou.com/short-video/3xwj6ifevi64u8k","hotScore":10369000,"normalizedScore":7400,"source":"kuaishou-hot"},{"title":"印度富二代坠亡系未婚妻和情人推下","url":"https://s.weibo.com/weibo?q=%23%E5%8D%B0%E5%BA%A6%E5%AF%8C%E4%BA%8C%E4%BB%A3%E5%9D%A0%E4%BA%A1%E7%B3%BB%E6%9C%AA%E5%A9%9A%E5%A6%BB%E5%92%8C%E6%83%85%E4%BA%BA%E6%8E%A8%E4%B8%8B%23&t=31&band_rank=48&Refer=top","hotScore":137366,"normalizedScore":7391,"source":"weibo-search"},{"title":"查分跳出“屏蔽” 班主任难掩激动","url":"https://so.toutiao.com/search?keyword=查分跳出“屏蔽”%20班主任难掩激动","hotScore":6164188,"normalizedScore":7391,"source":"toutiao-search"},{"title":"美光科技、闪迪股价大涨近20%","url":"https://www.baidu.com/s?wd=%E7%BE%8E%E5%85%89%E7%A7%91%E6%8A%80%E3%80%81%E9%97%AA%E8%BF%AA%E8%82%A1%E4%BB%B7%E5%A4%A7%E6%B6%A8%E8%BF%9120%25&sa=fyb_news&rsv_dl=fyb_news","hotScore":6477323,"normalizedScore":7333,"source":"baidu-hot"},{"title":"库拉索vs科特迪瓦","url":"https://www.douyin.com/hot/2547425","hotScore":9130178,"normalizedScore":7288,"source":"douyin-hot"},{"title":"C罗帽子戏法","url":"https://www.zhihu.com/search?q=C罗帽子戏法","hotScore":8,"normalizedScore":7273,"source":"zhihu-search"},{"title":"影视飓风Tim怎么变成老司机的","url":"https://s.weibo.com/weibo?q=%23%E5%BD%B1%E8%A7%86%E9%A3%93%E9%A3%8ETim%E6%80%8E%E4%B9%88%E5%8F%98%E6%88%90%E8%80%81%E5%8F%B8%E6%9C%BA%E7%9A%84%23&t=31&band_rank=49&Refer=top","hotScore":136662,"normalizedScore":7246,"source":"weibo-search"},{"title":"高考分数线全部公布","url":"https://so.toutiao.com/search?keyword=高考分数线全部公布","hotScore":5577588,"normalizedScore":7246,"source":"toutiao-search"},{"title":"河南高考600分及以上37544人","url":"https://www.kuaishou.com/short-video/3xhwqas3brmceyi","hotScore":10340000,"normalizedScore":7200,"source":"kuaishou-hot"},{"title":"美光科技市值首超Meta","url":"https://www.baidu.com/s?wd=%E7%BE%8E%E5%85%89%E7%A7%91%E6%8A%80%E5%B8%82%E5%80%BC%E9%A6%96%E8%B6%85Meta&sa=fyb_news&rsv_dl=fyb_news","hotScore":6370450,"normalizedScore":7167,"source":"baidu-hot"},{"title":"吴珈庆战胜薛珍麒晋级独牙四强","url":"https://www.douyin.com/hot/2547366","hotScore":9101489,"normalizedScore":7119,"source":"douyin-hot"},{"title":"发现脾胃喜欢一切温和的食物","url":"https://s.weibo.com/weibo?q=%E5%8F%91%E7%8E%B0%E8%84%BE%E8%83%83%E5%96%9C%E6%AC%A2%E4%B8%80%E5%88%87%E6%B8%A9%E5%92%8C%E7%9A%84%E9%A3%9F%E7%89%A9&t=31&band_rank=6&Refer=top","hotScore":127021,"normalizedScore":7101,"source":"weibo-search"},{"title":"李在明支持率为何暴跌","url":"https://so.toutiao.com/search?keyword=李在明支持率为何暴跌","hotScore":5046810,"normalizedScore":7101,"source":"toutiao-search"},{"title":"常熟3岁女童被杀害 嫌疑人在哺乳期","url":"https://www.baidu.com/s?wd=%E5%B8%B8%E7%86%9F3%E5%B2%81%E5%A5%B3%E7%AB%A5%E8%A2%AB%E6%9D%80%E5%AE%B3+%E5%AB%8C%E7%96%91%E4%BA%BA%E5%9C%A8%E5%93%BA%E4%B9%B3%E6%9C%9F&sa=fyb_news&rsv_dl=fyb_news","hotScore":6276297,"normalizedScore":7000,"source":"baidu-hot"},{"title":"黑耀时快手账号找到了","url":"https://www.kuaishou.com/short-video/3x9ai7hypzqapcy","hotScore":10319000,"normalizedScore":7000,"source":"kuaishou-hot"},{"title":"达沃斯论坛里的中式魅力","url":"https://s.weibo.com/weibo?q=%23%E8%BE%BE%E6%B2%83%E6%96%AF%E8%AE%BA%E5%9D%9B%E9%87%8C%E7%9A%84%E4%B8%AD%E5%BC%8F%E9%AD%85%E5%8A%9B%23&t=31&band_rank=3&Refer=top","hotScore":127021,"normalizedScore":6957,"source":"weibo-search"},{"title":"女顾客刚坐下店里瞬间坐满","url":"https://so.toutiao.com/search?keyword=女顾客刚坐下店里瞬间坐满","hotScore":4566543,"normalizedScore":6957,"source":"toutiao-search"},{"title":"厄瓜多尔vs德国","url":"https://www.douyin.com/hot/2547339","hotScore":8668334,"normalizedScore":6949,"source":"douyin-hot"},{"title":"日本主帅森保一的数学时刻又到了","url":"https://www.baidu.com/s?wd=%E6%97%A5%E6%9C%AC%E4%B8%BB%E5%B8%85%E6%A3%AE%E4%BF%9D%E4%B8%80%E7%9A%84%E6%95%B0%E5%AD%A6%E6%97%B6%E5%88%BB%E5%8F%88%E5%88%B0%E4%BA%86&sa=fyb_news&rsv_dl=fyb_news","hotScore":6179817,"normalizedScore":6833,"source":"baidu-hot"},{"title":"肖战杨紫白玉兰顶峰相见","url":"https://s.weibo.com/weibo?q=%23%E8%82%96%E6%88%98%E6%9D%A8%E7%B4%AB%E7%99%BD%E7%8E%89%E5%85%B0%E9%A1%B6%E5%B3%B0%E7%9B%B8%E8%A7%81%23&t=31&band_rank=13&Refer=top","hotScore":126994,"normalizedScore":6812,"source":"weibo-search"},{"title":"湖北高考600分及以上26883人","url":"https://so.toutiao.com/search?keyword=湖北高考600分及以上26883人","hotScore":4131979,"normalizedScore":6812,"source":"toutiao-search"},{"title":"日本发生6.9级地震","url":"https://www.kuaishou.com/short-video/3xuptmkk4jv8mgm","hotScore":10291000,"normalizedScore":6800,"source":"kuaishou-hot"},{"title":"三角洲S10卡牌玩法提前了解","url":"https://www.douyin.com/hot/2547195","hotScore":8611090,"normalizedScore":6780,"source":"douyin-hot"},{"title":"杨洋晚宴人气","url":"https://s.weibo.com/weibo?q=%E6%9D%A8%E6%B4%8B%E6%99%9A%E5%AE%B4%E4%BA%BA%E6%B0%94&t=31&band_rank=5&Refer=top","hotScore":126990,"normalizedScore":6667,"source":"weibo-search"},{"title":"拍摄者回应手臂粗巨蛇视频被指伪造","url":"https://so.toutiao.com/search?keyword=拍摄者回应手臂粗巨蛇视频被指伪造","hotScore":3738769,"normalizedScore":6667,"source":"toutiao-search"},{"title":"#全国考生正在晒分#","url":"https://www.baidu.com/s?wd=%23%E5%85%A8%E5%9B%BD%E8%80%83%E7%94%9F%E6%AD%A3%E5%9C%A8%E6%99%92%E5%88%86%23&sa=fyb_news&rsv_dl=fyb_news","hotScore":6096692,"normalizedScore":6667,"source":"baidu-hot"},{"title":"昨夜将至剧情好夯","url":"https://www.douyin.com/hot/2546961","hotScore":7840701,"normalizedScore":6610,"source":"douyin-hot"},{"title":"家有三残障女儿考618分","url":"https://www.kuaishou.com/short-video/3x7kjia2biq2e8c","hotScore":10264000,"normalizedScore":6600,"source":"kuaishou-hot"},{"title":"苹果回应涨价","url":"https://s.weibo.com/weibo?q=%23%E8%8B%B9%E6%9E%9C%E5%9B%9E%E5%BA%94%E6%B6%A8%E4%BB%B7%23&t=31&band_rank=2&Refer=top","hotScore":126979,"normalizedScore":6522,"source":"weibo-search"},{"title":"山东高考分数线公布","url":"https://so.toutiao.com/search?keyword=山东高考分数线公布","hotScore":3382978,"normalizedScore":6522,"source":"toutiao-search"},{"title":"高考查分","url":"https://www.baidu.com/s?wd=%E9%AB%98%E8%80%83%E6%9F%A5%E5%88%86&sa=fyb_news&rsv_dl=fyb_news","hotScore":5985865,"normalizedScore":6500,"source":"baidu-hot"},{"title":"日本vs瑞典","url":"https://www.douyin.com/hot/2547468","hotScore":7838195,"normalizedScore":6441,"source":"douyin-hot"},{"title":"贩卖低俗淫秽手办获刑","url":"https://www.kuaishou.com/short-video/3xk6s46cf4ijvrk","hotScore":10242000,"normalizedScore":6400,"source":"kuaishou-hot"},{"title":"网传检出甲酰胺的报告已撤回","url":"https://s.weibo.com/weibo?q=%23%E7%BD%91%E4%BC%A0%E6%A3%80%E5%87%BA%E7%94%B2%E9%85%B0%E8%83%BA%E7%9A%84%E6%8A%A5%E5%91%8A%E5%B7%B2%E6%92%A4%E5%9B%9E%23&t=31&band_rank=38&Refer=top","hotScore":126966,"normalizedScore":6377,"source":"weibo-search"},{"title":"13岁孩子不爱吃饭身高1.2米体重34斤","url":"https://so.toutiao.com/search?keyword=13岁孩子不爱吃饭身高1.2米体重34斤","hotScore":3061045,"normalizedScore":6377,"source":"toutiao-search"},{"title":"什么是情绪价值","url":"https://www.zhihu.com/search?q=什么是情绪价值","hotScore":7,"normalizedScore":6364,"source":"zhihu-search"},{"title":"“港剧第一贵妇”苗金凤去世","url":"https://www.baidu.com/s?wd=%E2%80%9C%E6%B8%AF%E5%89%A7%E7%AC%AC%E4%B8%80%E8%B4%B5%E5%A6%87%E2%80%9D%E8%8B%97%E9%87%91%E5%87%A4%E5%8E%BB%E4%B8%96&sa=fyb_news&rsv_dl=fyb_news","hotScore":5902276,"normalizedScore":6333,"source":"baidu-hot"},{"title":"英雄联盟新英雄洛克攻略","url":"https://www.douyin.com/hot/2547083","hotScore":7837406,"normalizedScore":6271,"source":"douyin-hot"},{"title":"苹果涨价iPhone未涨","url":"https://s.weibo.com/weibo?q=%23%E8%8B%B9%E6%9E%9C%E6%B6%A8%E4%BB%B7iPhone%E6%9C%AA%E6%B6%A8%23&t=31&band_rank=8&Refer=top","hotScore":126950,"normalizedScore":6232,"source":"weibo-search"},{"title":"A股这轮牛市你赚钱了吗","url":"https://so.toutiao.com/search?keyword=A股这轮牛市你赚钱了吗","hotScore":2769748,"normalizedScore":6232,"source":"toutiao-search"},{"title":"厄瓜多尔vs德国","url":"https://www.kuaishou.com/short-video/3xvz68uzex669uk","hotScore":10213000,"normalizedScore":6200,"source":"kuaishou-hot"},{"title":"男生复读一年从400多分到630分","url":"https://www.baidu.com/s?wd=%E7%94%B7%E7%94%9F%E5%A4%8D%E8%AF%BB%E4%B8%80%E5%B9%B4%E4%BB%8E400%E5%A4%9A%E5%88%86%E5%88%B0630%E5%88%86&sa=fyb_news&rsv_dl=fyb_news","hotScore":5807261,"normalizedScore":6167,"source":"baidu-hot"},{"title":"南非1:0韩国","url":"https://www.douyin.com/hot/2546677","hotScore":7829310,"normalizedScore":6102,"source":"douyin-hot"},{"title":"白玉兰预测","url":"https://s.weibo.com/weibo?q=%E7%99%BD%E7%8E%89%E5%85%B0%E9%A2%84%E6%B5%8B&t=31&band_rank=26&Refer=top","hotScore":126942,"normalizedScore":6087,"source":"weibo-search"},{"title":"中国AI智能体爆火世界杯","url":"https://so.toutiao.com/search?keyword=中国AI智能体爆火世界杯","hotScore":2716407,"normalizedScore":6087,"source":"toutiao-search"},{"title":"2026全球独角兽榜单出炉","url":"https://www.baidu.com/s?wd=2026%E5%85%A8%E7%90%83%E7%8B%AC%E8%A7%92%E5%85%BD%E6%A6%9C%E5%8D%95%E5%87%BA%E7%82%89&sa=fyb_news&rsv_dl=fyb_news","hotScore":5698621,"normalizedScore":6000,"source":"baidu-hot"},{"title":"中国单兵激光武器亮相","url":"https://www.kuaishou.com/short-video/3x5mdjgv5tccst2","hotScore":10183000,"normalizedScore":6000,"source":"kuaishou-hot"},{"title":"C罗球鞋上印有自己5个孩子名字","url":"https://s.weibo.com/weibo?q=%23C%E7%BD%97%E7%90%83%E9%9E%8B%E4%B8%8A%E5%8D%B0%E6%9C%89%E8%87%AA%E5%B7%B15%E4%B8%AA%E5%AD%A9%E5%AD%90%E5%90%8D%E5%AD%97%23&t=31&band_rank=10&Refer=top","hotScore":126929,"normalizedScore":5942,"source":"weibo-search"},{"title":"爸爸染红发女儿崩溃大哭","url":"https://so.toutiao.com/search?keyword=爸爸染红发女儿崩溃大哭","hotScore":2506171,"normalizedScore":5942,"source":"toutiao-search"},{"title":"奶皮子冰牛奶的风吹到了全国各地","url":"https://www.douyin.com/hot/2546917","hotScore":7823411,"normalizedScore":5932,"source":"douyin-hot"},{"title":"佛得角门将的战靴产自中国莆田","url":"https://www.baidu.com/s?wd=%E4%BD%9B%E5%BE%97%E8%A7%92%E9%97%A8%E5%B0%86%E7%9A%84%E6%88%98%E9%9D%B4%E4%BA%A7%E8%87%AA%E4%B8%AD%E5%9B%BD%E8%8E%86%E7%94%B0&sa=fyb_news&rsv_dl=fyb_news","hotScore":5613365,"normalizedScore":5833,"source":"baidu-hot"},{"title":"工地妈妈女儿考进全省前五","url":"https://www.kuaishou.com/short-video/3xzwzd9jqjf6ezg","hotScore":10130000,"normalizedScore":5800,"source":"kuaishou-hot"},{"title":"湖南两女子和狗被关笼中游街","url":"https://s.weibo.com/weibo?q=%23%E6%B9%96%E5%8D%97%E4%B8%A4%E5%A5%B3%E5%AD%90%E5%92%8C%E7%8B%97%E8%A2%AB%E5%85%B3%E7%AC%BC%E4%B8%AD%E6%B8%B8%E8%A1%97%23&t=31&band_rank=5&Refer=top","hotScore":126914,"normalizedScore":5797,"source":"weibo-search"},{"title":"民警下乡办案途中铲除15株野生大麻","url":"https://so.toutiao.com/search?keyword=民警下乡办案途中铲除15株野生大麻","hotScore":2457906,"normalizedScore":5797,"source":"toutiao-search"},{"title":"韩国输球众生相","url":"https://www.douyin.com/hot/2547173","hotScore":7808910,"normalizedScore":5763,"source":"douyin-hot"},{"title":"00后不愿意办信用卡了","url":"https://www.baidu.com/s?wd=00%E5%90%8E%E4%B8%8D%E6%84%BF%E6%84%8F%E5%8A%9E%E4%BF%A1%E7%94%A8%E5%8D%A1%E4%BA%86&sa=fyb_news&rsv_dl=fyb_news","hotScore":5502918,"normalizedScore":5667,"source":"baidu-hot"},{"title":"恋与深空新男主上线投诉飙涨万条","url":"https://s.weibo.com/weibo?q=%23%E6%81%8B%E4%B8%8E%E6%B7%B1%E7%A9%BA%E6%96%B0%E7%94%B7%E4%B8%BB%E4%B8%8A%E7%BA%BF%E6%8A%95%E8%AF%89%E9%A3%99%E6%B6%A8%E4%B8%87%E6%9D%A1%23&t=31&band_rank=18&Refer=top","hotScore":126898,"normalizedScore":5652,"source":"weibo-search"},{"title":"四川高考分数线公布","url":"https://so.toutiao.com/search?keyword=四川高考分数线公布","hotScore":2267678,"normalizedScore":5652,"source":"toutiao-search"},{"title":"榆林缉毒警徒手扒车门","url":"https://www.kuaishou.com/short-video/3x57ehb4s5c8uja","hotScore":10106000,"normalizedScore":5600,"source":"kuaishou-hot"},{"title":"内马尔赛后激动落泪","url":"https://www.douyin.com/hot/2546723","hotScore":7805351,"normalizedScore":5593,"source":"douyin-hot"},{"title":"杨幂牵杨紫上台","url":"https://s.weibo.com/weibo?q=%23%E6%9D%A8%E5%B9%82%E7%89%B5%E6%9D%A8%E7%B4%AB%E4%B8%8A%E5%8F%B0%23&t=31&band_rank=4&Refer=top","hotScore":126889,"normalizedScore":5507,"source":"weibo-search"},{"title":"物理类694分四川考生分享学习经验","url":"https://so.toutiao.com/search?keyword=物理类694分四川考生分享学习经验","hotScore":2224006,"normalizedScore":5507,"source":"toutiao-search"},{"title":"恐慌之下 有妈妈把纸尿裤塞进了烤箱","url":"https://www.baidu.com/s?wd=%E6%81%90%E6%85%8C%E4%B9%8B%E4%B8%8B+%E6%9C%89%E5%A6%88%E5%A6%88%E6%8A%8A%E7%BA%B8%E5%B0%BF%E8%A3%A4%E5%A1%9E%E8%BF%9B%E4%BA%86%E7%83%A4%E7%AE%B1&sa=fyb_news&rsv_dl=fyb_news","hotScore":5427103,"normalizedScore":5500,"source":"baidu-hot"},{"title":"高考分数线","url":"https://www.zhihu.com/search?q=高考分数线","hotScore":6,"normalizedScore":5455,"source":"zhihu-search"},{"title":"当我一直对照片不满意时","url":"https://www.douyin.com/hot/2546649","hotScore":7802979,"normalizedScore":5424,"source":"douyin-hot"},{"title":"张诗尧为内马尔回归首秀献舞","url":"https://www.kuaishou.com/short-video/3xrif69xtsz8bam","hotScore":10061000,"normalizedScore":5400,"source":"kuaishou-hot"},{"title":"本科线479考生794分嫌发挥失常","url":"https://s.weibo.com/weibo?q=%23%E6%9C%AC%E7%A7%91%E7%BA%BF479%E8%80%83%E7%94%9F794%E5%88%86%E5%AB%8C%E5%8F%91%E6%8C%A5%E5%A4%B1%E5%B8%B8%23&t=31&band_rank=12&Refer=top","hotScore":116948,"normalizedScore":5362,"source":"weibo-search"},{"title":"女孩高考查分激动落泪：我能上复旦了","url":"https://so.toutiao.com/search?keyword=女孩高考查分激动落泪：我能上复旦了","hotScore":2051880,"normalizedScore":5362,"source":"toutiao-search"},{"title":"药店老板非法出售48粒右美沙芬片获刑","url":"https://www.baidu.com/s?wd=%E8%8D%AF%E5%BA%97%E8%80%81%E6%9D%BF%E9%9D%9E%E6%B3%95%E5%87%BA%E5%94%AE48%E7%B2%92%E5%8F%B3%E7%BE%8E%E6%B2%99%E8%8A%AC%E7%89%87%E8%8E%B7%E5%88%91&sa=fyb_news&rsv_dl=fyb_news","hotScore":5415541,"normalizedScore":5333,"source":"baidu-hot"},{"title":"大狗一直叫叫叫到天荒地老","url":"https://www.douyin.com/hot/2547477","hotScore":7798567,"normalizedScore":5254,"source":"douyin-hot"},{"title":"郭京飞状态","url":"https://s.weibo.com/weibo?q=%23%E9%83%AD%E4%BA%AC%E9%A3%9E%E7%8A%B6%E6%80%81%23&t=31&band_rank=15&Refer=top","hotScore":100157,"normalizedScore":5217,"source":"weibo-search"},{"title":"钓友暴雨夜钓到118斤巨型青鱼","url":"https://so.toutiao.com/search?keyword=钓友暴雨夜钓到118斤巨型青鱼","hotScore":1856617,"normalizedScore":5217,"source":"toutiao-search"},{"title":"男子贩毒被抓当场吓瘫","url":"https://www.kuaishou.com/short-video/3xyiybbv5uvn95i","hotScore":10015000,"normalizedScore":5200,"source":"kuaishou-hot"},{"title":"黄金回到“8”字头 实探金店","url":"https://www.baidu.com/s?wd=%E9%BB%84%E9%87%91%E5%9B%9E%E5%88%B0%E2%80%9C8%E2%80%9D%E5%AD%97%E5%A4%B4+%E5%AE%9E%E6%8E%A2%E9%87%91%E5%BA%97&sa=fyb_news&rsv_dl=fyb_news","hotScore":5327902,"normalizedScore":5167,"source":"baidu-hot"},{"title":"晗少高考查分","url":"https://www.douyin.com/hot/2547190","hotScore":7792991,"normalizedScore":5085,"source":"douyin-hot"},{"title":"梁实第30次高考423分","url":"https://s.weibo.com/weibo?q=%23%E6%A2%81%E5%AE%9E%E7%AC%AC30%E6%AC%A1%E9%AB%98%E8%80%83423%E5%88%86%23&t=31&band_rank=46&Refer=top","hotScore":94169,"normalizedScore":5072,"source":"weibo-search"},{"title":"男子因汗味重被健身房退卡","url":"https://so.toutiao.com/search?keyword=男子因汗味重被健身房退卡","hotScore":1679937,"normalizedScore":5072,"source":"toutiao-search"},{"title":"刘涛看莲花血鸭被魔改当场emo","url":"https://www.baidu.com/s?wd=%E5%88%98%E6%B6%9B%E7%9C%8B%E8%8E%B2%E8%8A%B1%E8%A1%80%E9%B8%AD%E8%A2%AB%E9%AD%94%E6%94%B9%E5%BD%93%E5%9C%BAemo&sa=fyb_news&rsv_dl=fyb_news","hotScore":5225034,"normalizedScore":5000,"source":"baidu-hot"},{"title":"父母爱情张桂兰的苦难不该被忽视","url":"https://www.kuaishou.com/short-video/3xpbrbcqqkajs9w","hotScore":9960000,"normalizedScore":5000,"source":"kuaishou-hot"},{"title":"优酷不语只是一味发肖战","url":"https://s.weibo.com/weibo?q=%23%E4%BC%98%E9%85%B7%E4%B8%8D%E8%AF%AD%E5%8F%AA%E6%98%AF%E4%B8%80%E5%91%B3%E5%8F%91%E8%82%96%E6%88%98%23&t=31&band_rank=7&Refer=top","hotScore":81290,"normalizedScore":4928,"source":"weibo-search"},{"title":"8个鸡蛋接考的考生考了526分","url":"https://so.toutiao.com/search?keyword=8个鸡蛋接考的考生考了526分","hotScore":1520070,"normalizedScore":4928,"source":"toutiao-search"},{"title":"委内瑞拉1分钟2次7级以上强震","url":"https://www.douyin.com/hot/2546606","hotScore":7785168,"normalizedScore":4915,"source":"douyin-hot"},{"title":"湖北高考600分及以上26883人","url":"https://www.baidu.com/s?wd=%E6%B9%96%E5%8C%97%E9%AB%98%E8%80%83600%E5%88%86%E5%8F%8A%E4%BB%A5%E4%B8%8A26883%E4%BA%BA&sa=fyb_news&rsv_dl=fyb_news","hotScore":5130091,"normalizedScore":4833,"source":"baidu-hot"},{"title":"张钧甯原名更难认了","url":"https://www.kuaishou.com/short-video/3xku842qda9xeeq","hotScore":9933000,"normalizedScore":4800,"source":"kuaishou-hot"},{"title":"白鹿又去哪进修哭戏了","url":"https://s.weibo.com/weibo?q=%23%E7%99%BD%E9%B9%BF%E5%8F%88%E5%8E%BB%E5%93%AA%E8%BF%9B%E4%BF%AE%E5%93%AD%E6%88%8F%E4%BA%86%23&t=31&band_rank=25&Refer=top","hotScore":73521,"normalizedScore":4783,"source":"weibo-search"},{"title":"湖北分数线","url":"https://so.toutiao.com/search?keyword=湖北分数线","hotScore":1375416,"normalizedScore":4783,"source":"toutiao-search"},{"title":"超上镜纯色美甲合集来啦","url":"https://www.douyin.com/hot/2546742","hotScore":7781121,"normalizedScore":4746,"source":"douyin-hot"},{"title":"蔡磊段睿夫妇7年“破冰”之战","url":"https://www.baidu.com/s?wd=%E8%94%A1%E7%A3%8A%E6%AE%B5%E7%9D%BF%E5%A4%AB%E5%A6%877%E5%B9%B4%E2%80%9C%E7%A0%B4%E5%86%B0%E2%80%9D%E4%B9%8B%E6%88%98&sa=fyb_news&rsv_dl=fyb_news","hotScore":5040557,"normalizedScore":4667,"source":"baidu-hot"},{"title":"工位吃饭羞耻症","url":"https://s.weibo.com/weibo?q=%E5%B7%A5%E4%BD%8D%E5%90%83%E9%A5%AD%E7%BE%9E%E8%80%BB%E7%97%87&t=31&band_rank=41&Refer=top","hotScore":73305,"normalizedScore":4638,"source":"weibo-search"},{"title":"韩国记者问踢成这样是否食物中毒","url":"https://so.toutiao.com/search?keyword=韩国记者问踢成这样是否食物中毒","hotScore":1348927,"normalizedScore":4638,"source":"toutiao-search"},{"title":"男子跳舞柔韧度拉满","url":"https://www.kuaishou.com/short-video/3x8rdui7hb5nwys","hotScore":9906000,"normalizedScore":4600,"source":"kuaishou-hot"},{"title":"吴尊喊话国泰航空","url":"https://www.douyin.com/hot/2547547","hotScore":7760539,"normalizedScore":4576,"source":"douyin-hot"},{"title":"上海高考出分","url":"https://www.zhihu.com/search?q=上海高考出分","hotScore":5,"normalizedScore":4545,"source":"zhihu-search"},{"title":"长沙一对好友查分：1人屏蔽1人694分","url":"https://www.baidu.com/s?wd=%E9%95%BF%E6%B2%99%E4%B8%80%E5%AF%B9%E5%A5%BD%E5%8F%8B%E6%9F%A5%E5%88%86%EF%BC%9A1%E4%BA%BA%E5%B1%8F%E8%94%BD1%E4%BA%BA694%E5%88%86&sa=fyb_news&rsv_dl=fyb_news","hotScore":4932538,"normalizedScore":4500,"source":"baidu-hot"},{"title":"韩国 内讧","url":"https://s.weibo.com/weibo?q=%E9%9F%A9%E5%9B%BD%20%E5%86%85%E8%AE%A7&t=31&band_rank=9&Refer=top","hotScore":73268,"normalizedScore":4493,"source":"weibo-search"},{"title":"残疾女孩高考586分 想报法律专业","url":"https://so.toutiao.com/search?keyword=残疾女孩高考586分%20想报法律专业","hotScore":1244528,"normalizedScore":4493,"source":"toutiao-search"},{"title":"要P成哪样他才能发现不对劲","url":"https://www.douyin.com/hot/2546138","hotScore":7758599,"normalizedScore":4407,"source":"douyin-hot"},{"title":"昨夜将至江疏影成任重后妈了","url":"https://www.kuaishou.com/short-video/3xegsxeuf2a7n4u","hotScore":9863000,"normalizedScore":4400,"source":"kuaishou-hot"},{"title":"苹果涨价","url":"https://s.weibo.com/weibo?q=%E8%8B%B9%E6%9E%9C%E6%B6%A8%E4%BB%B7&t=31&band_rank=23&Refer=top","hotScore":73265,"normalizedScore":4348,"source":"weibo-search"},{"title":"小伙从高一垫底逆袭至年级前100名","url":"https://so.toutiao.com/search?keyword=小伙从高一垫底逆袭至年级前100名","hotScore":1220560,"normalizedScore":4348,"source":"toutiao-search"},{"title":"“霉霉”被曝7月3日举办婚礼","url":"https://www.baidu.com/s?wd=%E2%80%9C%E9%9C%89%E9%9C%89%E2%80%9D%E8%A2%AB%E6%9B%9D7%E6%9C%883%E6%97%A5%E4%B8%BE%E5%8A%9E%E5%A9%9A%E7%A4%BC&sa=fyb_news&rsv_dl=fyb_news","hotScore":4849558,"normalizedScore":4333,"source":"baidu-hot"},{"title":"广东白切鸡上综艺又被淘汰","url":"https://www.douyin.com/hot/2547109","hotScore":7745650,"normalizedScore":4237,"source":"douyin-hot"},{"title":"周杰伦演唱会劝退无票歌迷","url":"https://s.weibo.com/weibo?q=%E5%91%A8%E6%9D%B0%E4%BC%A6%E6%BC%94%E5%94%B1%E4%BC%9A%E5%8A%9D%E9%80%80%E6%97%A0%E7%A5%A8%E6%AD%8C%E8%BF%B7&t=31&band_rank=22&Refer=top","hotScore":68081,"normalizedScore":4203,"source":"weibo-search"},{"title":"为什么大多数人在牛市里反而亏钱","url":"https://so.toutiao.com/search?keyword=为什么大多数人在牛市里反而亏钱","hotScore":1126095,"normalizedScore":4203,"source":"toutiao-search"},{"title":"中国航母太快日本跟踪拍摄失败","url":"https://www.kuaishou.com/short-video/3xftjzwfskc9gzs","hotScore":9821000,"normalizedScore":4200,"source":"kuaishou-hot"},{"title":"新车车主收到换电池提醒？宝马回应","url":"https://www.baidu.com/s?wd=%E6%96%B0%E8%BD%A6%E8%BD%A6%E4%B8%BB%E6%94%B6%E5%88%B0%E6%8D%A2%E7%94%B5%E6%B1%A0%E6%8F%90%E9%86%92%EF%BC%9F%E5%AE%9D%E9%A9%AC%E5%9B%9E%E5%BA%94&sa=fyb_news&rsv_dl=fyb_news","hotScore":4744290,"normalizedScore":4167,"source":"baidu-hot"},{"title":"尹净汉退伍","url":"https://www.douyin.com/hot/2547066","hotScore":7735394,"normalizedScore":4068,"source":"douyin-hot"},{"title":"尊界","url":"https://s.weibo.com/weibo?q=%E5%B0%8A%E7%95%8C&t=31&band_rank=40&Refer=top","hotScore":66811,"normalizedScore":4058,"source":"weibo-search"},{"title":"国内第二波数码硬件涨价潮来袭","url":"https://so.toutiao.com/search?keyword=国内第二波数码硬件涨价潮来袭","hotScore":1104408,"normalizedScore":4058,"source":"toutiao-search"},{"title":"男子24万彩礼娶妻 领证后新娘找男友","url":"https://www.baidu.com/s?wd=%E7%94%B7%E5%AD%9024%E4%B8%87%E5%BD%A9%E7%A4%BC%E5%A8%B6%E5%A6%BB+%E9%A2%86%E8%AF%81%E5%90%8E%E6%96%B0%E5%A8%98%E6%89%BE%E7%94%B7%E5%8F%8B&sa=fyb_news&rsv_dl=fyb_news","hotScore":4741663,"normalizedScore":4000,"source":"baidu-hot"},{"title":"复旦中山厦门医院发现人类新基因","url":"https://www.kuaishou.com/short-video/3x86sebapqaqbxy","hotScore":9772000,"normalizedScore":4000,"source":"kuaishou-hot"},{"title":"潘玮柏听热巴爱吃眼睛都亮了","url":"https://s.weibo.com/weibo?q=%E6%BD%98%E7%8E%AE%E6%9F%8F%E5%90%AC%E7%83%AD%E5%B7%B4%E7%88%B1%E5%90%83%E7%9C%BC%E7%9D%9B%E9%83%BD%E4%BA%AE%E4%BA%86&t=31&band_rank=17&Refer=top","hotScore":66597,"normalizedScore":3913,"source":"weibo-search"},{"title":"詹俊：内马尔使巴西进攻端变化更多","url":"https://so.toutiao.com/search?keyword=詹俊：内马尔使巴西进攻端变化更多","hotScore":1018933,"normalizedScore":3913,"source":"toutiao-search"},{"title":"TA在拍纪念日而我在拍我的全世界","url":"https://www.douyin.com/hot/2547676","hotScore":7733885,"normalizedScore":3898,"source":"douyin-hot"},{"title":"员工四次配合反诈调查 护照仍被作废","url":"https://www.baidu.com/s?wd=%E5%91%98%E5%B7%A5%E5%9B%9B%E6%AC%A1%E9%85%8D%E5%90%88%E5%8F%8D%E8%AF%88%E8%B0%83%E6%9F%A5+%E6%8A%A4%E7%85%A7%E4%BB%8D%E8%A2%AB%E4%BD%9C%E5%BA%9F&sa=fyb_news&rsv_dl=fyb_news","hotScore":4661836,"normalizedScore":3833,"source":"baidu-hot"},{"title":"奥运冠军徐诗晓发禁毒倡议","url":"https://www.kuaishou.com/short-video/3xp22iux9ssgt5y","hotScore":9745000,"normalizedScore":3800,"source":"kuaishou-hot"},{"title":"美股","url":"https://s.weibo.com/weibo?q=%E7%BE%8E%E8%82%A1&t=31&band_rank=15&Refer=top","hotScore":62743,"normalizedScore":3768,"source":"weibo-search"},{"title":"吴越梅婷同框","url":"https://so.toutiao.com/search?keyword=吴越梅婷同框","hotScore":921969,"normalizedScore":3768,"source":"toutiao-search"},{"title":"想喊一声老崔再没人答应了","url":"https://www.douyin.com/hot/2547370","hotScore":7722396,"normalizedScore":3729,"source":"douyin-hot"},{"title":"委内瑞拉宣布多项措施应对强震灾情","url":"https://www.baidu.com/s?wd=%E5%A7%94%E5%86%85%E7%91%9E%E6%8B%89%E5%AE%A3%E5%B8%83%E5%A4%9A%E9%A1%B9%E6%8E%AA%E6%96%BD%E5%BA%94%E5%AF%B9%E5%BC%BA%E9%9C%87%E7%81%BE%E6%83%85&sa=fyb_news&rsv_dl=fyb_news","hotScore":4575080,"normalizedScore":3667,"source":"baidu-hot"},{"title":"天津高考出分","url":"https://www.zhihu.com/search?q=天津高考出分","hotScore":4,"normalizedScore":3636,"source":"zhihu-search"},{"title":"李小冉说小考教室在拆除中","url":"https://s.weibo.com/weibo?q=%23%E6%9D%8E%E5%B0%8F%E5%86%89%E8%AF%B4%E5%B0%8F%E8%80%83%E6%95%99%E5%AE%A4%E5%9C%A8%E6%8B%86%E9%99%A4%E4%B8%AD%23&t=31&band_rank=26&Refer=top","hotScore":55832,"normalizedScore":3623,"source":"weibo-search"},{"title":"男子徒手抓蛇被咬历经4次抢救","url":"https://so.toutiao.com/search?keyword=男子徒手抓蛇被咬历经4次抢救","hotScore":834232,"normalizedScore":3623,"source":"toutiao-search"},{"title":"鲍尔被交易至森林狼","url":"https://www.kuaishou.com/short-video/3xv662739rrtryg","hotScore":9715000,"normalizedScore":3600,"source":"kuaishou-hot"},{"title":"电影抓特务女儿为妈妈发声","url":"https://www.douyin.com/hot/2546948","hotScore":7719360,"normalizedScore":3559,"source":"douyin-hot"},{"title":"全球第一！中国超算“灵晟”再次登顶","url":"https://www.baidu.com/s?wd=%E5%85%A8%E7%90%83%E7%AC%AC%E4%B8%80%EF%BC%81%E4%B8%AD%E5%9B%BD%E8%B6%85%E7%AE%97%E2%80%9C%E7%81%B5%E6%99%9F%E2%80%9D%E5%86%8D%E6%AC%A1%E7%99%BB%E9%A1%B6&sa=fyb_news&rsv_dl=fyb_news","hotScore":4468751,"normalizedScore":3500,"source":"baidu-hot"},{"title":"恋与深空对不起文学","url":"https://s.weibo.com/weibo?q=%E6%81%8B%E4%B8%8E%E6%B7%B1%E7%A9%BA%E5%AF%B9%E4%B8%8D%E8%B5%B7%E6%96%87%E5%AD%A6&t=31&band_rank=27&Refer=top","hotScore":55824,"normalizedScore":3478,"source":"weibo-search"},{"title":"考生查分后激动到趴地","url":"https://so.toutiao.com/search?keyword=考生查分后激动到趴地","hotScore":754844,"normalizedScore":3478,"source":"toutiao-search"},{"title":"东北大学辽宁往年录取分数线","url":"https://www.kuaishou.com/short-video/3xxr88k3p2zsuyc","hotScore":9695000,"normalizedScore":3400,"source":"kuaishou-hot"},{"title":"吕德华王者语音包上线","url":"https://www.douyin.com/hot/2547601","hotScore":7717408,"normalizedScore":3390,"source":"douyin-hot"},{"title":"江苏高考600分以上40931人","url":"https://s.weibo.com/weibo?q=%23%E6%B1%9F%E8%8B%8F%E9%AB%98%E8%80%83600%E5%88%86%E4%BB%A5%E4%B8%8A40931%E4%BA%BA%23&t=31&band_rank=45&Refer=top","hotScore":55820,"normalizedScore":3333,"source":"weibo-search"},{"title":"张钧甯原名曝光 比艺名还难认","url":"https://so.toutiao.com/search?keyword=张钧甯原名曝光%20比艺名还难认","hotScore":683011,"normalizedScore":3333,"source":"toutiao-search"},{"title":"IBM推出全球首款亚1纳米芯片","url":"https://www.baidu.com/s?wd=IBM%E6%8E%A8%E5%87%BA%E5%85%A8%E7%90%83%E9%A6%96%E6%AC%BE%E4%BA%9A1%E7%BA%B3%E7%B1%B3%E8%8A%AF%E7%89%87&sa=fyb_news&rsv_dl=fyb_news","hotScore":4384455,"normalizedScore":3333,"source":"baidu-hot"},{"title":"像一阵细雨洒落我心底","url":"https://www.douyin.com/hot/2547717","hotScore":7715631,"normalizedScore":3220,"source":"douyin-hot"},{"title":"张嘉慧回应","url":"https://www.kuaishou.com/short-video/3x3n3pau7wzrif2","hotScore":9682000,"normalizedScore":3200,"source":"kuaishou-hot"},{"title":"毒贩为逃跑把婴儿往地上砸","url":"https://s.weibo.com/weibo?q=%23%E6%AF%92%E8%B4%A9%E4%B8%BA%E9%80%83%E8%B7%91%E6%8A%8A%E5%A9%B4%E5%84%BF%E5%BE%80%E5%9C%B0%E4%B8%8A%E7%A0%B8%23&t=31&band_rank=20&Refer=top","hotScore":55810,"normalizedScore":3188,"source":"weibo-search"},{"title":"考生海军招飞被淘汰仍坚持参军报国","url":"https://so.toutiao.com/search?keyword=考生海军招飞被淘汰仍坚持参军报国","hotScore":669857,"normalizedScore":3188,"source":"toutiao-search"},{"title":"日本砸钱洗白二战侵略史","url":"https://www.baidu.com/s?wd=%E6%97%A5%E6%9C%AC%E7%A0%B8%E9%92%B1%E6%B4%97%E7%99%BD%E4%BA%8C%E6%88%98%E4%BE%B5%E7%95%A5%E5%8F%B2&sa=fyb_news&rsv_dl=fyb_news","hotScore":4265948,"normalizedScore":3167,"source":"baidu-hot"},{"title":"叔叔版卓沅加入不齐舞团了","url":"https://www.douyin.com/hot/2547583","hotScore":7715434,"normalizedScore":3051,"source":"douyin-hot"},{"title":"油车真的崩盘了吗","url":"https://s.weibo.com/weibo?q=%23%E6%B2%B9%E8%BD%A6%E7%9C%9F%E7%9A%84%E5%B4%A9%E7%9B%98%E4%BA%86%E5%90%97%23&t=31&band_rank=30&Refer=top","hotScore":55799,"normalizedScore":3043,"source":"weibo-search"},{"title":"超龄打工人放弃养老医保缴费有何后果","url":"https://so.toutiao.com/search?keyword=超龄打工人放弃养老医保缴费有何后果","hotScore":618014,"normalizedScore":3043,"source":"toutiao-search"},{"title":"几内亚总理参观黑灯工厂","url":"https://www.baidu.com/s?wd=%E5%87%A0%E5%86%85%E4%BA%9A%E6%80%BB%E7%90%86%E5%8F%82%E8%A7%82%E9%BB%91%E7%81%AF%E5%B7%A5%E5%8E%82&sa=fyb_news&rsv_dl=fyb_news","hotScore":4168554,"normalizedScore":3000,"source":"baidu-hot"},{"title":"南非1比0韩国","url":"https://www.kuaishou.com/short-video/3xpus8y3n7gpqxe","hotScore":9669000,"normalizedScore":3000,"source":"kuaishou-hot"},{"title":"杨幂豪门嫡长姐","url":"https://s.weibo.com/weibo?q=%23%E6%9D%A8%E5%B9%82%E8%B1%AA%E9%97%A8%E5%AB%A1%E9%95%BF%E5%A7%90%23&t=31&band_rank=16&Refer=top","hotScore":55794,"normalizedScore":2899,"source":"weibo-search"},{"title":"日本荷兰谁能小组第一出线","url":"https://so.toutiao.com/search?keyword=日本荷兰谁能小组第一出线","hotScore":559202,"normalizedScore":2899,"source":"toutiao-search"},{"title":"中年叛逆期的黄毛觉醒","url":"https://www.douyin.com/hot/2547188","hotScore":7713858,"normalizedScore":2881,"source":"douyin-hot"},{"title":"法国家长用“土法”为学校教室降温","url":"https://www.baidu.com/s?wd=%E6%B3%95%E5%9B%BD%E5%AE%B6%E9%95%BF%E7%94%A8%E2%80%9C%E5%9C%9F%E6%B3%95%E2%80%9D%E4%B8%BA%E5%AD%A6%E6%A0%A1%E6%95%99%E5%AE%A4%E9%99%8D%E6%B8%A9&sa=fyb_news&rsv_dl=fyb_news","hotScore":4097036,"normalizedScore":2833,"source":"baidu-hot"},{"title":"中国功夫震撼巴黎街头","url":"https://www.kuaishou.com/short-video/3xjvzr8vx2cwia6","hotScore":9618000,"normalizedScore":2800,"source":"kuaishou-hot"},{"title":"儿子高考502分收到妈妈幸福一巴掌","url":"https://s.weibo.com/weibo?q=%23%E5%84%BF%E5%AD%90%E9%AB%98%E8%80%83502%E5%88%86%E6%94%B6%E5%88%B0%E5%A6%88%E5%A6%88%E5%B9%B8%E7%A6%8F%E4%B8%80%E5%B7%B4%E6%8E%8C%23&t=31&band_rank=32&Refer=top","hotScore":55781,"normalizedScore":2754,"source":"weibo-search"},{"title":"两个儿子过本科线 木工老爸眼眶红了","url":"https://so.toutiao.com/search?keyword=两个儿子过本科线%20木工老爸眼眶红了","hotScore":548433,"normalizedScore":2754,"source":"toutiao-search"},{"title":"福建高考出分","url":"https://www.zhihu.com/search?q=福建高考出分","hotScore":3,"normalizedScore":2727,"source":"zhihu-search"},{"title":"天空灰得像哭过","url":"https://www.douyin.com/hot/2547486","hotScore":7712706,"normalizedScore":2712,"source":"douyin-hot"},{"title":"男子将20万礼金遗落共享单车车篮里","url":"https://www.baidu.com/s?wd=%E7%94%B7%E5%AD%90%E5%B0%8620%E4%B8%87%E7%A4%BC%E9%87%91%E9%81%97%E8%90%BD%E5%85%B1%E4%BA%AB%E5%8D%95%E8%BD%A6%E8%BD%A6%E7%AF%AE%E9%87%8C&sa=fyb_news&rsv_dl=fyb_news","hotScore":4061434,"normalizedScore":2667,"source":"baidu-hot"},{"title":"外网嘲讽韩国队真丢脸","url":"https://s.weibo.com/weibo?q=%23%E5%A4%96%E7%BD%91%E5%98%B2%E8%AE%BD%E9%9F%A9%E5%9B%BD%E9%98%9F%E7%9C%9F%E4%B8%A2%E8%84%B8%23&t=31&band_rank=21&Refer=top","hotScore":55769,"normalizedScore":2609,"source":"weibo-search"},{"title":"媒体：高考放榜看见“沉默的大多数”","url":"https://so.toutiao.com/search?keyword=媒体：高考放榜看见“沉默的大多数”","hotScore":505987,"normalizedScore":2609,"source":"toutiao-search"},{"title":"湖州破获上头电子烟案","url":"https://www.kuaishou.com/short-video/3xnrueixh3qx25m","hotScore":9565000,"normalizedScore":2600,"source":"kuaishou-hot"},{"title":"肖战黄觉双双入围白玉兰奖","url":"https://www.douyin.com/hot/2547702","hotScore":7708986,"normalizedScore":2542,"source":"douyin-hot"},{"title":"苹果大幅涨价 涉及iPad等多个产品","url":"https://www.baidu.com/s?wd=%E8%8B%B9%E6%9E%9C%E5%A4%A7%E5%B9%85%E6%B6%A8%E4%BB%B7+%E6%B6%89%E5%8F%8AiPad%E7%AD%89%E5%A4%9A%E4%B8%AA%E4%BA%A7%E5%93%81&sa=fyb_news&rsv_dl=fyb_news","hotScore":3973754,"normalizedScore":2500,"source":"baidu-hot"},{"title":"恋与深空嘴上认错实际行动全无","url":"https://s.weibo.com/weibo?q=%23%E6%81%8B%E4%B8%8E%E6%B7%B1%E7%A9%BA%E5%98%B4%E4%B8%8A%E8%AE%A4%E9%94%99%E5%AE%9E%E9%99%85%E8%A1%8C%E5%8A%A8%E5%85%A8%E6%97%A0%23&t=31&band_rank=34&Refer=top","hotScore":55767,"normalizedScore":2464,"source":"weibo-search"},{"title":"世界杯生死战前伊朗队被迫滞留机场","url":"https://so.toutiao.com/search?keyword=世界杯生死战前伊朗队被迫滞留机场","hotScore":496242,"normalizedScore":2464,"source":"toutiao-search"},{"title":"日本球员称目标是最终夺冠","url":"https://www.kuaishou.com/short-video/3xvhty22rd6j8cm","hotScore":9541000,"normalizedScore":2400,"source":"kuaishou-hot"},{"title":"姜乘澜夏日伪素颜妆容教学","url":"https://www.douyin.com/hot/2547345","hotScore":7707295,"normalizedScore":2373,"source":"douyin-hot"},{"title":"高考693分荆门学子传授学习经验","url":"https://www.baidu.com/s?wd=%E9%AB%98%E8%80%83693%E5%88%86%E8%8D%86%E9%97%A8%E5%AD%A6%E5%AD%90%E4%BC%A0%E6%8E%88%E5%AD%A6%E4%B9%A0%E7%BB%8F%E9%AA%8C&sa=fyb_news&rsv_dl=fyb_news","hotScore":3898565,"normalizedScore":2333,"source":"baidu-hot"},{"title":"逆水寒手游","url":"https://s.weibo.com/weibo?q=%E9%80%86%E6%B0%B4%E5%AF%92%E6%89%8B%E6%B8%B8&t=31&band_rank=35&Refer=top","hotScore":55759,"normalizedScore":2319,"source":"weibo-search"},{"title":"“C罗骗了全世界”背后的变与不变","url":"https://so.toutiao.com/search?keyword=“C罗骗了全世界”背后的变与不变","hotScore":457836,"normalizedScore":2319,"source":"toutiao-search"},{"title":"用胜利之舞庆祝内马尔回归","url":"https://www.douyin.com/hot/2546661","hotScore":7704681,"normalizedScore":2203,"source":"douyin-hot"},{"title":"武汉一高中出9名高分学霸","url":"https://www.kuaishou.com/short-video/3xgmx9bgiiiu75e","hotScore":9515000,"normalizedScore":2200,"source":"kuaishou-hot"},{"title":"检测机构回应又有纸尿裤检出甲酰胺","url":"https://s.weibo.com/weibo?q=%23%E6%A3%80%E6%B5%8B%E6%9C%BA%E6%9E%84%E5%9B%9E%E5%BA%94%E5%8F%88%E6%9C%89%E7%BA%B8%E5%B0%BF%E8%A3%A4%E6%A3%80%E5%87%BA%E7%94%B2%E9%85%B0%E8%83%BA%23&t=31&band_rank=36&Refer=top","hotScore":55747,"normalizedScore":2174,"source":"weibo-search"},{"title":"韩国主帅：输球非食物中毒就是踢得烂","url":"https://so.toutiao.com/search?keyword=韩国主帅：输球非食物中毒就是踢得烂","hotScore":414267,"normalizedScore":2174,"source":"toutiao-search"},{"title":"印富二代坠亡系被未婚妻和情人推下","url":"https://www.baidu.com/s?wd=%E5%8D%B0%E5%AF%8C%E4%BA%8C%E4%BB%A3%E5%9D%A0%E4%BA%A1%E7%B3%BB%E8%A2%AB%E6%9C%AA%E5%A9%9A%E5%A6%BB%E5%92%8C%E6%83%85%E4%BA%BA%E6%8E%A8%E4%B8%8B&sa=fyb_news&rsv_dl=fyb_news","hotScore":3898101,"normalizedScore":2167,"source":"baidu-hot"},{"title":"王者荣耀6.25正式服更新","url":"https://www.douyin.com/hot/2546556","hotScore":7702388,"normalizedScore":2034,"source":"douyin-hot"},{"title":"王欣瑜vs大坂直美","url":"https://s.weibo.com/weibo?q=%E7%8E%8B%E6%AC%A3%E7%91%9Cvs%E5%A4%A7%E5%9D%82%E7%9B%B4%E7%BE%8E&t=31&band_rank=37&Refer=top","hotScore":55741,"normalizedScore":2029,"source":"weibo-search"},{"title":"山东潍坊一楼盘工地发现墓葬群","url":"https://so.toutiao.com/search?keyword=山东潍坊一楼盘工地发现墓葬群","hotScore":406289,"normalizedScore":2029,"source":"toutiao-search"},{"title":"长沙多部门回应水上野划乱象","url":"https://www.baidu.com/s?wd=%E9%95%BF%E6%B2%99%E5%A4%9A%E9%83%A8%E9%97%A8%E5%9B%9E%E5%BA%94%E6%B0%B4%E4%B8%8A%E9%87%8E%E5%88%92%E4%B9%B1%E8%B1%A1&sa=fyb_news&rsv_dl=fyb_news","hotScore":3799755,"normalizedScore":2000,"source":"baidu-hot"},{"title":"蔡天凤母亲涉诈骗被追逃","url":"https://www.kuaishou.com/short-video/3xddgwrsujdnf6c","hotScore":9492000,"normalizedScore":2000,"source":"kuaishou-hot"},{"title":"中国男排VS比利时男排","url":"https://s.weibo.com/weibo?q=%E4%B8%AD%E5%9B%BD%E7%94%B7%E6%8E%92VS%E6%AF%94%E5%88%A9%E6%97%B6%E7%94%B7%E6%8E%92&t=31&band_rank=38&Refer=top","hotScore":55727,"normalizedScore":1884,"source":"weibo-search"},{"title":"舅舅舅妈带大的孩子高考超常发挥","url":"https://so.toutiao.com/search?keyword=舅舅舅妈带大的孩子高考超常发挥","hotScore":374844,"normalizedScore":1884,"source":"toutiao-search"},{"title":"电影四渡北京首映礼","url":"https://www.douyin.com/hot/2547089","hotScore":7700712,"normalizedScore":1864,"source":"douyin-hot"},{"title":"吴尊发文控诉国泰航空","url":"https://www.baidu.com/s?wd=%E5%90%B4%E5%B0%8A%E5%8F%91%E6%96%87%E6%8E%A7%E8%AF%89%E5%9B%BD%E6%B3%B0%E8%88%AA%E7%A9%BA&sa=fyb_news&rsv_dl=fyb_news","hotScore":3781747,"normalizedScore":1833,"source":"baidu-hot"},{"title":"重庆高考出分","url":"https://www.zhihu.com/search?q=重庆高考出分","hotScore":2,"normalizedScore":1818,"source":"zhihu-search"},{"title":"赵露思闭眼插奶茶挑战","url":"https://www.kuaishou.com/short-video/3xmkhz63wr6x8pq","hotScore":9446000,"normalizedScore":1800,"source":"kuaishou-hot"},{"title":"千香定档节奏","url":"https://s.weibo.com/weibo?q=%23%E5%8D%83%E9%A6%99%E5%AE%9A%E6%A1%A3%E8%8A%82%E5%A5%8F%23&t=31&band_rank=35&Refer=top","hotScore":55715,"normalizedScore":1739,"source":"weibo-search"},{"title":"“中通二代”提前录取中科大少创班","url":"https://so.toutiao.com/search?keyword=“中通二代”提前录取中科大少创班","hotScore":367625,"normalizedScore":1739,"source":"toutiao-search"},{"title":"韩立剑阵拼豆夯爆了","url":"https://www.douyin.com/hot/2546559","hotScore":7700396,"normalizedScore":1695,"source":"douyin-hot"},{"title":"老人时隔80年终于“见到”烈士父兄","url":"https://www.baidu.com/s?wd=%E8%80%81%E4%BA%BA%E6%97%B6%E9%9A%9480%E5%B9%B4%E7%BB%88%E4%BA%8E%E2%80%9C%E8%A7%81%E5%88%B0%E2%80%9D%E7%83%88%E5%A3%AB%E7%88%B6%E5%85%84&sa=fyb_news&rsv_dl=fyb_news","hotScore":3712255,"normalizedScore":1667,"source":"baidu-hot"},{"title":"特朗普再跳YMCA","url":"https://www.kuaishou.com/short-video/3xk4dc5brsmri2a","hotScore":9423000,"normalizedScore":1600,"source":"kuaishou-hot"},{"title":"胡歌白玉兰提名晚宴发言","url":"https://s.weibo.com/weibo?q=%E8%83%A1%E6%AD%8C%E7%99%BD%E7%8E%89%E5%85%B0%E6%8F%90%E5%90%8D%E6%99%9A%E5%AE%B4%E5%8F%91%E8%A8%80&t=31&band_rank=40&Refer=top","hotScore":55711,"normalizedScore":1594,"source":"weibo-search"},{"title":"广东今年普通类考生超41万人上本科线","url":"https://so.toutiao.com/search?keyword=广东今年普通类考生超41万人上本科线","hotScore":339173,"normalizedScore":1594,"source":"toutiao-search"},{"title":"张诗尧为内马尔回归首秀献舞","url":"https://www.douyin.com/hot/2547028","hotScore":7696470,"normalizedScore":1525,"source":"douyin-hot"},{"title":"天天吃外卖等于给身体“埋雷”吗","url":"https://www.baidu.com/s?wd=%E5%A4%A9%E5%A4%A9%E5%90%83%E5%A4%96%E5%8D%96%E7%AD%89%E4%BA%8E%E7%BB%99%E8%BA%AB%E4%BD%93%E2%80%9C%E5%9F%8B%E9%9B%B7%E2%80%9D%E5%90%97&sa=fyb_news&rsv_dl=fyb_news","hotScore":3681422,"normalizedScore":1500,"source":"baidu-hot"},{"title":"江西高考600分以上17122人","url":"https://s.weibo.com/weibo?q=%23%E6%B1%9F%E8%A5%BF%E9%AB%98%E8%80%83600%E5%88%86%E4%BB%A5%E4%B8%8A17122%E4%BA%BA%23&t=31&band_rank=41&Refer=top","hotScore":55700,"normalizedScore":1449,"source":"weibo-search"},{"title":"国防部回应美英法德涉台言论","url":"https://so.toutiao.com/search?keyword=国防部回应美英法德涉台言论","hotScore":306896,"normalizedScore":1449,"source":"toutiao-search"},{"title":"广东男童被踢死生父称愿撤销谅解","url":"https://www.kuaishou.com/short-video/3x2h7gd3ahp3bua","hotScore":9411000,"normalizedScore":1400,"source":"kuaishou-hot"},{"title":"薛珍麒八强赛后发抖音","url":"https://www.douyin.com/hot/2547613","hotScore":7695731,"normalizedScore":1356,"source":"douyin-hot"},{"title":"市监局称山姆涉事凉席甲醛报告合规","url":"https://www.baidu.com/s?wd=%E5%B8%82%E7%9B%91%E5%B1%80%E7%A7%B0%E5%B1%B1%E5%A7%86%E6%B6%89%E4%BA%8B%E5%87%89%E5%B8%AD%E7%94%B2%E9%86%9B%E6%8A%A5%E5%91%8A%E5%90%88%E8%A7%84&sa=fyb_news&rsv_dl=fyb_news","hotScore":3598414,"normalizedScore":1333,"source":"baidu-hot"},{"title":"四川高考600分及以上26697人","url":"https://s.weibo.com/weibo?q=%23%E5%9B%9B%E5%B7%9D%E9%AB%98%E8%80%83600%E5%88%86%E5%8F%8A%E4%BB%A5%E4%B8%8A26697%E4%BA%BA%23&t=31&band_rank=50&Refer=top","hotScore":55695,"normalizedScore":1304,"source":"weibo-search"},{"title":"贵州菜真的会“咬”人","url":"https://so.toutiao.com/search?keyword=贵州菜真的会“咬”人","hotScore":300986,"normalizedScore":1304,"source":"toutiao-search"},{"title":"国防部批日本军国主义","url":"https://www.kuaishou.com/short-video/3xsiij5uauix432","hotScore":9399000,"normalizedScore":1200,"source":"kuaishou-hot"},{"title":"我已爱你爱到不聪明","url":"https://www.douyin.com/hot/2545461","hotScore":7694571,"normalizedScore":1186,"source":"douyin-hot"},{"title":"“试工”即“用工”主张合法吗","url":"https://www.baidu.com/s?wd=%E2%80%9C%E8%AF%95%E5%B7%A5%E2%80%9D%E5%8D%B3%E2%80%9C%E7%94%A8%E5%B7%A5%E2%80%9D%E4%B8%BB%E5%BC%A0%E5%90%88%E6%B3%95%E5%90%97&sa=fyb_news&rsv_dl=fyb_news","hotScore":3524315,"normalizedScore":1167,"source":"baidu-hot"},{"title":"请世界善待只想干好本职任务的人","url":"https://s.weibo.com/weibo?q=%E8%AF%B7%E4%B8%96%E7%95%8C%E5%96%84%E5%BE%85%E5%8F%AA%E6%83%B3%E5%B9%B2%E5%A5%BD%E6%9C%AC%E8%81%8C%E4%BB%BB%E5%8A%A1%E7%9A%84%E4%BA%BA&t=31&band_rank=43&Refer=top","hotScore":55687,"normalizedScore":1159,"source":"weibo-search"},{"title":"女生成绩被屏蔽激动落泪","url":"https://so.toutiao.com/search?keyword=女生成绩被屏蔽激动落泪","hotScore":277691,"normalizedScore":1159,"source":"toutiao-search"},{"title":"高考后该如何重新出发","url":"https://www.douyin.com/hot/2546591","hotScore":7694568,"normalizedScore":1017,"source":"douyin-hot"},{"title":"女孩感冒服药离世暴露基层药店乱象","url":"https://s.weibo.com/weibo?q=%23%E5%A5%B3%E5%AD%A9%E6%84%9F%E5%86%92%E6%9C%8D%E8%8D%AF%E7%A6%BB%E4%B8%96%E6%9A%B4%E9%9C%B2%E5%9F%BA%E5%B1%82%E8%8D%AF%E5%BA%97%E4%B9%B1%E8%B1%A1%23&t=31&band_rank=44&Refer=top","hotScore":55676,"normalizedScore":1014,"source":"weibo-search"},{"title":"女子吐槽路边摊烤串太贵声音都变形了","url":"https://so.toutiao.com/search?keyword=女子吐槽路边摊烤串太贵声音都变形了","hotScore":272343,"normalizedScore":1014,"source":"toutiao-search"},{"title":"钓友暴雨夜钓到118斤巨型青鱼","url":"https://www.baidu.com/s?wd=%E9%92%93%E5%8F%8B%E6%9A%B4%E9%9B%A8%E5%A4%9C%E9%92%93%E5%88%B0118%E6%96%A4%E5%B7%A8%E5%9E%8B%E9%9D%92%E9%B1%BC&sa=fyb_news&rsv_dl=fyb_news","hotScore":3425752,"normalizedScore":1000,"source":"baidu-hot"},{"title":"三亚考生高考分数未达预期","url":"https://www.kuaishou.com/short-video/3xsfi99376c4hmc","hotScore":9391000,"normalizedScore":1000,"source":"kuaishou-hot"},{"title":"黑龙江高考出分","url":"https://www.zhihu.com/search?q=黑龙江高考出分","hotScore":1,"normalizedScore":909,"source":"zhihu-search"},{"title":"多地再被曝冻货偏航事件","url":"https://s.weibo.com/weibo?q=%23%E5%A4%9A%E5%9C%B0%E5%86%8D%E8%A2%AB%E6%9B%9D%E5%86%BB%E8%B4%A7%E5%81%8F%E8%88%AA%E4%BA%8B%E4%BB%B6%23&t=31&band_rank=22&Refer=top","hotScore":55669,"normalizedScore":870,"source":"weibo-search"},{"title":"谢霆锋王菲到达西安","url":"https://so.toutiao.com/search?keyword=谢霆锋王菲到达西安","hotScore":251265,"normalizedScore":870,"source":"toutiao-search"},{"title":"当室友教我男生拍照姿势","url":"https://www.douyin.com/hot/2546646","hotScore":7686915,"normalizedScore":847,"source":"douyin-hot"},{"title":"名记：黄蜂将鲍尔交易至森林狼","url":"https://www.baidu.com/s?wd=%E5%90%8D%E8%AE%B0%EF%BC%9A%E9%BB%84%E8%9C%82%E5%B0%86%E9%B2%8D%E5%B0%94%E4%BA%A4%E6%98%93%E8%87%B3%E6%A3%AE%E6%9E%97%E7%8B%BC&sa=fyb_news&rsv_dl=fyb_news","hotScore":3403922,"normalizedScore":833,"source":"baidu-hot"},{"title":"库拉索vs科特迪瓦","url":"https://www.kuaishou.com/short-video/3xhdxct9hafc4v2","hotScore":9385000,"normalizedScore":800,"source":"kuaishou-hot"},{"title":"失联13岁男孩落入坑洞疑靠喝水存活","url":"https://s.weibo.com/weibo?q=%23%E5%A4%B1%E8%81%9413%E5%B2%81%E7%94%B7%E5%AD%A9%E8%90%BD%E5%85%A5%E5%9D%91%E6%B4%9E%E7%96%91%E9%9D%A0%E5%96%9D%E6%B0%B4%E5%AD%98%E6%B4%BB%23&t=31&band_rank=39&Refer=top","hotScore":55658,"normalizedScore":725,"source":"weibo-search"},{"title":"上海电视节白玉兰奖荣耀之夜群星璀璨","url":"https://so.toutiao.com/search?keyword=上海电视节白玉兰奖荣耀之夜群星璀璨","hotScore":246426,"normalizedScore":725,"source":"toutiao-search"},{"title":"飞舞吧忍者西装男团","url":"https://www.douyin.com/hot/2547589","hotScore":7684714,"normalizedScore":678,"source":"douyin-hot"},{"title":"女孩639分想报西安交大 曾因病休学","url":"https://www.baidu.com/s?wd=%E5%A5%B3%E5%AD%A9639%E5%88%86%E6%83%B3%E6%8A%A5%E8%A5%BF%E5%AE%89%E4%BA%A4%E5%A4%A7+%E6%9B%BE%E5%9B%A0%E7%97%85%E4%BC%91%E5%AD%A6&sa=fyb_news&rsv_dl=fyb_news","hotScore":3309903,"normalizedScore":667,"source":"baidu-hot"},{"title":"珠海外卖店被查7人被刑拘","url":"https://www.kuaishou.com/short-video/3xugxnvv26bcegu","hotScore":9377000,"normalizedScore":600,"source":"kuaishou-hot"},{"title":"孙颖莎兼项赛程密集","url":"https://s.weibo.com/weibo?q=%E5%AD%99%E9%A2%96%E8%8E%8E%E5%85%BC%E9%A1%B9%E8%B5%9B%E7%A8%8B%E5%AF%86%E9%9B%86&t=31&band_rank=47&Refer=top","hotScore":55646,"normalizedScore":580,"source":"weibo-search"},{"title":"乌男特工假扮“寂寞主妇”套俄军情报","url":"https://so.toutiao.com/search?keyword=乌男特工假扮“寂寞主妇”套俄军情报","hotScore":222976,"normalizedScore":580,"source":"toutiao-search"},{"title":"九屏发色帮我决定夏天染什么","url":"https://www.douyin.com/hot/2547607","hotScore":7674943,"normalizedScore":508,"source":"douyin-hot"},{"title":"缉毒警提醒离开视线的饮品不要喝","url":"https://www.baidu.com/s?wd=%E7%BC%89%E6%AF%92%E8%AD%A6%E6%8F%90%E9%86%92%E7%A6%BB%E5%BC%80%E8%A7%86%E7%BA%BF%E7%9A%84%E9%A5%AE%E5%93%81%E4%B8%8D%E8%A6%81%E5%96%9D&sa=fyb_news&rsv_dl=fyb_news","hotScore":3245073,"normalizedScore":500,"source":"baidu-hot"},{"title":"腾讯到白玉兰只干一件事","url":"https://s.weibo.com/weibo?q=%23%E8%85%BE%E8%AE%AF%E5%88%B0%E7%99%BD%E7%8E%89%E5%85%B0%E5%8F%AA%E5%B9%B2%E4%B8%80%E4%BB%B6%E4%BA%8B%23&t=31&band_rank=29&Refer=top","hotScore":55636,"normalizedScore":435,"source":"weibo-search"},{"title":"四川一考生考出666分好成绩","url":"https://so.toutiao.com/search?keyword=四川一考生考出666分好成绩","hotScore":205719,"normalizedScore":435,"source":"toutiao-search"},{"title":"孟子义百花杀好美的恶女","url":"https://www.kuaishou.com/short-video/3xakji3rpb7qafi","hotScore":9369000,"normalizedScore":400,"source":"kuaishou-hot"},{"title":"黄明昊机智张顶级建模自拍","url":"https://www.douyin.com/hot/2547545","hotScore":7672695,"normalizedScore":339,"source":"douyin-hot"},{"title":"中国足协：将启用“捂嘴红牌”等新规","url":"https://www.baidu.com/s?wd=%E4%B8%AD%E5%9B%BD%E8%B6%B3%E5%8D%8F%EF%BC%9A%E5%B0%86%E5%90%AF%E7%94%A8%E2%80%9C%E6%8D%82%E5%98%B4%E7%BA%A2%E7%89%8C%E2%80%9D%E7%AD%89%E6%96%B0%E8%A7%84&sa=fyb_news&rsv_dl=fyb_news","hotScore":3143184,"normalizedScore":333,"source":"baidu-hot"},{"title":"长鑫存储年底产能有望超越美光","url":"https://s.weibo.com/weibo?q=%E9%95%BF%E9%91%AB%E5%AD%98%E5%82%A8%E5%B9%B4%E5%BA%95%E4%BA%A7%E8%83%BD%E6%9C%89%E6%9C%9B%E8%B6%85%E8%B6%8A%E7%BE%8E%E5%85%89&t=31&band_rank=34&Refer=top","hotScore":55630,"normalizedScore":290,"source":"weibo-search"},{"title":"南非足球的“回响”","url":"https://so.toutiao.com/search?keyword=南非足球的“回响”","hotScore":201757,"normalizedScore":290,"source":"toutiao-search"},{"title":"女生高考前十淡定继续睡觉","url":"https://www.kuaishou.com/short-video/3xrqvcawts5jj49","hotScore":9360000,"normalizedScore":200,"source":"kuaishou-hot"},{"title":"C罗的魔性贯口也来了","url":"https://www.douyin.com/hot/2545992","hotScore":7672568,"normalizedScore":169,"source":"douyin-hot"},{"title":"“渝见小面”发帖征名","url":"https://www.baidu.com/s?wd=%E2%80%9C%E6%B8%9D%E8%A7%81%E5%B0%8F%E9%9D%A2%E2%80%9D%E5%8F%91%E5%B8%96%E5%BE%81%E5%90%8D&sa=fyb_news&rsv_dl=fyb_news","hotScore":3112169,"normalizedScore":167,"source":"baidu-hot"},{"title":"零跑D99价格","url":"https://s.weibo.com/weibo?q=%23%E9%9B%B6%E8%B7%91D99%E4%BB%B7%E6%A0%BC%23&t=31&band_rank=50&Refer=top","hotScore":55617,"normalizedScore":145,"source":"weibo-search"},{"title":"拉梅洛·鲍尔被交易至森林狼","url":"https://so.toutiao.com/search?keyword=拉梅洛·鲍尔被交易至森林狼","hotScore":149465,"normalizedScore":145,"source":"toutiao-search"}]